Workbook

Sheet Instruções e Resumo
A1: SESC PAULISTA — PROJETO COSMOCHÃO (v12.0)
A3: PLANILHA DE COTAÇÃO DE MATERIAIS, INSUMOS E SERVIÇOS
A5: ORIENTAÇÕES PARA PREENCHIMENTO E COTAÇÃO:
A6: 1. Esta planilha contém o levantamento quantitativo detalhado dos materiais, insumos e serviços da exposição CosmoChão.
A7: 2. NOTA DA v12.0: Adicionado fornecimento de vale-alimentação para a fase de galpão (+20,0 pessoa-dias / R$ 600,00).
A8: 3. Os fornecedores devem preencher EXCLUSIVAMENTE a coluna 'Custo Unitário (R$)' [células destacadas em AZUL CLARO].
A9: 4. Os valores totais por item, sub-totais por disciplina e o valor total geral são calculados AUTOMATICAMENTE.
A10: 5. No campo 'Observações do Fornecedor', informe a marca oferecida, prazos de entrega ou eventuais ressalvas técnicas.
A11: 6. O campo Status indica a origem do dado no projeto: EXPLÍCITO, DERIVADO, PENDENTE, DIVERGENTE, FECHADO ou REFORMADO.
A13: RESUMO CONSOLIDADO DA COTAÇÃO
A15: Indicador | B15: Valor / Status
A16: TOTAL GERAL COTADO (R$) | B16: ='Resumo por Disciplina'!D13 + 'Mão de Obra e Serviços'!G21 -> 197096.48
A17: Total de Itens Mapeados | B17: =COUNTA('Cotação de Materiais'!A4:A44) + COUNTA('Mão de Obra e Serviços'!A4:A20) -> 56
A18: Disciplinas Atendidas | B18: 10
A19: Legenda de Preenchimento | B19: Azul Claro = Campo Editável pelo Fornecedor | Verde = Cálculo Automático
A21: LEGENDA DOS STATUS DO LEVANTAMENTO
A22: Status | B22: Descrição / Conceito
A23: EXPLÍCITO | B23: Dado quantitativo ou especificação presente diretamente no memorial / desenho.
A24: DERIVADO | B24: Dado calculado matematicamente a partir de parâmetros das fontes (ex: consumo de tinta/ignífugo).
A25: PENDENTE | B25: Informação que depende de definição executiva, medição in loco ou cotação detalhada.
A26: DIVERGENTE | B26: Conflito identificado entre diferentes memoriais do projeto (ex: massas de lastro).
A27: FECHADO | B27: Item com cotação de mercado confirmada e fechada.
A28: REFORMADO | B28: Elemento existente no acervo do SESC que passará por tratamento, pintura ou restauração.

Sheet Cotação de Materiais
A1: COTAÇÃO DE MATERIAIS E INSUMOS — SESC PAULISTA (COSMOCHÃO v12.0)
A3: Item | B3: Disciplina | C3: Material / Elemento | D3: Especificação Técnica | E3: Quantidade | F3: Unidade | G3: Custo Unitário (R$) | H3: Custo Total (R$) | I3: Status | J3: Aplicação / Local | K3: Observações do Fornecedor / Marca
A4: MAT-01 | B4: Marcenaria e Cenotecnia | C4: Chapas de MDF Comum 18mm | D4: Chapa de MDF Comum / Cru 18mm (2,75 x 1,85 m) — Ignifugação posterior c/ CKC-2020 | E4: 302 | F4: m² | G4: 51.68 | H4: =IFERROR(E4*G4, 0) -> 15607.36 | I4: EXPLÍCITO | J4: Painéis P01-P07, PR01 (48,5m²), PR02 (48,5m²) e bases M06-M18, M22, M26, M27 | K4: Leo Madeiras R$ 262,90/chapa = R$ 51,68/m² (60 chapas)
A5: MAT-02 | B5: Marcenaria e Cenotecnia | C5: Chapas de MDF Comum 10mm | D5: Chapa de MDF Comum / Cru 10mm — Ignifugação posterior c/ CKC-2020 | E5: 45 | F5: m² | G5: 33.42 | H5: =IFERROR(E5*G5, 0) -> 1503.9 | I5: PENDENTE | J5: Estações M19-M21, M24, Carrinho M23 e Caixa M25 | K5: MDF Comum 10mm — R$ 170,00/chapa = R$ 33,42/m² (~9 chapas)
A6: MAT-03 | B6: Marcenaria e Cenotecnia | C6: Chapas de MDF Comum 6mm e 15mm | D6: Chapas de MDF Comum / Cru 6mm (R$ 118,90) e 15mm (R$ 218,90) — Média ponderada R$ 33,20/m² | E6: 30 | F6: m² | G6: 33.2 | H6: =IFERROR(E6*G6, 0) -> 996 | I6: PENDENTE | J6: Tampo da Mesa M01 e bases escultóricas M02-M05 | K6: 15m² de 6mm (~3 chapas) + 15m² de 15mm (~3 chapas)
A7: MAT-04 | B7: Marcenaria e Cenotecnia | C7: Pontaletes de Madeira | D7: Seção de 5 x 5 cm em madeira para estrutura interna | E7: 180 | F7: m | G7: 18 | H7: =IFERROR(E7*G7, 0) -> 3240 | I7: DERIVADO | J7: Estrutura interna de P01-P06, PR01, PR02, M02-M05, M13 | K7: Sarrafo de pinus/cedrinho 5x5cm (R$ 18,00/m)
A8: MET-01 | B8: Serralheria e Estruturas Metálicas | C8: Perfis Tubulares S03 | D8: Tubo de aço 50 x 50 x 5,0 mm (7,07 kg/m) | E8: 47 | F8: m | G8: 70 | H8: =IFERROR(E8*G8, 0) -> 3290 | I8: PENDENTE | J8: Estrutura metálica interna da Base M27 (Obra Solange Pessoa) | K8: 47m de tubo = 332,29 kg de aço
A9: MET-02 | B9: Serralheria e Estruturas Metálicas | C9: Tubos de Aço Estrutural | D9: Tubo de aço 50 x 50 x 3,0 mm (4,43 kg/m) | E9: 25 | F9: m | G9: 45.85 | H9: =IFERROR(E9*G9, 0) -> 1146.25 | I9: DERIVADO | J9: 4 Barracudas S01 (P05) e 4 Barracudas Piso-Teto (Obra Davi) | K9: 25m de tubo = 110,75 kg de aço (Barra 6m R$ 275,08)
A10: MET-03 | B10: Serralheria e Estruturas Metálicas | C10: Molduras Metálicas S01 | D10: Metalon 50 x 50 mm (37 x 93 cm) c/ sapata e contrapesos | E10: 2 | F10: un | G10: 450 | H10: =IFERROR(E10*G10, 0) -> 900 | I10: EXPLÍCITO | J10: Caixas de marcenaria S01 / Reforço P05 (Obra Davi) | K10: Conjunto de 2 molduras S01
A11: MET-04 | B11: Serralheria e Estruturas Metálicas | C11: Mão-Francesa Metálica S02 | D11: Tubo 50 x 50 mm e chapa maciça 3 mm (40 x 40 cm) | E11: 2 | F11: un | G11: 280 | H11: =IFERROR(E11*G11, 0) -> 560 | I11: EXPLÍCITO | J11: Sustentação do barco no Painel P05 | K11: Conjunto de 2 mãos-francesas S02
A12: MET-05 | B12: Serralheria e Estruturas Metálicas | C12: Placas de Apoio de Aço | D12: Chapa de aço 100 x 100 x 5 mm c/ barra roscada e contraporca | E12: 8 | F12: un | G12: 65 | H12: =IFERROR(E12*G12, 0) -> 520 | I12: EXPLÍCITO | J12: Extremidades das 4 barracudas piso-teto (Obra Davi) | K12: Placas de fixação superior e inferior
A13: MET-06 | B13: Serralheria e Estruturas Metálicas | C13: Perfis de Alumínio de Canto | D13: Perfil de sobrepor 16 x 16 mm (L = 180 cm) para LED c/ difusor | E13: 2 | F13: un | G13: 65 | H13: =IFERROR(E13*G13, 0) -> 130 | I13: PENDENTE | J13: Nichos superior e inferior da Vitrine M22 (Francisco Brennand) | K13: Perfil de alumínio 16x16mm + difusor PMMA
A14: ELE-01 | B14: Elétrica e Iluminação | C14: Quadro QDLF-Temporário | D14: Caixa de sobrepor 3F+N+T (220/127V), barramento 80A | E14: 1 | F14: un | G14: 1850 | H14: =IFERROR(E14*G14, 0) -> 1850 | I14: PENDENTE | J14: Quadro provisório de distribuição no 5º andar | K14: Quadro provisório completo com barramento 80A
A15: ELE-02 | B15: Elétrica e Iluminação | C15: Cabo Alimentador Geral | D15: Cabo flexível Afumex 0,6/1kV 90°C (3#10 + N10 + PE10 mm²) | E15: 45 | F15: m | G15: 14.67 | H15: =IFERROR(E15*G15, 0) -> 660.15 | I15: EXPLÍCITO | J15: Interligação do QG-N-05 PV ao QDLF-Temporário | K15: Cabo Prysmian Afumex 10 mm² (R$ 14,67/m)
... A44: MOB-03 | B44: Elementos Reformados | C44: Mesa Tátil | D44: Repintura acrílica na cor Terra Roxa c/ vinil de recorte | E44: 1 | F44: un | G44: 180 | H44: =IFERROR(E44*G44, 0) -> 180 | I44: REFORMADO | J44: Espaço Educativo | K44: Repintura e vinil de recorte
A45: TOTAL GERAL | G45: TOTAL: | H45: =SUM(H4:H44) -> 78534.481

Sheet Resumo por Disciplina
A1: RESUMO DE CUSTOS POR DISCIPLINA — SESC PAULISTA (v12.0)
A3: Item | B3: Disciplina | C3: Qtd. Itens Mapeados | D3: Valor Total Cotado (R$) | E3: % do Total Geral
A4: 01 | B4: Marcenaria e Cenotecnia | C4: =COUNTIF('Cotação de Materiais'!B4:B44, B4) -> 4 | D4: =SUMIF('Cotação de Materiais'!B4:B44, B4, 'Cotação de Materiais'!H4:H44) -> 21347.26 | E4: =D4/$D$13 -> 0.27182022
A5: 02 | B5: Serralheria e Estruturas Metálicas | C5: =COUNTIF('Cotação de Materiais'!B4:B44, B5) -> 6 | D5: =SUMIF('Cotação de Materiais'!B4:B44, B5, 'Cotação de Materiais'!H4:H44) -> 6546.25 | E5: =D5/$D$13 -> 0.083355106
A6: 03 | B6: Elétrica e Iluminação | C6: =COUNTIF('Cotação de Materiais'!B4:B44, B6) -> 8 | D6: =SUMIF('Cotação de Materiais'!B4:B44, B6, 'Cotação de Materiais'!H4:H44) -> 9176.262 | E6: =D6/$D$13 -> 0.11684373
A7: 04 | B7: Pintura e Acabamentos | C7: =COUNTIF('Cotação de Materiais'!B4:B44, B7) -> 3 | D7: =SUMIF('Cotação de Materiais'!B4:B44, B7, 'Cotação de Materiais'!H4:H44) -> 6741.02 | E7: =D7/$D$13 -> 0.085835163
A8: 05 | B8: Vidros e Acrílicos | C8: =COUNTIF('Cotação de Materiais'!B4:B44, B8) -> 1 | D8: =SUMIF('Cotação de Materiais'!B4:B44, B8, 'Cotação de Materiais'!H4:H44) -> 1376.71 | E8: =D8/$D$13 -> 0.017530007
A9: 06 | B9: Comunicação Visual | C9: =COUNTIF('Cotação de Materiais'!B4:B44, B9) -> 3 | D9: =SUMIF('Cotação de Materiais'!B4:B44, B9, 'Cotação de Materiais'!H4:H44) -> 13681.459 | E9: =D9/$D$13 -> 0.17420958
A10: 07 | B10: Segurança Contra Incêndio | C10: =COUNTIF('Cotação de Materiais'!B4:B44, B10) -> 5 | D10: =SUMIF('Cotação de Materiais'!B4:B44, B10, 'Cotação de Materiais'!H4:H44) -> 10636.92 | E10: =D10/$D$13 -> 0.13544267
A11: 08 | B11: Ferragens e Ancoragens | C11: =COUNTIF('Cotação de Materiais'!B4:B44, B11) -> 4 | D11: =SUMIF('Cotação de Materiais'!B4:B44, B11, 'Cotação de Materiais'!H4:H44) -> 7048.6 | E11: =D11/$D$13 -> 0.089751659
A12: 09 | B12: Elementos Reformados | C12: =COUNTIF('Cotação de Materiais'!B4:B44, B12) -> 5 | D12: =SUMIF('Cotação de Materiais'!B4:B44, B12, 'Cotação de Materiais'!H4:H44) -> 1980 | E12: =D12/$D$13 -> 0.025211856
A13: TOTAL | B13: TODAS AS DISCIPLINAS | C13: =SUM(C4:C12) -> 39 | D13: =SUM(D4:D12) -> 78534.481 | E13: =SUM(E4:E12) -> 1

Sheet Mão de Obra e Serviços
A1: COTAÇÃO E REGISTRO DE MÃO DE OBRA, SERVIÇOS E LOGÍSTICA — SESC PAULISTA (COSMOCHÃO v12.0)
A3: Item | B3: Categoria / Função | C3: Especificação / Escopo | D3: Quantidade Est. | E3: Unidade | F3: Valor Unitário (R$) | G3: Custo Total (R$) | H3: Status
A4: MO-01 | B4: Pintura por empreita — mão de obra | C4: Pintura acrílica de painéis novos (P01–P07, PR01, PR02), existentes e móveis (Preço Fechado / Empreita c/ supervisor embutido) | D4: 559.22 | E4: m² | F4: 50 | G4: =IFERROR(D4*F4, 0) -> 27961 | H4: EXPLÍCITO
A5: MO-02A | B5: Marceneiro / Cenotécnico (Galpão) | C5: Equipe de 4 marceneiros alocada por 5 dias de pré-fabricação no galpão (4 p x 5 dias) | D5: 20 | E5: pessoa-dia | F5: 250 | G5: =IFERROR(D5*F5, 0) -> 5000 | H5: EXPLÍCITO
A6: MO-02B | B6: Marceneiro / Cenotécnico (SESC) | C6: Equipe de 8 marceneiros alocada nos 20 dias de montagem no SESC (8 p x 20 dias) | D6: 160 | E6: pessoa-dia | F6: 270 | G6: =IFERROR(D6*F6, 0) -> 43200 | H6: EXPLÍCITO
A7: MO-03 | B7: Ajudante, carga e descarga | C7: 4 ajudantes nos 2 primeiros dias de montagem no SESC (8 p-d) e no dia da desmontagem (4 p-d) | D7: 10 | E7: pessoa-dia | F7: 130 | G7: =IFERROR(D7*F7, 0) -> 1300 | H7: EXPLÍCITO
A8: MO-04 | B8: Equipe de Limpeza | C8: 3 pessoas alocadas nos últimos 3 dias de montagem no SESC para limpeza fina pré-abertura | D8: 9 | E8: pessoa-dia | F8: 100 | G8: =IFERROR(D8*F8, 0) -> 900 | H8: EXPLÍCITO
A9: MO-05 | B9: Serralheiro — EMPREITA | C9: Montagem e ajustes de estruturas metálicas S01, S02, S03 e barracudas (Preço Fechado / Empreita) | D9: 1 | E9: cj | F9: 5000 | G9: =IFERROR(D9*F9, 0) -> 5000 | H9: FECHADO
A10: MO-06 | B10: Supervisor de Montagem | C10: 1 supervisor dedicado durante toda a montagem no SESC (20 dias); supervisão de pintura e elétrica embutida nas empreitas | D10: 20 | E10: dia | F10: 300 | G10: =IFERROR(D10*F10, 0) -> 6000 | H10: EXPLÍCITO
A11: MO-07 | B11: Tapeceiro | C11: Serviços de tapeçaria, estofamento e revestimentos têxteis | D11: 5 | E11: pessoa-dia | F11: 1 | G11: =IFERROR(D11*F11, 0) -> 5 | H11: PENDENTE
A12: MO-08 | B12: Adesivador | C12: 2 pessoas alocadas por 3 dias para aplicação de insulfilm e vinil de recorte | D12: 6 | E12: pessoa-dia | F12: 250 | G12: =IFERROR(D12*F12, 0) -> 1500 | H12: EXPLÍCITO
A13: MO-09 | B13: Eletricista — EMPREITA | C13: Instalação do QDLF-Temporário, fiação, iluminação LED M01/M22 (Preço Fechado / Empreita c/ supervisor embutido) | D13: 1 | E13: cj | F13: 7000 | G13: =IFERROR(D13*F13, 0) -> 7000 | H13: FECHADO
A14: MO-10 | B14: Equipe de Manutenção Expositiva | C14: Visitas quinzenais durante os 8 meses de exposição com equipe dedicada de 2 pessoas (18 visitas x 2 p) | D14: 36 | E14: pessoa-dia | F14: 200 | G14: =IFERROR(D14*F14, 0) -> 7200 | H14: DERIVADO
A15: LOG-01A | B15: Alimentação (Campo SESC) | C15: Vale-alimentação para equipe operacional durante atuação em campo no SESC (212 pessoa-dias de campo) | D15: 212 | E15: pessoa-dia | F15: 28 | G15: =IFERROR(D15*F15, 0) -> 5936 | H15: DERIVADO
... A20: ENG-01 | B20: ART — referência interna | C20: Anotação de Responsabilidade Técnica de engenharia civil/mecânica | D20: 1 | E20: registro | F20: 1500 | G20: =IFERROR(D20*F20, 0) -> 1500 | H20: EXPLÍCITO
B21: TOTAL DE MÃO DE OBRA, SERVIÇOS E LOGÍSTICA | G21: =SUM(G4:G20) -> 118562

Sheet Dashboard Executivo
A1: PAINEL EXECUTIVO — SESC PAULISTA | COSMOCHÃO
R2: Disciplina | S2: Valor | U2: Componente | V2: Valor
A3: Base v12.0 | Fabricação em galpão: 5 dias úteis | Montagem SESC: 28/10 a 16/11 | Reserva técnica: 17/11 | Abertura: 18/11/2026 | R3: Marcenaria e Cenotecnia | S3: ='Resumo por Disciplina'!D4 -> 21347.26 | U3: Materiais e Insumos | V3: ='Cotação de Materiais'!H45 -> 78534.481
R4: Serralheria e Estruturas Metálicas | S4: ='Resumo por Disciplina'!D5 -> 6546.25 | U4: M.O. + Serviços + Logística | V4: ='Mão de Obra e Serviços'!G21 -> 118562
A5: CUSTO TOTAL GERAL | F5: MATERIAIS E INSUMOS | J5: M.O. + SERVIÇOS + LOGÍSTICA | N5: ITENS PENDENTES DE DEFINIÇÃO | R5: Elétrica e Iluminação | S5: ='Resumo por Disciplina'!D6 -> 9176.262
R6: Pintura e Acabamentos | S6: ='Resumo por Disciplina'!D7 -> 6741.02
A7: ="R$ "&TEXT('Instruções e Resumo'!B16,"#,##0.00") -> R$ 197,096.48 | F7: ="R$ "&TEXT('Cotação de Materiais'!H45,"#,##0.00") -> R$ 78,534.48 | J7: ="R$ "&TEXT('Mão de Obra e Serviços'!G21,"#,##0.00") -> R$ 118,562.00 | N7: =COUNTIF('Cotação de Materiais'!I4:I44,"PENDENTE")+COUNTIF('Mão de Obra e Serviços'!H4:H20,"PENDENTE") -> 6 | R7: Vidros e Acrílicos | S7: ='Resumo por Disciplina'!D8 -> 1376.71
R8: Comunicação Visual | S8: ='Resumo por Disciplina'!D9 -> 13681.459
R9: Segurança Contra Incêndio | S9: ='Resumo por Disciplina'!D10 -> 10636.92
A10: GALPÃO — EQUIPE | F10: GALPÃO — DURAÇÃO | J10: SESC — EQUIPE PRINCIPAL | N10: MARGEM DE SEGURANÇA | R10: Ferragens e Ancoragens | S10: ='Resumo por Disciplina'!D11 -> 7048.6
R11: Elementos Reformados | S11: ='Resumo por Disciplina'!D12 -> 1980
A12: =4 -> 4 | F12: =5 -> 5 | J12: =8 -> 8 | N12: =1 -> 1
A15: CUSTOS POR DISCIPLINA | J15: COMPOSIÇÃO DO CUSTO
A34: CRONOGRAMA EXECUTIVO — VISÃO GERAL
A35: Fase | D35: Período | F35: Equipe | I35: Objetivo
A36: Pré-fabricação no galpão | D36: 21–27/10 | F36: 4 marceneiros | I36: 5 dias úteis de fabricação; preparação e ignifugação antes da entrada no SESC.
A37: Entrada + implantação pesada | D37: 28–30/10 | F37: 8 marc. + 4 ajud. (28–29) | I37: Descarga, distribuição, locação e início das estruturas/painéis.
A38: Montagem pesada | D38: 31/10–05/11 | F38: 8 marc. + serralheria | I38: Painéis, estruturas principais, P05, PR01/PR02 e fechamentos.
A39: Montagem técnica / especiais | D39: 06–10/11 | F39: 8 marc. + elétrica/serralheria | I39: M22, M27, bases especiais, ancoragens e fechamentos técnicos.
A40: Mobiliário + elétrica + CV | D40: 11–13/11 | F40: 8 marc. + eletricista + 2 adesiv. | I40: Mobiliário, acessibilidade, LED, eletrofita, insulfilm e vinil.
A41: Acabamentos e correções | D41: 14–16/11 | F41: 8 marc. + pintura + limpeza | I41: Retoques, testes, alinhamentos e limpeza progressiva.
A42: Reserva / entrega técnica | D42: 17/11 | F42: Equipe mínima + limpeza | I42: Punch list, correções finais e liberação.
A43: Abertura da exposição | D43: 18/11 | F43: — | I43: Abertura ao público.
A45: MATERIAIS DE MAIOR IMPACTO — BASE ATUAL | J45: STATUS DA COTAÇÃO / PENDÊNCIAS
A46: Item | B46: Material | E46: Disciplina | G46: Custo Total | J46: Status | M46: Quantidade
A47: ='Cotação de Materiais'!A31 -> SEG-01 | B47: ='Cotação de Materiais'!C31 -> Retardante de Chamas CKC-2020 | E47: ='Cotação de Materiais'!B31 -> Segurança Contra Incêndio | G47: ="R$ "&TEXT('Cotação de Materiais'!H31,"#,##0.00") -> R$ 8,760.00 | J47: PENDENTE | M47: =COUNTIF('Cotação de Materiais'!I4:I44,"PENDENTE")+COUNTIF('Mão de Obra e Serviços'!H4:H20,"PENDENTE") -> 6
A48: ='Cotação de Materiais'!A4 -> MAT-01 | B48: ='Cotação de Materiais'!C4 -> Chapas de MDF Comum 18mm | E48: ='Cotação de Materiais'!B4 -> Marcenaria e Cenotecnia | G48: ="R$ "&TEXT('Cotação de Materiais'!H4,"#,##0.00") -> R$ 15,607.36 | J48: FECHADO | M48: =COUNTIF('Cotação de Materiais'!I4:I44,"FECHADO")+COUNTIF('Mão de Obra e Serviços'!H4:H20,"FECHADO") -> 6
A49: ='Cotação de Materiais'!A25 -> VID-01 | B49: ='Cotação de Materiais'!C25 -> Vidro Laminado M01 | E49: ='Cotação de Materiais'!B25 -> Vidros e Acrílicos | G49: ="R$ "&TEXT('Cotação de Materiais'!H25,"#,##0.00") -> R$ 1,376.71 | J49: EXPLÍCITO | M49: =COUNTIF('Cotação de Materiais'!I4:I44,"EXPLÍCITO")+COUNTIF('Mão de Obra e Serviços'!H4:H20,"EXPLÍCITO") -> 28
A50: ='Cotação de Materiais'!A28 -> CV-01 | B50: ='Cotação de Materiais'!C28 -> Aplicação de Película Refl. Prata-Bronze 05 | E50: ='Cotação de Materiais'!B28 -> Comunicação Visual | G50: ="R$ "&TEXT('Cotação de Materiais'!H28,"#,##0.00") -> R$ 8,209.46 | J50: DERIVADO | M50: =COUNTIF('Cotação de Materiais'!I4:I44,"DERIVADO")+COUNTIF('Mão de Obra e Serviços'!H4:H20,"DERIVADO") -> 11
A51: ='Cotação de Materiais'!A39 -> FER-04 | B51: ='Cotação de Materiais'!C39 -> Lastros de Estabilização | E51: ='Cotação de Materiais'!B39 -> Ferragens e Ancoragens | G51: ="R$ "&TEXT('Cotação de Materiais'!H39,"#,##0.00") -> R$ 4,800.00 | J51: REFORMADO | M51: =COUNTIF('Cotação de Materiais'!I4:I44,"REFORMADO")+COUNTIF('Mão de Obra e Serviços'!H4:H20,"REFORMADO") -> 5
A52: ='Cotação de Materiais'!A17 -> ELE-04 | B52: ='Cotação de Materiais'!C17 -> Cabos PP Antichama | E52: ='Cotação de Materiais'!B17 -> Elétrica e Iluminação | G52: ="R$ "&TEXT('Cotação de Materiais'!H17,"#,##0.00") -> R$ 3,987.50
A53: ='Cotação de Materiais'!A24 -> TIN-03 | B53: ='Cotação de Materiais'!C24 -> Tinta Acrílica Branca | E53: ='Cotação de Materiais'!B24 -> Pintura e Acabamentos | G53: ="R$ "&TEXT('Cotação de Materiais'!H24,"#,##0.00") -> R$ 3,695.52 | J53: Itens pendentes atuais: MDF 10mm, MDF 6/15mm, tubo S03, perfil LED, QDLF temporário e tapeceiro. Revisar antes do fechamento final.
A54: ='Cotação de Materiais'!A29 -> CV-02 | B54: ='Cotação de Materiais'!C29 -> Remoção de Película Anterior | E54: ='Cotação de Materiais'!B29 -> Comunicação Visual | G54: ="R$ "&TEXT('Cotação de Materiais'!H29,"#,##0.00") -> R$ 3,429.12
A56: Detalhamento: custos item a item na aba “Cotação de Materiais”; mão de obra, serviços e logística na aba “Mão de Obra e Serviços”; cronograma diário na aba “Cronograma Operacional”.

Sheet Cronograma Operacional
A1: CRONOGRAMA OPERACIONAL — COSMOCHÃO | FABRICAÇÃO + MONTAGEM SESC
A3: Planejamento-base: 4 marceneiros no galpão por 5 dias úteis; 8 marceneiros na montagem principal do SESC; 17/11 reservado para entrega técnica.
A5: Código | B5: Fase | C5: Início | D5: Fim | E5: Duração | F5: Equipe principal | G5: Objetivo / observação | H5: 46316 | I5: 46317 | J5: 46318 | K5: 46319 | L5: 46320 | M5: 46321 | N5: 46322 | O5: 46323 | P5: 46324 | Q5: 46325 | R5: 46326 | S5: 46327 | T5: 46328 | U5: 46329 | V5: 46330 | W5: 46331 | X5: 46332 | Y5: 46333 | Z5: 46334 | AA5: 46335 | AB5: 46336 | AC5: 46337 | AD5: 46338 | AE5: 46339 | AF5: 46340 | AG5: 46341 | AH5: 46342 | AI5: 46343 | AJ5: 46344
H6: QUA | I6: QUI | J6: SEX | K6: SÁB | L6: DOM | M6: SEG | N6: TER | O6: QUA | P6: QUI | Q6: SEX | R6: SÁB | S6: DOM | T6: SEG | U6: TER | V6: QUA | W6: QUI | X6: SEX | Y6: SÁB | Z6: DOM | AA6: SEG | AB6: TER | AC6: QUA | AD6: QUI | AE6: SEX | AF6: SÁB | AG6: DOM | AH6: SEG | AI6: TER | AJ6: QUA
A7: GAL-01 | B7: Pré-fabricação em Galpão | C7: 46316 | D7: 46322 | E7: 5 dias úteis | F7: 4 marceneiros | G7: Pré-fabricação, preparação dos módulos e ignifugação antes da entrada no SESC. | H7: ■ | I7: ■ | J7: ■ | M7: ■ | N7: ■
A8: SESC-01 | B8: Entrada + Implantação Pesada | C8: 46323 | D8: 46325 | E8: 3 dias | F8: 8 marc. + 4 ajud. (28–29) + supervisor | G8: Descarga, distribuição, locação e início das estruturas/painéis. | O8: ■ | P8: ■ | Q8: ■
A9: SESC-02 | B9: Montagem Pesada | C9: 46326 | D9: 46331 | E9: 6 dias | F9: 8 marc. + serralheria + supervisor | G9: Painéis, estruturas principais, P05, PR01/PR02 e fechamentos. | R9: ■ | S9: ■ | T9: ■ | U9: ■ | V9: ■ | W9: ■
A10: SESC-03 | B10: Montagem Técnica / Especiais | C10: 46332 | D10: 46336 | E10: 5 dias | F10: 8 marc. + elétrica/serralheria + supervisor | G10: M22, M27, bases especiais, ancoragens e fechamentos técnicos. | X10: ■ | Y10: ■ | Z10: ■ | AA10: ■ | AB10: ■
A11: SESC-04 | B11: Mobiliário + Elétrica + Comunicação | C11: 46337 | D11: 46339 | E11: 3 dias | F11: 8 marc. + eletricista + 2 adesivadores + supervisor | G11: Mobiliário, acessibilidade, LED, eletrofita, insulfilm e vinil. | AC11: ■ | AD11: ■ | AE11: ■
A12: SESC-05 | B12: Acabamentos + Correções | C12: 46340 | D12: 46342 | E12: 3 dias | F12: 8 marc. + pintura + limpeza + supervisor | G12: Retoques, alinhamentos, testes e limpeza progressiva. | AF12: ■ | AG12: ■ | AH12: ■
A13: SESC-06 | B13: Reserva / Entrega Técnica | C13: 46343 | D13: 46343 | E13: 1 dia | F13: Equipe mínima + 3 limpeza | G13: Punch list, correções finais, limpeza fina e liberação. | AI13: ■
A14: MARCO | B14: Abertura ao Público | C14: 46344 | D14: 46344 | E14: Marco | F14: — | G14: Abertura oficial da exposição. | AJ14: ■
A17: MAPA DE EQUIPES E CUSTOS DIRETAMENTE RELACIONADOS À MONTAGEM
A18: Item | B18: Equipe / Função | C18: Quantidade | D18: Unidade | E18: Valor Unitário | F18: Custo Total | G18: Observação
A19: MO-02A | B19: Marceneiros — Galpão | C19: ='Mão de Obra e Serviços'!D5 -> 20 | D19: ='Mão de Obra e Serviços'!E5 -> pessoa-dia | E19: ="R$ "&TEXT('Mão de Obra e Serviços'!F5,"#,##0.00") -> R$ 250.00 | F19: ="R$ "&TEXT('Mão de Obra e Serviços'!G5,"#,##0.00") -> R$ 5,000.00 | G19: 5 dias × 4 pessoas
A20: MO-02B | B20: Marceneiros — SESC | C20: ='Mão de Obra e Serviços'!D6 -> 160 | D20: ='Mão de Obra e Serviços'!E6 -> pessoa-dia | E20: ="R$ "&TEXT('Mão de Obra e Serviços'!F6,"#,##0.00") -> R$ 270.00 | F20: ="R$ "&TEXT('Mão de Obra e Serviços'!G6,"#,##0.00") -> R$ 43,200.00 | G20: 20 dias × 8 pessoas
A21: MO-03 | B21: Ajudantes / carga e descarga | C21: ='Mão de Obra e Serviços'!D7 -> 10 | D21: ='Mão de Obra e Serviços'!E7 -> pessoa-dia | E21: ="R$ "&TEXT('Mão de Obra e Serviços'!F7,"#,##0.00") -> R$ 130.00 | F21: ="R$ "&TEXT('Mão de Obra e Serviços'!G7,"#,##0.00") -> R$ 1,300.00 | G21: 8 p-d na montagem + 4 p-d na desmontagem
A22: MO-04 | B22: Limpeza fina | C22: ='Mão de Obra e Serviços'!D8 -> 9 | D22: ='Mão de Obra e Serviços'!E8 -> pessoa-dia | E22: ="R$ "&TEXT('Mão de Obra e Serviços'!F8,"#,##0.00") -> R$ 100.00 | F22: ="R$ "&TEXT('Mão de Obra e Serviços'!G8,"#,##0.00") -> R$ 900.00 | G22: 3 pessoas × 3 dias
A23: MO-05 | B23: Serralheria — empreita | C23: ='Mão de Obra e Serviços'!D9 -> 1 | D23: ='Mão de Obra e Serviços'!E9 -> cj | E23: ="R$ "&TEXT('Mão de Obra e Serviços'!F9,"#,##0.00") -> R$ 5,000.00 | F23: ="R$ "&TEXT('Mão de Obra e Serviços'!G9,"#,##0.00") -> R$ 5,000.00 | G23: Preço fechado
A24: MO-06 | B24: Supervisor de montagem | C24: ='Mão de Obra e Serviços'!D10 -> 20 | D24: ='Mão de Obra e Serviços'!E10 -> dia | E24: ="R$ "&TEXT('Mão de Obra e Serviços'!F10,"#,##0.00") -> R$ 300.00 | F24: ="R$ "&TEXT('Mão de Obra e Serviços'!G10,"#,##0.00") -> R$ 6,000.00 | G24: 20 dias
A25: MO-07 | B25: Tapeceiro | C25: ='Mão de Obra e Serviços'!D11 -> 5 | D25: ='Mão de Obra e Serviços'!E11 -> pessoa-dia | E25: ="R$ "&TEXT('Mão de Obra e Serviços'!F11,"#,##0.00") -> R$ 1.00 | F25: ="R$ "&TEXT('Mão de Obra e Serviços'!G11,"#,##0.00") -> R$ 5.00 | G25: Quantidade ainda pendente
A26: MO-08 | B26: Adesivadores | C26: ='Mão de Obra e Serviços'!D12 -> 6 | D26: ='Mão de Obra e Serviços'!E12 -> pessoa-dia | E26: ="R$ "&TEXT('Mão de Obra e Serviços'!F12,"#,##0.00") -> R$ 250.00 | F26: ="R$ "&TEXT('Mão de Obra e Serviços'!G12,"#,##0.00") -> R$ 1,500.00 | G26: 2 pessoas × 3 dias
A27: MO-09 | B27: Eletricista — empreita | C27: ='Mão de Obra e Serviços'!D13 -> 1 | D27: ='Mão de Obra e Serviços'!E13 -> cj | E27: ="R$ "&TEXT('Mão de Obra e Serviços'!F13,"#,##0.00") -> R$ 7,000.00 | F27: ="R$ "&TEXT('Mão de Obra e Serviços'!G13,"#,##0.00") -> R$ 7,000.00 | G27: Preço fechado
A29: Premissas do planejamento: o período de 28/10 a 16/11 utiliza os 20 dias corridos previstos para a equipe principal de 8 marceneiros. O dia 17/11 fica preservado como contingência/entrega técnica. A pré-fabricação de 21 a 27/10 considera 5 dias úteis (21, 22, 23, 26 e 27/10). Horários noturnos/restrições operacionais continuam sujeitos ao alinhamento com o SESC.
A33: Fonte operacional: cronograma do projeto + parâmetros de equipe da planilha v12.0. Custos permanecem vinculados às abas-base para atualização automática.
