Workbook

Sheet Instruções e Resumo
A1: SESC PAULISTA — PROJETO COSMOCHÃO (v12.0)
A3: PLANILHA DE COTAÇÃO DE MATERIAIS, INSUMOS E SERVIÇOS
A5: ORIENTAÇÕES PARA PREENCHIMENTO E COTAÇÃO:
A6: 1. Esta planilha contém o levantamento quantitativo detalhado dos materiais, insumos e serviços da exposição CosmoChão.
A7: 2. NOTA DA v12.0: Adicionado fornecimento de vale-alimentação para a fase de galpão (+20,0 pessoa-dias / R$ 600,00).
A8: 3. Os fornecedores devem preencher EXCLUSIVAMENTE a coluna 'Custo Unitário (R$)' [células destacadas em AZUL CLARO].
A9: 4. Os valores totais por item, sub-totais por disciplina e o valor total geral são calculados AUTOMATICAMENTE.
A10: 5. No campo 'Observações do Fornecedor', informe a marca oferecida, prazos de entrega ou eventuais ressalvas técnicas.
A11: 6. O campo Status indica a origem do dado no projeto: EXPLÍCITO, DERIVADO, PENDENTE, DIVERGENTE, FECHADO ou REFORMADO.
A13: RESUMO CONSOLIDADO DA COTAÇÃO
A15: Indicador | B15: Valor / Status
A16: TOTAL GERAL COTADO (R$) | B16: ='Resumo por Disciplina'!D13 + 'Mão de Obra e Serviços'!G21 -> 197096.48
A17: Total de Itens Mapeados | B17: =COUNTA('Cotação de Materiais'!A4:A44) + COUNTA('Mão de Obra e Serviços'!A4:A20) -> 56
A18: Disciplinas Atendidas | B18: 10
A19: Legenda de Preenchimento | B19: Azul Claro = Campo Editável pelo Fornecedor | Verde = Cálculo Automático
A21: LEGENDA DOS STATUS DO LEVANTAMENTO
A22: Status | B22: Descrição / Conceito
A23: EXPLÍCITO | B23: Dado quantitativo ou especificação presente diretamente no memorial / desenho.
A24: DERIVADO | B24: Dado calculado matematicamente a partir de parâmetros das fontes (ex: consumo de tinta/ignífugo).
A25: PENDENTE | B25: Informação que depende de definição executiva, medição in loco ou cotação detalhada.
A26: DIVERGENTE | B26: Conflito identificado entre diferentes memoriais do projeto (ex: massas de lastro).
A27: FECHADO | B27: Item com cotação de mercado confirmada e fechada.
A28: REFORMADO | B28: Elemento existente no acervo do SESC que passará por tratamento, pintura ou restauração.
A31: COMO GERAR O PREÇO E O ANEXO III (v15)
A32: 1. Preencha os custos nas abas Cotação de Materiais e Mão de Obra e Serviços (azul claro), como sempre.
A33: 2. Na aba Rateio Anexo, diga para qual item do Anexo vai cada linha de custo (Item Anexo + Base). Frete, ART, supervisão = INDIRETO.
A34: 3. Confira: coluna "Rateio no Anexo (%)" das abas de custo tem que dar 100% (vermelho = falta ratear).
A35: 4. Na aba Precificação, digite o PREÇO FINAL DESEJADO e o % da sobra que vai pro material (padrão 50%). A MO compensa sozinha.
A36: 5. A aba Anexo III sai pronta, com unitários em centavos e total fechando no preço. Itens "SEM CUSTO" em vermelho = falta linha de custo.
A37: 6. Preencher a oficial do Sesc: na aba Anexo III, coluna M mostra cada bloco (ex.: F10:G13). Copie o bloco e cole na mesma faixa da oficial com COLAR ESPECIAL > VALORES. Nunca colar normal (cria vínculo externo).

Sheet Precificação
A1: PRECIFICAÇÃO — CUSTO → PREÇO DE VENDA → ANEXO III
A2: Azul = você digita | Verde = calcula sozinho | Amarelo = resultado principal
A3: Parâmetro | B3: Valor | C3: Como funciona
A4: Custo de material (R$) | B4: ='Cotação de Materiais'!H45 -> 78534.481 | C4: Soma da aba Cotação de Materiais.
A5: Custo de MO + serviços + logística (R$) | B5: ='Mão de Obra e Serviços'!G21 -> 118562 | C5: Soma da aba Mão de Obra e Serviços (inclui frete, alimentação, ART).
A6: CUSTO TOTAL (R$) | B6: =B4+B5 -> 197096.48 | C6: Motor de partida: tudo sai daqui.
A8: PREÇO FINAL DESEJADO (R$) | B8: 339500 | C8: Digite o preço que você quer fechar. O Anexo III fecha exatamente nesse valor.
A9: Sobra sobre o custo (R$) | B9: =B8-B6 -> 142403.52 | C9: Preço desejado − custo total. É isso que vai ser dividido entre material e MO.
A10: Markup total sobre o custo | B10: =IF(B6=0,0,B8/B6-1) -> 0.72250665 | C10: Quanto o preço está acima do custo, no geral.
A12: % DA SOBRA QUE VAI PRO MATERIAL | B12: 0.5 | C12: Começa em 50%. Achou o material caro? Baixe aqui — a MO compensa sozinha e o total não muda.
A13: % da sobra que vai pra MO | B13: =1-B12 -> 0.5 | C13: Automático: 100% − o que foi pro material.
A15: Acréscimo no material (R$) | B15: =B9*B12 -> 71201.759
A16: Acréscimo na MO (R$) | B16: =B9*B13 -> 71201.759
A17: Acréscimo % sobre o custo de material | B17: =IF(B4=0,0,B15/B4) -> 0.90663054 | C17: Esse % é aplicado no custo de material de TODOS os itens.
A18: Acréscimo % sobre o custo de MO | B18: =IF(B5=0,0,B16/B5) -> 0.60054452 | C18: Esse % é aplicado no custo de MO de TODOS os itens.
A19: Fator material | B19: =1+B17 -> 1.9066305 | C19: Custo de material × fator = venda de material.
A20: Fator MO | B20: =1+B18 -> 1.6005445 | C20: Custo de MO × fator = venda de MO.
A22: Venda de material (R$) | B22: =B4*B19 -> 149736.24
A23: Venda de MO (R$) | B23: =B5*B20 -> 189763.76
A24: VENDA TOTAL (R$) | B24: =B22+B23 -> 339500 | C24: Tem que ser igual ao preço desejado.
A26: Item que absorve os centavos (qtd = 1) | B26: A.7.5 | C26: Arredondar unitário pra centavo gera sobra de centavos. Ela vai pra MO deste item. Use um item com quantidade 1.
A27: Centavos de arredondamento (R$) | B27: ='Anexo III'!F3 -> -0.42 | C27: Normalmente centavos. Vermelho (mais de R$ 5) = confira o rateio.
A28: Total do Anexo III (R$) | B28: ='Anexo III'!K3 -> 339500
A29: Anexo III fecha no preço desejado? | B29: =IF(AND(ABS(B28-B8)<0.005,B30=0),"SIM","NÃO — confira") -> SIM | C29: SIM só se o total bate E todo o custo chegou nos itens do Anexo.
A30: Custo que NÃO chegou nos itens do Anexo (R$) | B30: =ROUND(B6-'Anexo III'!R3,2) -> 0 | C30: Tem que ser zero. Se não for: linha de custo sem destino ou com item errado na aba Rateio Anexo (coluna M e colunas "Rateio no Anexo" em vermelho).
A31: Itens do Anexo SEM CUSTO | B31: =COUNTIF('Anexo III'!L8:L400,"SEM CUSTO*") -> 2 | C31: Itens do Sesc sem nenhuma linha de custo: vão sair com preço zero. Crie a linha de custo e rateie.
A32: Qtd do item de centavos | B32: =IFERROR(INDEX('Anexo III'!E8:E400,MATCH(B26,'Anexo III'!B8:B400,0)),"NÃO ACHEI") -> 1 | C32: Tem que ser 1.
A34: POR DISCIPLINA (mesmo % em todas; o total fecha no preço desejado)
A35: Disciplina | B35: Custo material | C35: Custo MO | D35: Custo total | E35: % acrésc. material | F35: Venda material | G35: % acrésc. MO | H35: Venda MO | I35: Venda total | J35: % da venda
A36: Marcenaria e Cenotecnia | B36: =SUMIF('Cotação de Materiais'!$B$4:$B$200,A36,'Cotação de Materiais'!$H$4:$H$200) -> 21347.26 | C36: =SUMIF('Mão de Obra e Serviços'!$I$4:$I$200,A36,'Mão de Obra e Serviços'!$G$4:$G$200) -> 48200 | D36: =B36+C36 -> 69547.26 | E36: =$B$17 -> 0.90663054 | F36: =B36*$B$19 -> 40701.338 | G36: =$B$18 -> 0.60054452 | H36: =C36*$B$20 -> 77146.246 | I36: =F36+H36 -> 117847.58 | J36: =IF($I$47=0,0,I36/$I$47) -> 0.34712101
A37: Serralheria e Estruturas Metálicas | B37: =SUMIF('Cotação de Materiais'!$B$4:$B$200,A37,'Cotação de Materiais'!$H$4:$H$200) -> 6546.25 | C37: =SUMIF('Mão de Obra e Serviços'!$I$4:$I$200,A37,'Mão de Obra e Serviços'!$G$4:$G$200) -> 5000 | D37: =B37+C37 -> 11546.25 | E37: =$B$17 -> 0.90663054 | F37: =B37*$B$19 -> 12481.28 | G37: =$B$18 -> 0.60054452 | H37: =C37*$B$20 -> 8002.7226 | I37: =F37+H37 -> 20484.003 | J37: =IF($I$47=0,0,I37/$I$47) -> 0.060335796
A38: Elétrica e Iluminação | B38: =SUMIF('Cotação de Materiais'!$B$4:$B$200,A38,'Cotação de Materiais'!$H$4:$H$200) -> 9176.262 | C38: =SUMIF('Mão de Obra e Serviços'!$I$4:$I$200,A38,'Mão de Obra e Serviços'!$G$4:$G$200) -> 7000 | D38: =B38+C38 -> 16176.262 | E38: =$B$17 -> 0.90663054 | F38: =B38*$B$19 -> 17495.741 | G38: =$B$18 -> 0.60054452 | H38: =C38*$B$20 -> 11203.812 | I38: =F38+H38 -> 28699.553 | J38: =IF($I$47=0,0,I38/$I$47) -> 0.084534766
A39: Pintura e Acabamentos | B39: =SUMIF('Cotação de Materiais'!$B$4:$B$200,A39,'Cotação de Materiais'!$H$4:$H$200) -> 6741.02 | C39: =SUMIF('Mão de Obra e Serviços'!$I$4:$I$200,A39,'Mão de Obra e Serviços'!$G$4:$G$200) -> 27961 | D39: =B39+C39 -> 34702.02 | E39: =$B$17 -> 0.90663054 | F39: =B39*$B$19 -> 12852.635 | G39: =$B$18 -> 0.60054452 | H39: =C39*$B$20 -> 44752.825 | I39: =F39+H39 -> 57605.46 | J39: =IF($I$47=0,0,I39/$I$47) -> 0.16967735
A40: Vidros e Acrílicos | B40: =SUMIF('Cotação de Materiais'!$B$4:$B$200,A40,'Cotação de Materiais'!$H$4:$H$200) -> 1376.71 | C40: =SUMIF('Mão de Obra e Serviços'!$I$4:$I$200,A40,'Mão de Obra e Serviços'!$G$4:$G$200) -> 0 | D40: =B40+C40 -> 1376.71 | E40: =$B$17 -> 0.90663054 | F40: =B40*$B$19 -> 2624.8773 | G40: =$B$18 -> 0.60054452 | H40: =C40*$B$20 -> 0 | I40: =F40+H40 -> 2624.8773 | J40: =IF($I$47=0,0,I40/$I$47) -> 0.0077315975
A41: Comunicação Visual | B41: =SUMIF('Cotação de Materiais'!$B$4:$B$200,A41,'Cotação de Materiais'!$H$4:$H$200) -> 13681.459 | C41: =SUMIF('Mão de Obra e Serviços'!$I$4:$I$200,A41,'Mão de Obra e Serviços'!$G$4:$G$200) -> 1500 | D41: =B41+C41 -> 15181.459 | E41: =$B$17 -> 0.90663054 | F41: =B41*$B$19 -> 26085.488 | G41: =$B$18 -> 0.60054452 | H41: =C41*$B$20 -> 2400.8168 | I41: =F41+H41 -> 28486.305 | J41: =IF($I$47=0,0,I41/$I$47) -> 0.083906641
A42: Segurança Contra Incêndio | B42: =SUMIF('Cotação de Materiais'!$B$4:$B$200,A42,'Cotação de Materiais'!$H$4:$H$200) -> 10636.92 | C42: =SUMIF('Mão de Obra e Serviços'!$I$4:$I$200,A42,'Mão de Obra e Serviços'!$G$4:$G$200) -> 0 | D42: =B42+C42 -> 10636.92 | E42: =$B$17 -> 0.90663054 | F42: =B42*$B$19 -> 20280.677 | G42: =$B$18 -> 0.60054452 | H42: =C42*$B$20 -> 0 | I42: =F42+H42 -> 20280.677 | J42: =IF($I$47=0,0,I42/$I$47) -> 0.059736897
A43: Ferragens e Ancoragens | B43: =SUMIF('Cotação de Materiais'!$B$4:$B$200,A43,'Cotação de Materiais'!$H$4:$H$200) -> 7048.6 | C43: =SUMIF('Mão de Obra e Serviços'!$I$4:$I$200,A43,'Mão de Obra e Serviços'!$G$4:$G$200) -> 0 | D43: =B43+C43 -> 7048.6 | E43: =$B$17 -> 0.90663054 | F43: =B43*$B$19 -> 13439.076 | G43: =$B$18 -> 0.60054452 | H43: =C43*$B$20 -> 0 | I43: =F43+H43 -> 13439.076 | J43: =IF($I$47=0,0,I43/$I$47) -> 0.039584907
A44: Elementos Reformados | B44: =SUMIF('Cotação de Materiais'!$B$4:$B$200,A44,'Cotação de Materiais'!$H$4:$H$200) -> 1980 | C44: =SUMIF('Mão de Obra e Serviços'!$I$4:$I$200,A44,'Mão de Obra e Serviços'!$G$4:$G$200) -> 0 | D44: =B44+C44 -> 1980 | E44: =$B$17 -> 0.90663054 | F44: =B44*$B$19 -> 3775.1285 | G44: =$B$18 -> 0.60054452 | H44: =C44*$B$20 -> 0 | I44: =F44+H44 -> 3775.1285 | J44: =IF($I$47=0,0,I44/$I$47) -> 0.011119672
A45: Serviços Gerais e Manutenção | B45: =SUMIF('Cotação de Materiais'!$B$4:$B$200,A45,'Cotação de Materiais'!$H$4:$H$200) -> 0 | C45: =SUMIF('Mão de Obra e Serviços'!$I$4:$I$200,A45,'Mão de Obra e Serviços'!$G$4:$G$200) -> 8100 | D45: =B45+C45 -> 8100 | E45: =$B$17 -> 0.90663054 | F45: =B45*$B$19 -> 0 | G45: =$B$18 -> 0.60054452 | H45: =C45*$B$20 -> 12964.411 | I45: =F45+H45 -> 12964.411 | J45: =IF($I$47=0,0,I45/$I$47) -> 0.038186776
A46: Logística e Indiretos | B46: =SUMIF('Cotação de Materiais'!$B$4:$B$200,A46,'Cotação de Materiais'!$H$4:$H$200) -> 0 | C46: =SUMIF('Mão de Obra e Serviços'!$I$4:$I$200,A46,'Mão de Obra e Serviços'!$G$4:$G$200) -> 20801 | D46: =B46+C46 -> 20801 | E46: =$B$17 -> 0.90663054 | F46: =B46*$B$19 -> 0 | G46: =$B$18 -> 0.60054452 | H46: =C46*$B$20 -> 33292.927 | I46: =F46+H46 -> 33292.927 | J46: =IF($I$47=0,0,I46/$I$47) -> 0.098064585
A47: TOTAL | B47: =SUM(B36:B46) -> 78534.481 | C47: =SUM(C36:C46) -> 118562 | D47: =SUM(D36:D46) -> 197096.48 | F47: =SUM(F36:F46) -> 149736.24 | H47: =SUM(H36:H46) -> 189763.76 | I47: =SUM(I36:I46) -> 339500 | J47: =SUM(J36:J46) -> 1
A48: Custo sem disciplina (tem que ser zero) | D48: =ROUND(B6-D47,2) -> 0

Sheet Cotação de Materiais
A1: COTAÇÃO DE MATERIAIS E INSUMOS — SESC PAULISTA (COSMOCHÃO v12.0)
A3: Item | B3: Disciplina | C3: Material / Elemento | D3: Especificação Técnica | E3: Quantidade | F3: Unidade | G3: Custo Unitário (R$) | H3: Custo Total (R$) | I3: Status | J3: Aplicação / Local | K3: Observações do Fornecedor / Marca | L3: Rateio no Anexo (%)
A4: MAT-01 | B4: Marcenaria e Cenotecnia | C4: Chapas de MDF Comum 18mm | D4: Chapa de MDF Comum / Cru 18mm (2,75 x 1,85 m) — Ignifugação posterior c/ CKC-2020 | E4: 302 | F4: m² | G4: 51.68 | H4: =IFERROR(E4*G4, 0) -> 15607.36 | I4: EXPLÍCITO | J4: Painéis P01-P07, PR01 (48,5m²), PR02 (48,5m²) e bases M06-M18, M22, M26, M27 | K4: Leo Madeiras R$ 262,90/chapa = R$ 51,68/m² (60 chapas) | L4: =SUMIFS('Rateio Anexo'!$H$6:$H$600,'Rateio Anexo'!$A$6:$A$600,A4,'Rateio Anexo'!$M$6:$M$600,"") -> 1
A5: MAT-02 | B5: Marcenaria e Cenotecnia | C5: Chapas de MDF Comum 10mm | D5: Chapa de MDF Comum / Cru 10mm — Ignifugação posterior c/ CKC-2020 | E5: 45 | F5: m² | G5: 33.42 | H5: =IFERROR(E5*G5, 0) -> 1503.9 | I5: PENDENTE | J5: Estações M19-M21, M24, Carrinho M23 e Caixa M25 | K5: MDF Comum 10mm — R$ 170,00/chapa = R$ 33,42/m² (~9 chapas) | L5: =SUMIFS('Rateio Anexo'!$H$6:$H$600,'Rateio Anexo'!$A$6:$A$600,A5,'Rateio Anexo'!$M$6:$M$600,"") -> 1
A6: MAT-03 | B6: Marcenaria e Cenotecnia | C6: Chapas de MDF Comum 6mm e 15mm | D6: Chapas de MDF Comum / Cru 6mm (R$ 118,90) e 15mm (R$ 218,90) — Média ponderada R$ 33,20/m² | E6: 30 | F6: m² | G6: 33.2 | H6: =IFERROR(E6*G6, 0) -> 996 | I6: PENDENTE | J6: Tampo da Mesa M01 e bases escultóricas M02-M05 | K6: 15m² de 6mm (~3 chapas) + 15m² de 15mm (~3 chapas) | L6: =SUMIFS('Rateio Anexo'!$H$6:$H$600,'Rateio Anexo'!$A$6:$A$600,A6,'Rateio Anexo'!$M$6:$M$600,"") -> 1
A7: MAT-04 | B7: Marcenaria e Cenotecnia | C7: Pontaletes de Madeira | D7: Seção de 5 x 5 cm em madeira para estrutura interna | E7: 180 | F7: m | G7: 18 | H7: =IFERROR(E7*G7, 0) -> 3240 | I7: DERIVADO | J7: Estrutura interna de P01-P06, PR01, PR02, M02-M05, M13 | K7: Sarrafo de pinus/cedrinho 5x5cm (R$ 18,00/m) | L7: =SUMIFS('Rateio Anexo'!$H$6:$H$600,'Rateio Anexo'!$A$6:$A$600,A7,'Rateio Anexo'!$M$6:$M$600,"") -> 1
A8: MET-01 | B8: Serralheria e Estruturas Metálicas | C8: Perfis Tubulares S03 | D8: Tubo de aço 50 x 50 x 5,0 mm (7,07 kg/m) | E8: 47 | F8: m | G8: 70 | H8: =IFERROR(E8*G8, 0) -> 3290 | I8: PENDENTE | J8: Estrutura metálica interna da Base M27 (Obra Solange Pessoa) | K8: 47m de tubo = 332,29 kg de aço | L8: =SUMIFS('Rateio Anexo'!$H$6:$H$600,'Rateio Anexo'!$A$6:$A$600,A8,'Rateio Anexo'!$M$6:$M$600,"") -> 1
A9: MET-02 | B9: Serralheria e Estruturas Metálicas | C9: Tubos de Aço Estrutural | D9: Tubo de aço 50 x 50 x 3,0 mm (4,43 kg/m) | E9: 25 | F9: m | G9: 45.85 | H9: =IFERROR(E9*G9, 0) -> 1146.25 | I9: DERIVADO | J9: 4 Barracudas S01 (P05) e 4 Barracudas Piso-Teto (Obra Davi) | K9: 25m de tubo = 110,75 kg de aço (Barra 6m R$ 275,08) | L9: =SUMIFS('Rateio Anexo'!$H$6:$H$600,'Rateio Anexo'!$A$6:$A$600,A9,'Rateio Anexo'!$M$6:$M$600,"") -> 1
A10: MET-03 | B10: Serralheria e Estruturas Metálicas | C10: Molduras Metálicas S01 | D10: Metalon 50 x 50 mm (37 x 93 cm) c/ sapata e contrapesos | E10: 2 | F10: un | G10: 450 | H10: =IFERROR(E10*G10, 0) -> 900 | I10: EXPLÍCITO | J10: Caixas de marcenaria S01 / Reforço P05 (Obra Davi) | K10: Conjunto de 2 molduras S01 | L10: =SUMIFS('Rateio Anexo'!$H$6:$H$600,'Rateio Anexo'!$A$6:$A$600,A10,'Rateio Anexo'!$M$6:$M$600,"") -> 1
A11: MET-04 | B11: Serralheria e Estruturas Metálicas | C11: Mão-Francesa Metálica S02 | D11: Tubo 50 x 50 mm e chapa maciça 3 mm (40 x 40 cm) | E11: 2 | F11: un | G11: 280 | H11: =IFERROR(E11*G11, 0) -> 560 | I11: EXPLÍCITO | J11: Sustentação do barco no Painel P05 | K11: Conjunto de 2 mãos-francesas S02 | L11: =SUMIFS('Rateio Anexo'!$H$6:$H$600,'Rateio Anexo'!$A$6:$A$600,A11,'Rateio Anexo'!$M$6:$M$600,"") -> 1
A12: MET-05 | B12: Serralheria e Estruturas Metálicas | C12: Placas de Apoio de Aço | D12: Chapa de aço 100 x 100 x 5 mm c/ barra roscada e contraporca | E12: 8 | F12: un | G12: 65 | H12: =IFERROR(E12*G12, 0) -> 520 | I12: EXPLÍCITO | J12: Extremidades das 4 barracudas piso-teto (Obra Davi) | K12: Placas de fixação superior e inferior | L12: =SUMIFS('Rateio Anexo'!$H$6:$H$600,'Rateio Anexo'!$A$6:$A$600,A12,'Rateio Anexo'!$M$6:$M$600,"") -> 1
A13: MET-06 | B13: Serralheria e Estruturas Metálicas | C13: Perfis de Alumínio de Canto | D13: Perfil de sobrepor 16 x 16 mm (L = 180 cm) para LED c/ difusor | E13: 2 | F13: un | G13: 65 | H13: =IFERROR(E13*G13, 0) -> 130 | I13: PENDENTE | J13: Nichos superior e inferior da Vitrine M22 (Francisco Brennand) | K13: Perfil de alumínio 16x16mm + difusor PMMA | L13: =SUMIFS('Rateio Anexo'!$H$6:$H$600,'Rateio Anexo'!$A$6:$A$600,A13,'Rateio Anexo'!$M$6:$M$600,"") -> 1
A14: ELE-01 | B14: Elétrica e Iluminação | C14: Quadro QDLF-Temporário | D14: Caixa de sobrepor 3F+N+T (220/127V), barramento 80A | E14: 1 | F14: un | G14: 1850 | H14: =IFERROR(E14*G14, 0) -> 1850 | I14: PENDENTE | J14: Quadro provisório de distribuição no 5º andar | K14: Quadro provisório completo com barramento 80A | L14: =SUMIFS('Rateio Anexo'!$H$6:$H$600,'Rateio Anexo'!$A$6:$A$600,A14,'Rateio Anexo'!$M$6:$M$600,"") -> 1
A15: ELE-02 | B15: Elétrica e Iluminação | C15: Cabo Alimentador Geral | D15: Cabo flexível Afumex 0,6/1kV 90°C (3#10 + N10 + PE10 mm²) | E15: 45 | F15: m | G15: 14.67 | H15: =IFERROR(E15*G15, 0) -> 660.15 | I15: EXPLÍCITO | J15: Interligação do QG-N-05 PV ao QDLF-Temporário | K15: Cabo Prysmian Afumex 10 mm² (R$ 14,67/m) | L15: =SUMIFS('Rateio Anexo'!$H$6:$H$600,'Rateio Anexo'!$A$6:$A$600,A15,'Rateio Anexo'!$M$6:$M$600,"") -> 1
... A44: MOB-03 | B44: Elementos Reformados | C44: Mesa Tátil | D44: Repintura acrílica na cor Terra Roxa c/ vinil de recorte | E44: 1 | F44: un | G44: 180 | H44: =IFERROR(E44*G44, 0) -> 180 | I44: REFORMADO | J44: Espaço Educativo | K44: Repintura e vinil de recorte | L44: =SUMIFS('Rateio Anexo'!$H$6:$H$600,'Rateio Anexo'!$A$6:$A$600,A44,'Rateio Anexo'!$M$6:$M$600,"") -> 1
A45: TOTAL GERAL | G45: TOTAL: | H45: =SUM(H4:H44) -> 78534.481

Sheet Mão de Obra e Serviços
A1: COTAÇÃO E REGISTRO DE MÃO DE OBRA, SERVIÇOS E LOGÍSTICA — SESC PAULISTA (COSMOCHÃO v12.0)
A3: Item | B3: Categoria / Função | C3: Especificação / Escopo | D3: Quantidade Est. | E3: Unidade | F3: Valor Unitário (R$) | G3: Custo Total (R$) | H3: Status | I3: Disciplina | J3: Rateio no Anexo (%)
A4: MO-01 | B4: Pintura por empreita — mão de obra | C4: Pintura acrílica de painéis novos (P01–P07, PR01, PR02), existentes e móveis (Preço Fechado / Empreita c/ supervisor embutido) | D4: 559.22 | E4: m² | F4: 50 | G4: =IFERROR(D4*F4, 0) -> 27961 | H4: EXPLÍCITO | I4: Pintura e Acabamentos | J4: =SUMIFS('Rateio Anexo'!$H$6:$H$600,'Rateio Anexo'!$A$6:$A$600,A4,'Rateio Anexo'!$M$6:$M$600,"") -> 1
A5: MO-02A | B5: Marceneiro / Cenotécnico (Galpão) | C5: Equipe de 4 marceneiros alocada por 5 dias de pré-fabricação no galpão (4 p x 5 dias) | D5: 20 | E5: pessoa-dia | F5: 250 | G5: =IFERROR(D5*F5, 0) -> 5000 | H5: EXPLÍCITO | I5: Marcenaria e Cenotecnia | J5: =SUMIFS('Rateio Anexo'!$H$6:$H$600,'Rateio Anexo'!$A$6:$A$600,A5,'Rateio Anexo'!$M$6:$M$600,"") -> 1
A6: MO-02B | B6: Marceneiro / Cenotécnico (SESC) | C6: Equipe de 8 marceneiros alocada nos 20 dias de montagem no SESC (8 p x 20 dias) | D6: 160 | E6: pessoa-dia | F6: 270 | G6: =IFERROR(D6*F6, 0) -> 43200 | H6: EXPLÍCITO | I6: Marcenaria e Cenotecnia | J6: =SUMIFS('Rateio Anexo'!$H$6:$H$600,'Rateio Anexo'!$A$6:$A$600,A6,'Rateio Anexo'!$M$6:$M$600,"") -> 1
A7: MO-03 | B7: Ajudante, carga e descarga | C7: 4 ajudantes nos 2 primeiros dias de montagem no SESC (8 p-d) e no dia da desmontagem (4 p-d) | D7: 10 | E7: pessoa-dia | F7: 130 | G7: =IFERROR(D7*F7, 0) -> 1300 | H7: EXPLÍCITO | I7: Logística e Indiretos | J7: =SUMIFS('Rateio Anexo'!$H$6:$H$600,'Rateio Anexo'!$A$6:$A$600,A7,'Rateio Anexo'!$M$6:$M$600,"") -> 1
A8: MO-04 | B8: Equipe de Limpeza | C8: 3 pessoas alocadas nos últimos 3 dias de montagem no SESC para limpeza fina pré-abertura | D8: 9 | E8: pessoa-dia | F8: 100 | G8: =IFERROR(D8*F8, 0) -> 900 | H8: EXPLÍCITO | I8: Serviços Gerais e Manutenção | J8: =SUMIFS('Rateio Anexo'!$H$6:$H$600,'Rateio Anexo'!$A$6:$A$600,A8,'Rateio Anexo'!$M$6:$M$600,"") -> 1
A9: MO-05 | B9: Serralheiro — EMPREITA | C9: Montagem e ajustes de estruturas metálicas S01, S02, S03 e barracudas (Preço Fechado / Empreita) | D9: 1 | E9: cj | F9: 5000 | G9: =IFERROR(D9*F9, 0) -> 5000 | H9: FECHADO | I9: Serralheria e Estruturas Metálicas | J9: =SUMIFS('Rateio Anexo'!$H$6:$H$600,'Rateio Anexo'!$A$6:$A$600,A9,'Rateio Anexo'!$M$6:$M$600,"") -> 1
A10: MO-06 | B10: Supervisor de Montagem | C10: 1 supervisor dedicado durante toda a montagem no SESC (20 dias); supervisão de pintura e elétrica embutida nas empreitas | D10: 20 | E10: dia | F10: 300 | G10: =IFERROR(D10*F10, 0) -> 6000 | H10: EXPLÍCITO | I10: Logística e Indiretos | J10: =SUMIFS('Rateio Anexo'!$H$6:$H$600,'Rateio Anexo'!$A$6:$A$600,A10,'Rateio Anexo'!$M$6:$M$600,"") -> 1
A11: MO-07 | B11: Tapeceiro | C11: Serviços de tapeçaria, estofamento e revestimentos têxteis | D11: 5 | E11: pessoa-dia | F11: 1 | G11: =IFERROR(D11*F11, 0) -> 5 | H11: PENDENTE | I11: Logística e Indiretos | J11: =SUMIFS('Rateio Anexo'!$H$6:$H$600,'Rateio Anexo'!$A$6:$A$600,A11,'Rateio Anexo'!$M$6:$M$600,"") -> 1
A12: MO-08 | B12: Adesivador | C12: 2 pessoas alocadas por 3 dias para aplicação de insulfilm e vinil de recorte | D12: 6 | E12: pessoa-dia | F12: 250 | G12: =IFERROR(D12*F12, 0) -> 1500 | H12: EXPLÍCITO | I12: Comunicação Visual | J12: =SUMIFS('Rateio Anexo'!$H$6:$H$600,'Rateio Anexo'!$A$6:$A$600,A12,'Rateio Anexo'!$M$6:$M$600,"") -> 1
A13: MO-09 | B13: Eletricista — EMPREITA | C13: Instalação do QDLF-Temporário, fiação, iluminação LED M01/M22 (Preço Fechado / Empreita c/ supervisor embutido) | D13: 1 | E13: cj | F13: 7000 | G13: =IFERROR(D13*F13, 0) -> 7000 | H13: FECHADO | I13: Elétrica e Iluminação | J13: =SUMIFS('Rateio Anexo'!$H$6:$H$600,'Rateio Anexo'!$A$6:$A$600,A13,'Rateio Anexo'!$M$6:$M$600,"") -> 1
A14: MO-10 | B14: Equipe de Manutenção Expositiva | C14: Visitas quinzenais durante os 8 meses de exposição com equipe dedicada de 2 pessoas (18 visitas x 2 p) | D14: 36 | E14: pessoa-dia | F14: 200 | G14: =IFERROR(D14*F14, 0) -> 7200 | H14: DERIVADO | I14: Serviços Gerais e Manutenção | J14: =SUMIFS('Rateio Anexo'!$H$6:$H$600,'Rateio Anexo'!$A$6:$A$600,A14,'Rateio Anexo'!$M$6:$M$600,"") -> 1
A15: LOG-01A | B15: Alimentação (Campo SESC) | C15: Vale-alimentação para equipe operacional durante atuação em campo no SESC (212 pessoa-dias de campo) | D15: 212 | E15: pessoa-dia | F15: 28 | G15: =IFERROR(D15*F15, 0) -> 5936 | H15: DERIVADO | I15: Logística e Indiretos | J15: =SUMIFS('Rateio Anexo'!$H$6:$H$600,'Rateio Anexo'!$A$6:$A$600,A15,'Rateio Anexo'!$M$6:$M$600,"") -> 1
... A20: ENG-01 | B20: ART — referência interna | C20: Anotação de Responsabilidade Técnica de engenharia civil/mecânica | D20: 1 | E20: registro | F20: 1500 | G20: =IFERROR(D20*F20, 0) -> 1500 | H20: EXPLÍCITO | I20: Logística e Indiretos | J20: =SUMIFS('Rateio Anexo'!$H$6:$H$600,'Rateio Anexo'!$A$6:$A$600,A20,'Rateio Anexo'!$M$6:$M$600,"") -> 1
B21: TOTAL DE MÃO DE OBRA, SERVIÇOS E LOGÍSTICA | G21: =SUM(G4:G20) -> 118562

Sheet Rateio Anexo
A1: RATEIO — DE ONDE VEM O CUSTO DE CADA ITEM DO ANEXO
A2: Cada linha de custo (MAT-xx / MO-xx) é dividida entre itens do Anexo pelo PESO (base × fator). Item "INDIRETO" = frete, ART, supervisão etc.: é espalhado nos itens proporcional ao custo direto.
A3: Total rateado (R$) | C3: =SUM(K6:K600) -> 197096.48 | E3: Indireto material (R$) | G3: =SUMIFS(K6:K600,D6:D600,"INDIRETO",B6:B600,"MAT") -> 280 | I3: Indireto MO (R$) | K3: =SUMIFS(K6:K600,D6:D600,"INDIRETO",B6:B600,"MO") -> 20367.667
A5: Código custo | B5: Tipo | C5: Descrição do custo | D5: Item Anexo | E5: Base | F5: Fator | G5: Peso | H5: % do custo | I5: Custo da linha | K5: Custo rateado | L5: Base do peso (de onde saiu) | M5: Conferência
A6: MAT-01 | B6: =IF($A6="","",IF(ISNUMBER(MATCH($A6,'Cotação de Materiais'!$A$4:$A$200,0)),"MAT",IF(ISNUMBER(MATCH($A6,'Mão de Obra e Serviços'!$A$4:$A$200,0)),"MO","CÓDIGO?"))) -> MAT | C6: =IF($A6="","",IFERROR(INDEX('Cotação de Materiais'!$C$4:$C$200,MATCH($A6,'Cotação de Materiais'!$A$4:$A$200,0)),IFERROR(INDEX('Mão de Obra e Serviços'!$B$4:$B$200,MATCH($A6,'Mão de Obra e Serviços'!$A$4:$A$200,0)),""))) -> Chapas de MDF Comum 18mm | D6: A.2.1 | E6: 14 | F6: 1 | G6: =IF($A6="","",E6*IF(F6="",1,F6)) -> 14 | H6: =IF($A6="","",IF(SUMIF($A$6:$A$600,$A6,$G$6:$G$600)=0,0,G6/SUMIF($A$6:$A$600,$A6,$G$6:$G$600))) -> 0.035194449 | I6: =IF($A6="","",IFERROR(INDEX('Cotação de Materiais'!$H$4:$H$200,MATCH($A6,'Cotação de Materiais'!$A$4:$A$200,0)),IFERROR(INDEX('Mão de Obra e Serviços'!$G$4:$G$200,MATCH($A6,'Mão de Obra e Serviços'!$A$4:$A$200,0)),0))) -> 15607.36 | K6: =IF($A6="","",I6*H6) -> 549.29244 | L6: m² (painel = Anexo; base = envoltória) | M6: =IF($A6="","",IF(B6="CÓDIGO?","CÓDIGO NÃO ACHADO",IF($D6="","FALTA ITEM DO ANEXO",IF($D6="INDIRETO","",IF(COUNTIFS('Anexo III'!$B$8:$B$400,$D6,'Anexo III'!$E$8:$E$400,">0")=0,"ITEM NÃO ACHADO NO ANEXO","")))))
A7: MAT-01 | B7: =IF($A7="","",IF(ISNUMBER(MATCH($A7,'Cotação de Materiais'!$A$4:$A$200,0)),"MAT",IF(ISNUMBER(MATCH($A7,'Mão de Obra e Serviços'!$A$4:$A$200,0)),"MO","CÓDIGO?"))) -> MAT | C7: =IF($A7="","",IFERROR(INDEX('Cotação de Materiais'!$C$4:$C$200,MATCH($A7,'Cotação de Materiais'!$A$4:$A$200,0)),IFERROR(INDEX('Mão de Obra e Serviços'!$B$4:$B$200,MATCH($A7,'Mão de Obra e Serviços'!$A$4:$A$200,0)),""))) -> Chapas de MDF Comum 18mm | D7: A.2.2 | E7: 11.8 | F7: 1 | G7: =IF($A7="","",E7*IF(F7="",1,F7)) -> 11.8 | H7: =IF($A7="","",IF(SUMIF($A$6:$A$600,$A7,$G$6:$G$600)=0,0,G7/SUMIF($A$6:$A$600,$A7,$G$6:$G$600))) -> 0.029663893 | I7: =IF($A7="","",IFERROR(INDEX('Cotação de Materiais'!$H$4:$H$200,MATCH($A7,'Cotação de Materiais'!$A$4:$A$200,0)),IFERROR(INDEX('Mão de Obra e Serviços'!$G$4:$G$200,MATCH($A7,'Mão de Obra e Serviços'!$A$4:$A$200,0)),0))) -> 15607.36 | K7: =IF($A7="","",I7*H7) -> 462.97506 | L7: m² (painel = Anexo; base = envoltória) | M7: =IF($A7="","",IF(B7="CÓDIGO?","CÓDIGO NÃO ACHADO",IF($D7="","FALTA ITEM DO ANEXO",IF($D7="INDIRETO","",IF(COUNTIFS('Anexo III'!$B$8:$B$400,$D7,'Anexo III'!$E$8:$E$400,">0")=0,"ITEM NÃO ACHADO NO ANEXO","")))))
A8: MAT-01 | B8: =IF($A8="","",IF(ISNUMBER(MATCH($A8,'Cotação de Materiais'!$A$4:$A$200,0)),"MAT",IF(ISNUMBER(MATCH($A8,'Mão de Obra e Serviços'!$A$4:$A$200,0)),"MO","CÓDIGO?"))) -> MAT | C8: =IF($A8="","",IFERROR(INDEX('Cotação de Materiais'!$C$4:$C$200,MATCH($A8,'Cotação de Materiais'!$A$4:$A$200,0)),IFERROR(INDEX('Mão de Obra e Serviços'!$B$4:$B$200,MATCH($A8,'Mão de Obra e Serviços'!$A$4:$A$200,0)),""))) -> Chapas de MDF Comum 18mm | D8: A.2.3 | E8: 32 | F8: 1 | G8: =IF($A8="","",E8*IF(F8="",1,F8)) -> 32 | H8: =IF($A8="","",IF(SUMIF($A$6:$A$600,$A8,$G$6:$G$600)=0,0,G8/SUMIF($A$6:$A$600,$A8,$G$6:$G$600))) -> 0.080444456 | I8: =IF($A8="","",IFERROR(INDEX('Cotação de Materiais'!$H$4:$H$200,MATCH($A8,'Cotação de Materiais'!$A$4:$A$200,0)),IFERROR(INDEX('Mão de Obra e Serviços'!$G$4:$G$200,MATCH($A8,'Mão de Obra e Serviços'!$A$4:$A$200,0)),0))) -> 15607.36 | K8: =IF($A8="","",I8*H8) -> 1255.5256 | L8: m² (painel = Anexo; base = envoltória) | M8: =IF($A8="","",IF(B8="CÓDIGO?","CÓDIGO NÃO ACHADO",IF($D8="","FALTA ITEM DO ANEXO",IF($D8="INDIRETO","",IF(COUNTIFS('Anexo III'!$B$8:$B$400,$D8,'Anexo III'!$E$8:$E$400,">0")=0,"ITEM NÃO ACHADO NO ANEXO","")))))
A9: MAT-01 | B9: =IF($A9="","",IF(ISNUMBER(MATCH($A9,'Cotação de Materiais'!$A$4:$A$200,0)),"MAT",IF(ISNUMBER(MATCH($A9,'Mão de Obra e Serviços'!$A$4:$A$200,0)),"MO","CÓDIGO?"))) -> MAT | C9: =IF($A9="","",IFERROR(INDEX('Cotação de Materiais'!$C$4:$C$200,MATCH($A9,'Cotação de Materiais'!$A$4:$A$200,0)),IFERROR(INDEX('Mão de Obra e Serviços'!$B$4:$B$200,MATCH($A9,'Mão de Obra e Serviços'!$A$4:$A$200,0)),""))) -> Chapas de MDF Comum 18mm | D9: A.2.4 | E9: 25 | F9: 1 | G9: =IF($A9="","",E9*IF(F9="",1,F9)) -> 25 | H9: =IF($A9="","",IF(SUMIF($A$6:$A$600,$A9,$G$6:$G$600)=0,0,G9/SUMIF($A$6:$A$600,$A9,$G$6:$G$600))) -> 0.062847231 | I9: =IF($A9="","",IFERROR(INDEX('Cotação de Materiais'!$H$4:$H$200,MATCH($A9,'Cotação de Materiais'!$A$4:$A$200,0)),IFERROR(INDEX('Mão de Obra e Serviços'!$G$4:$G$200,MATCH($A9,'Mão de Obra e Serviços'!$A$4:$A$200,0)),0))) -> 15607.36 | K9: =IF($A9="","",I9*H9) -> 980.87936 | L9: m² (painel = Anexo; base = envoltória) | M9: =IF($A9="","",IF(B9="CÓDIGO?","CÓDIGO NÃO ACHADO",IF($D9="","FALTA ITEM DO ANEXO",IF($D9="INDIRETO","",IF(COUNTIFS('Anexo III'!$B$8:$B$400,$D9,'Anexo III'!$E$8:$E$400,">0")=0,"ITEM NÃO ACHADO NO ANEXO","")))))
A10: MAT-01 | B10: =IF($A10="","",IF(ISNUMBER(MATCH($A10,'Cotação de Materiais'!$A$4:$A$200,0)),"MAT",IF(ISNUMBER(MATCH($A10,'Mão de Obra e Serviços'!$A$4:$A$200,0)),"MO","CÓDIGO?"))) -> MAT | C10: =IF($A10="","",IFERROR(INDEX('Cotação de Materiais'!$C$4:$C$200,MATCH($A10,'Cotação de Materiais'!$A$4:$A$200,0)),IFERROR(INDEX('Mão de Obra e Serviços'!$B$4:$B$200,MATCH($A10,'Mão de Obra e Serviços'!$A$4:$A$200,0)),""))) -> Chapas de MDF Comum 18mm | D10: A.2.5 | E10: 16.5 | F10: 1 | G10: =IF($A10="","",E10*IF(F10="",1,F10)) -> 16.5 | H10: =IF($A10="","",IF(SUMIF($A$6:$A$600,$A10,$G$6:$G$600)=0,0,G10/SUMIF($A$6:$A$600,$A10,$G$6:$G$600))) -> 0.041479172 | I10: =IF($A10="","",IFERROR(INDEX('Cotação de Materiais'!$H$4:$H$200,MATCH($A10,'Cotação de Materiais'!$A$4:$A$200,0)),IFERROR(INDEX('Mão de Obra e Serviços'!$G$4:$G$200,MATCH($A10,'Mão de Obra e Serviços'!$A$4:$A$200,0)),0))) -> 15607.36 | K10: =IF($A10="","",I10*H10) -> 647.38038 | L10: m² (painel = Anexo; base = envoltória) | M10: =IF($A10="","",IF(B10="CÓDIGO?","CÓDIGO NÃO ACHADO",IF($D10="","FALTA ITEM DO ANEXO",IF($D10="INDIRETO","",IF(COUNTIFS('Anexo III'!$B$8:$B$400,$D10,'Anexo III'!$E$8:$E$400,">0")=0,"ITEM NÃO ACHADO NO ANEXO","")))))
A11: MAT-01 | B11: =IF($A11="","",IF(ISNUMBER(MATCH($A11,'Cotação de Materiais'!$A$4:$A$200,0)),"MAT",IF(ISNUMBER(MATCH($A11,'Mão de Obra e Serviços'!$A$4:$A$200,0)),"MO","CÓDIGO?"))) -> MAT | C11: =IF($A11="","",IFERROR(INDEX('Cotação de Materiais'!$C$4:$C$200,MATCH($A11,'Cotação de Materiais'!$A$4:$A$200,0)),IFERROR(INDEX('Mão de Obra e Serviços'!$B$4:$B$200,MATCH($A11,'Mão de Obra e Serviços'!$A$4:$A$200,0)),""))) -> Chapas de MDF Comum 18mm | D11: A.2.6 | E11: 3.8 | F11: 1 | G11: =IF($A11="","",E11*IF(F11="",1,F11)) -> 3.8 | H11: =IF($A11="","",IF(SUMIF($A$6:$A$600,$A11,$G$6:$G$600)=0,0,G11/SUMIF($A$6:$A$600,$A11,$G$6:$G$600))) -> 0.0095527791 | I11: =IF($A11="","",IFERROR(INDEX('Cotação de Materiais'!$H$4:$H$200,MATCH($A11,'Cotação de Materiais'!$A$4:$A$200,0)),IFERROR(INDEX('Mão de Obra e Serviços'!$G$4:$G$200,MATCH($A11,'Mão de Obra e Serviços'!$A$4:$A$200,0)),0))) -> 15607.36 | K11: =IF($A11="","",I11*H11) -> 149.09366 | L11: m² (painel = Anexo; base = envoltória) | M11: =IF($A11="","",IF(B11="CÓDIGO?","CÓDIGO NÃO ACHADO",IF($D11="","FALTA ITEM DO ANEXO",IF($D11="INDIRETO","",IF(COUNTIFS('Anexo III'!$B$8:$B$400,$D11,'Anexo III'!$E$8:$E$400,">0")=0,"ITEM NÃO ACHADO NO ANEXO","")))))
A12: MAT-01 | B12: =IF($A12="","",IF(ISNUMBER(MATCH($A12,'Cotação de Materiais'!$A$4:$A$200,0)),"MAT",IF(ISNUMBER(MATCH($A12,'Mão de Obra e Serviços'!$A$4:$A$200,0)),"MO","CÓDIGO?"))) -> MAT | C12: =IF($A12="","",IFERROR(INDEX('Cotação de Materiais'!$C$4:$C$200,MATCH($A12,'Cotação de Materiais'!$A$4:$A$200,0)),IFERROR(INDEX('Mão de Obra e Serviços'!$B$4:$B$200,MATCH($A12,'Mão de Obra e Serviços'!$A$4:$A$200,0)),""))) -> Chapas de MDF Comum 18mm | D12: A.2.7 | E12: 5.2 | F12: 1 | G12: =IF($A12="","",E12*IF(F12="",1,F12)) -> 5.2 | H12: =IF($A12="","",IF(SUMIF($A$6:$A$600,$A12,$G$6:$G$600)=0,0,G12/SUMIF($A$6:$A$600,$A12,$G$6:$G$600))) -> 0.013072224 | I12: =IF($A12="","",IFERROR(INDEX('Cotação de Materiais'!$H$4:$H$200,MATCH($A12,'Cotação de Materiais'!$A$4:$A$200,0)),IFERROR(INDEX('Mão de Obra e Serviços'!$G$4:$G$200,MATCH($A12,'Mão de Obra e Serviços'!$A$4:$A$200,0)),0))) -> 15607.36 | K12: =IF($A12="","",I12*H12) -> 204.02291 | L12: m² (painel = Anexo; base = envoltória) | M12: =IF($A12="","",IF(B12="CÓDIGO?","CÓDIGO NÃO ACHADO",IF($D12="","FALTA ITEM DO ANEXO",IF($D12="INDIRETO","",IF(COUNTIFS('Anexo III'!$B$8:$B$400,$D12,'Anexo III'!$E$8:$E$400,">0")=0,"ITEM NÃO ACHADO NO ANEXO","")))))
A13: MAT-01 | B13: =IF($A13="","",IF(ISNUMBER(MATCH($A13,'Cotação de Materiais'!$A$4:$A$200,0)),"MAT",IF(ISNUMBER(MATCH($A13,'Mão de Obra e Serviços'!$A$4:$A$200,0)),"MO","CÓDIGO?"))) -> MAT | C13: =IF($A13="","",IFERROR(INDEX('Cotação de Materiais'!$C$4:$C$200,MATCH($A13,'Cotação de Materiais'!$A$4:$A$200,0)),IFERROR(INDEX('Mão de Obra e Serviços'!$B$4:$B$200,MATCH($A13,'Mão de Obra e Serviços'!$A$4:$A$200,0)),""))) -> Chapas de MDF Comum 18mm | D13: A.2.8 | E13: 35 | F13: 1 | G13: =IF($A13="","",E13*IF(F13="",1,F13)) -> 35 | H13: =IF($A13="","",IF(SUMIF($A$6:$A$600,$A13,$G$6:$G$600)=0,0,G13/SUMIF($A$6:$A$600,$A13,$G$6:$G$600))) -> 0.087986123 | I13: =IF($A13="","",IFERROR(INDEX('Cotação de Materiais'!$H$4:$H$200,MATCH($A13,'Cotação de Materiais'!$A$4:$A$200,0)),IFERROR(INDEX('Mão de Obra e Serviços'!$G$4:$G$200,MATCH($A13,'Mão de Obra e Serviços'!$A$4:$A$200,0)),0))) -> 15607.36 | K13: =IF($A13="","",I13*H13) -> 1373.2311 | L13: m² (painel = Anexo; base = envoltória) | M13: =IF($A13="","",IF(B13="CÓDIGO?","CÓDIGO NÃO ACHADO",IF($D13="","FALTA ITEM DO ANEXO",IF($D13="INDIRETO","",IF(COUNTIFS('Anexo III'!$B$8:$B$400,$D13,'Anexo III'!$E$8:$E$400,">0")=0,"ITEM NÃO ACHADO NO ANEXO","")))))
A14: MAT-01 | B14: =IF($A14="","",IF(ISNUMBER(MATCH($A14,'Cotação de Materiais'!$A$4:$A$200,0)),"MAT",IF(ISNUMBER(MATCH($A14,'Mão de Obra e Serviços'!$A$4:$A$200,0)),"MO","CÓDIGO?"))) -> MAT | C14: =IF($A14="","",IFERROR(INDEX('Cotação de Materiais'!$C$4:$C$200,MATCH($A14,'Cotação de Materiais'!$A$4:$A$200,0)),IFERROR(INDEX('Mão de Obra e Serviços'!$B$4:$B$200,MATCH($A14,'Mão de Obra e Serviços'!$A$4:$A$200,0)),""))) -> Chapas de MDF Comum 18mm | D14: A.2.9 | E14: 97 | F14: 1 | G14: =IF($A14="","",E14*IF(F14="",1,F14)) -> 97 | H14: =IF($A14="","",IF(SUMIF($A$6:$A$600,$A14,$G$6:$G$600)=0,0,G14/SUMIF($A$6:$A$600,$A14,$G$6:$G$600))) -> 0.24384726 | I14: =IF($A14="","",IFERROR(INDEX('Cotação de Materiais'!$H$4:$H$200,MATCH($A14,'Cotação de Materiais'!$A$4:$A$200,0)),IFERROR(INDEX('Mão de Obra e Serviços'!$G$4:$G$200,MATCH($A14,'Mão de Obra e Serviços'!$A$4:$A$200,0)),0))) -> 15607.36 | K14: =IF($A14="","",I14*H14) -> 3805.8119 | L14: m² (painel = Anexo; base = envoltória) | M14: =IF($A14="","",IF(B14="CÓDIGO?","CÓDIGO NÃO ACHADO",IF($D14="","FALTA ITEM DO ANEXO",IF($D14="INDIRETO","",IF(COUNTIFS('Anexo III'!$B$8:$B$400,$D14,'Anexo III'!$E$8:$E$400,">0")=0,"ITEM NÃO ACHADO NO ANEXO","")))))
A15: MAT-01 | B15: =IF($A15="","",IF(ISNUMBER(MATCH($A15,'Cotação de Materiais'!$A$4:$A$200,0)),"MAT",IF(ISNUMBER(MATCH($A15,'Mão de Obra e Serviços'!$A$4:$A$200,0)),"MO","CÓDIGO?"))) -> MAT | C15: =IF($A15="","",IFERROR(INDEX('Cotação de Materiais'!$C$4:$C$200,MATCH($A15,'Cotação de Materiais'!$A$4:$A$200,0)),IFERROR(INDEX('Mão de Obra e Serviços'!$B$4:$B$200,MATCH($A15,'Mão de Obra e Serviços'!$A$4:$A$200,0)),""))) -> Chapas de MDF Comum 18mm | D15: A.4.4 | E15: 38.58 | F15: 1 | G15: =IF($A15="","",E15*IF(F15="",1,F15)) -> 38.58 | H15: =IF($A15="","",IF(SUMIF($A$6:$A$600,$A15,$G$6:$G$600)=0,0,G15/SUMIF($A$6:$A$600,$A15,$G$6:$G$600))) -> 0.096985847 | I15: =IF($A15="","",IFERROR(INDEX('Cotação de Materiais'!$H$4:$H$200,MATCH($A15,'Cotação de Materiais'!$A$4:$A$200,0)),IFERROR(INDEX('Mão de Obra e Serviços'!$G$4:$G$200,MATCH($A15,'Mão de Obra e Serviços'!$A$4:$A$200,0)),0))) -> 15607.36 | K15: =IF($A15="","",I15*H15) -> 1513.693 | L15: m² (painel = Anexo; base = envoltória) | M15: =IF($A15="","",IF(B15="CÓDIGO?","CÓDIGO NÃO ACHADO",IF($D15="","FALTA ITEM DO ANEXO",IF($D15="INDIRETO","",IF(COUNTIFS('Anexo III'!$B$8:$B$400,$D15,'Anexo III'!$E$8:$E$400,">0")=0,"ITEM NÃO ACHADO NO ANEXO","")))))
A16: MAT-01 | B16: =IF($A16="","",IF(ISNUMBER(MATCH($A16,'Cotação de Materiais'!$A$4:$A$200,0)),"MAT",IF(ISNUMBER(MATCH($A16,'Mão de Obra e Serviços'!$A$4:$A$200,0)),"MO","CÓDIGO?"))) -> MAT | C16: =IF($A16="","",IFERROR(INDEX('Cotação de Materiais'!$C$4:$C$200,MATCH($A16,'Cotação de Materiais'!$A$4:$A$200,0)),IFERROR(INDEX('Mão de Obra e Serviços'!$B$4:$B$200,MATCH($A16,'Mão de Obra e Serviços'!$A$4:$A$200,0)),""))) -> Chapas de MDF Comum 18mm | D16: A.4.5 | E16: 12.5 | F16: 1 | G16: =IF($A16="","",E16*IF(F16="",1,F16)) -> 12.5 | H16: =IF($A16="","",IF(SUMIF($A$6:$A$600,$A16,$G$6:$G$600)=0,0,G16/SUMIF($A$6:$A$600,$A16,$G$6:$G$600))) -> 0.031423615 | I16: =IF($A16="","",IFERROR(INDEX('Cotação de Materiais'!$H$4:$H$200,MATCH($A16,'Cotação de Materiais'!$A$4:$A$200,0)),IFERROR(INDEX('Mão de Obra e Serviços'!$G$4:$G$200,MATCH($A16,'Mão de Obra e Serviços'!$A$4:$A$200,0)),0))) -> 15607.36 | K16: =IF($A16="","",I16*H16) -> 490.43968 | L16: m² (painel = Anexo; base = envoltória) | M16: =IF($A16="","",IF(B16="CÓDIGO?","CÓDIGO NÃO ACHADO",IF($D16="","FALTA ITEM DO ANEXO",IF($D16="INDIRETO","",IF(COUNTIFS('Anexo III'!$B$8:$B$400,$D16,'Anexo III'!$E$8:$E$400,">0")=0,"ITEM NÃO ACHADO NO ANEXO","")))))
A17: MAT-01 | B17: =IF($A17="","",IF(ISNUMBER(MATCH($A17,'Cotação de Materiais'!$A$4:$A$200,0)),"MAT",IF(ISNUMBER(MATCH($A17,'Mão de Obra e Serviços'!$A$4:$A$200,0)),"MO","CÓDIGO?"))) -> MAT | C17: =IF($A17="","",IFERROR(INDEX('Cotação de Materiais'!$C$4:$C$200,MATCH($A17,'Cotação de Materiais'!$A$4:$A$200,0)),IFERROR(INDEX('Mão de Obra e Serviços'!$B$4:$B$200,MATCH($A17,'Mão de Obra e Serviços'!$A$4:$A$200,0)),""))) -> Chapas de MDF Comum 18mm | D17: A.4.6 | E17: 2.11 | F17: 1 | G17: =IF($A17="","",E17*IF(F17="",1,F17)) -> 2.11 | H17: =IF($A17="","",IF(SUMIF($A$6:$A$600,$A17,$G$6:$G$600)=0,0,G17/SUMIF($A$6:$A$600,$A17,$G$6:$G$600))) -> 0.0053043063 | I17: =IF($A17="","",IFERROR(INDEX('Cotação de Materiais'!$H$4:$H$200,MATCH($A17,'Cotação de Materiais'!$A$4:$A$200,0)),IFERROR(INDEX('Mão de Obra e Serviços'!$G$4:$G$200,MATCH($A17,'Mão de Obra e Serviços'!$A$4:$A$200,0)),0))) -> 15607.36 | K17: =IF($A17="","",I17*H17) -> 82.786218 | L17: m² (painel = Anexo; base = envoltória) | M17: =IF($A17="","",IF(B17="CÓDIGO?","CÓDIGO NÃO ACHADO",IF($D17="","FALTA ITEM DO ANEXO",IF($D17="INDIRETO","",IF(COUNTIFS('Anexo III'!$B$8:$B$400,$D17,'Anexo III'!$E$8:$E$400,">0")=0,"ITEM NÃO ACHADO NO ANEXO","")))))
... A267: ENG-01 | B267: =IF($A267="","",IF(ISNUMBER(MATCH($A267,'Cotação de Materiais'!$A$4:$A$200,0)),"MAT",IF(ISNUMBER(MATCH($A267,'Mão de Obra e Serviços'!$A$4:$A$200,0)),"MO","CÓDIGO?"))) -> MO | C267: =IF($A267="","",IFERROR(INDEX('Cotação de Materiais'!$C$4:$C$200,MATCH($A267,'Cotação de Materiais'!$A$4:$A$200,0)),IFERROR(INDEX('Mão de Obra e Serviços'!$B$4:$B$200,MATCH($A267,'Mão de Obra e Serviços'!$A$4:$A$200,0)),""))) -> ART — referência interna | D267: INDIRETO | E267: 1 | F267: 1 | G267: =IF($A267="","",E267*IF(F267="",1,F267)) -> 1 | H267: =IF($A267="","",IF(SUMIF($A$6:$A$600,$A267,$G$6:$G$600)=0,0,G267/SUMIF($A$6:$A$600,$A267,$G$6:$G$600))) -> 1 | I267: =IF($A267="","",IFERROR(INDEX('Cotação de Materiais'!$H$4:$H$200,MATCH($A267,'Cotação de Materiais'!$A$4:$A$200,0)),IFERROR(INDEX('Mão de Obra e Serviços'!$G$4:$G$200,MATCH($A267,'Mão de Obra e Serviços'!$A$4:$A$200,0)),0))) -> 1500 | K267: =IF($A267="","",I267*H267) -> 1500 | L267: logística/ART → indireto | M267: =IF($A267="","",IF(B267="CÓDIGO?","CÓDIGO NÃO ACHADO",IF($D267="","FALTA ITEM DO ANEXO",IF($D267="INDIRETO","",IF(COUNTIFS('Anexo III'!$B$8:$B$400,$D267,'Anexo III'!$E$8:$E$400,">0")=0,"ITEM NÃO ACHADO NO ANEXO","")))))
B268: =IF($A268="","",IF(ISNUMBER(MATCH($A268,'Cotação de Materiais'!$A$4:$A$200,0)),"MAT",IF(ISNUMBER(MATCH($A268,'Mão de Obra e Serviços'!$A$4:$A$200,0)),"MO","CÓDIGO?"))) | C268: =IF($A268="","",IFERROR(INDEX('Cotação de Materiais'!$C$4:$C$200,MATCH($A268,'Cotação de Materiais'!$A$4:$A$200,0)),IFERROR(INDEX('Mão de Obra e Serviços'!$B$4:$B$200,MATCH($A268,'Mão de Obra e Serviços'!$A$4:$A$200,0)),""))) | G268: =IF($A268="","",E268*IF(F268="",1,F268)) | H268: =IF($A268="","",IF(SUMIF($A$6:$A$600,$A268,$G$6:$G$600)=0,0,G268/SUMIF($A$6:$A$600,$A268,$G$6:$G$600))) | I268: =IF($A268="","",IFERROR(INDEX('Cotação de Materiais'!$H$4:$H$200,MATCH($A268,'Cotação de Materiais'!$A$4:$A$200,0)),IFERROR(INDEX('Mão de Obra e Serviços'!$G$4:$G$200,MATCH($A268,'Mão de Obra e Serviços'!$A$4:$A$200,0)),0))) | K268: =IF($A268="","",I268*H268) | M268: =IF($A268="","",IF(B268="CÓDIGO?","CÓDIGO NÃO ACHADO",IF($D268="","FALTA ITEM DO ANEXO",IF($D268="INDIRETO","",IF(COUNTIFS('Anexo III'!$B$8:$B$400,$D268,'Anexo III'!$E$8:$E$400,">0")=0,"ITEM NÃO ACHADO NO ANEXO","")))))
B269: =IF($A269="","",IF(ISNUMBER(MATCH($A269,'Cotação de Materiais'!$A$4:$A$200,0)),"MAT",IF(ISNUMBER(MATCH($A269,'Mão de Obra e Serviços'!$A$4:$A$200,0)),"MO","CÓDIGO?"))) | C269: =IF($A269="","",IFERROR(INDEX('Cotação de Materiais'!$C$4:$C$200,MATCH($A269,'Cotação de Materiais'!$A$4:$A$200,0)),IFERROR(INDEX('Mão de Obra e Serviços'!$B$4:$B$200,MATCH($A269,'Mão de Obra e Serviços'!$A$4:$A$200,0)),""))) | G269: =IF($A269="","",E269*IF(F269="",1,F269)) | H269: =IF($A269="","",IF(SUMIF($A$6:$A$600,$A269,$G$6:$G$600)=0,0,G269/SUMIF($A$6:$A$600,$A269,$G$6:$G$600))) | I269: =IF($A269="","",IFERROR(INDEX('Cotação de Materiais'!$H$4:$H$200,MATCH($A269,'Cotação de Materiais'!$A$4:$A$200,0)),IFERROR(INDEX('Mão de Obra e Serviços'!$G$4:$G$200,MATCH($A269,'Mão de Obra e Serviços'!$A$4:$A$200,0)),0))) | K269: =IF($A269="","",I269*H269) | M269: =IF($A269="","",IF(B269="CÓDIGO?","CÓDIGO NÃO ACHADO",IF($D269="","FALTA ITEM DO ANEXO",IF($D269="INDIRETO","",IF(COUNTIFS('Anexo III'!$B$8:$B$400,$D269,'Anexo III'!$E$8:$E$400,">0")=0,"ITEM NÃO ACHADO NO ANEXO","")))))
B270: =IF($A270="","",IF(ISNUMBER(MATCH($A270,'Cotação de Materiais'!$A$4:$A$200,0)),"MAT",IF(ISNUMBER(MATCH($A270,'Mão de Obra e Serviços'!$A$4:$A$200,0)),"MO","CÓDIGO?"))) | C270: =IF($A270="","",IFERROR(INDEX('Cotação de Materiais'!$C$4:$C$200,MATCH($A270,'Cotação de Materiais'!$A$4:$A$200,0)),IFERROR(INDEX('Mão de Obra e Serviços'!$B$4:$B$200,MATCH($A270,'Mão de Obra e Serviços'!$A$4:$A$200,0)),""))) | G270: =IF($A270="","",E270*IF(F270="",1,F270)) | H270: =IF($A270="","",IF(SUMIF($A$6:$A$600,$A270,$G$6:$G$600)=0,0,G270/SUMIF($A$6:$A$600,$A270,$G$6:$G$600))) | I270: =IF($A270="","",IFERROR(INDEX('Cotação de Materiais'!$H$4:$H$200,MATCH($A270,'Cotação de Materiais'!$A$4:$A$200,0)),IFERROR(INDEX('Mão de Obra e Serviços'!$G$4:$G$200,MATCH($A270,'Mão de Obra e Serviços'!$A$4:$A$200,0)),0))) | K270: =IF($A270="","",I270*H270) | M270: =IF($A270="","",IF(B270="CÓDIGO?","CÓDIGO NÃO ACHADO",IF($D270="","FALTA ITEM DO ANEXO",IF($D270="INDIRETO","",IF(COUNTIFS('Anexo III'!$B$8:$B$400,$D270,'Anexo III'!$E$8:$E$400,">0")=0,"ITEM NÃO ACHADO NO ANEXO","")))))
B271: =IF($A271="","",IF(ISNUMBER(MATCH($A271,'Cotação de Materiais'!$A$4:$A$200,0)),"MAT",IF(ISNUMBER(MATCH($A271,'Mão de Obra e Serviços'!$A$4:$A$200,0)),"MO","CÓDIGO?"))) | C271: =IF($A271="","",IFERROR(INDEX('Cotação de Materiais'!$C$4:$C$200,MATCH($A271,'Cotação de Materiais'!$A$4:$A$200,0)),IFERROR(INDEX('Mão de Obra e Serviços'!$B$4:$B$200,MATCH($A271,'Mão de Obra e Serviços'!$A$4:$A$200,0)),""))) | G271: =IF($A271="","",E271*IF(F271="",1,F271)) | H271: =IF($A271="","",IF(SUMIF($A$6:$A$600,$A271,$G$6:$G$600)=0,0,G271/SUMIF($A$6:$A$600,$A271,$G$6:$G$600))) | I271: =IF($A271="","",IFERROR(INDEX('Cotação de Materiais'!$H$4:$H$200,MATCH($A271,'Cotação de Materiais'!$A$4:$A$200,0)),IFERROR(INDEX('Mão de Obra e Serviços'!$G$4:$G$200,MATCH($A271,'Mão de Obra e Serviços'!$A$4:$A$200,0)),0))) | K271: =IF($A271="","",I271*H271) | M271: =IF($A271="","",IF(B271="CÓDIGO?","CÓDIGO NÃO ACHADO",IF($D271="","FALTA ITEM DO ANEXO",IF($D271="INDIRETO","",IF(COUNTIFS('Anexo III'!$B$8:$B$400,$D271,'Anexo III'!$E$8:$E$400,">0")=0,"ITEM NÃO ACHADO NO ANEXO","")))))
B272: =IF($A272="","",IF(ISNUMBER(MATCH($A272,'Cotação de Materiais'!$A$4:$A$200,0)),"MAT",IF(ISNUMBER(MATCH($A272,'Mão de Obra e Serviços'!$A$4:$A$200,0)),"MO","CÓDIGO?"))) | C272: =IF($A272="","",IFERROR(INDEX('Cotação de Materiais'!$C$4:$C$200,MATCH($A272,'Cotação de Materiais'!$A$4:$A$200,0)),IFERROR(INDEX('Mão de Obra e Serviços'!$B$4:$B$200,MATCH($A272,'Mão de Obra e Serviços'!$A$4:$A$200,0)),""))) | G272: =IF($A272="","",E272*IF(F272="",1,F272)) | H272: =IF($A272="","",IF(SUMIF($A$6:$A$600,$A272,$G$6:$G$600)=0,0,G272/SUMIF($A$6:$A$600,$A272,$G$6:$G$600))) | I272: =IF($A272="","",IFERROR(INDEX('Cotação de Materiais'!$H$4:$H$200,MATCH($A272,'Cotação de Materiais'!$A$4:$A$200,0)),IFERROR(INDEX('Mão de Obra e Serviços'!$G$4:$G$200,MATCH($A272,'Mão de Obra e Serviços'!$A$4:$A$200,0)),0))) | K272: =IF($A272="","",I272*H272) | M272: =IF($A272="","",IF(B272="CÓDIGO?","CÓDIGO NÃO ACHADO",IF($D272="","FALTA ITEM DO ANEXO",IF($D272="INDIRETO","",IF(COUNTIFS('Anexo III'!$B$8:$B$400,$D272,'Anexo III'!$E$8:$E$400,">0")=0,"ITEM NÃO ACHADO NO ANEXO","")))))
B273: =IF($A273="","",IF(ISNUMBER(MATCH($A273,'Cotação de Materiais'!$A$4:$A$200,0)),"MAT",IF(ISNUMBER(MATCH($A273,'Mão de Obra e Serviços'!$A$4:$A$200,0)),"MO","CÓDIGO?"))) | C273: =IF($A273="","",IFERROR(INDEX('Cotação de Materiais'!$C$4:$C$200,MATCH($A273,'Cotação de Materiais'!$A$4:$A$200,0)),IFERROR(INDEX('Mão de Obra e Serviços'!$B$4:$B$200,MATCH($A273,'Mão de Obra e Serviços'!$A$4:$A$200,0)),""))) | G273: =IF($A273="","",E273*IF(F273="",1,F273)) | H273: =IF($A273="","",IF(SUMIF($A$6:$A$600,$A273,$G$6:$G$600)=0,0,G273/SUMIF($A$6:$A$600,$A273,$G$6:$G$600))) | I273: =IF($A273="","",IFERROR(INDEX('Cotação de Materiais'!$H$4:$H$200,MATCH($A273,'Cotação de Materiais'!$A$4:$A$200,0)),IFERROR(INDEX('Mão de Obra e Serviços'!$G$4:$G$200,MATCH($A273,'Mão de Obra e Serviços'!$A$4:$A$200,0)),0))) | K273: =IF($A273="","",I273*H273) | M273: =IF($A273="","",IF(B273="CÓDIGO?","CÓDIGO NÃO ACHADO",IF($D273="","FALTA ITEM DO ANEXO",IF($D273="INDIRETO","",IF(COUNTIFS('Anexo III'!$B$8:$B$400,$D273,'Anexo III'!$E$8:$E$400,">0")=0,"ITEM NÃO ACHADO NO ANEXO","")))))
B274: =IF($A274="","",IF(ISNUMBER(MATCH($A274,'Cotação de Materiais'!$A$4:$A$200,0)),"MAT",IF(ISNUMBER(MATCH($A274,'Mão de Obra e Serviços'!$A$4:$A$200,0)),"MO","CÓDIGO?"))) | C274: =IF($A274="","",IFERROR(INDEX('Cotação de Materiais'!$C$4:$C$200,MATCH($A274,'Cotação de Materiais'!$A$4:$A$200,0)),IFERROR(INDEX('Mão de Obra e Serviços'!$B$4:$B$200,MATCH($A274,'Mão de Obra e Serviços'!$A$4:$A$200,0)),""))) | G274: =IF($A274="","",E274*IF(F274="",1,F274)) | H274: =IF($A274="","",IF(SUMIF($A$6:$A$600,$A274,$G$6:$G$600)=0,0,G274/SUMIF($A$6:$A$600,$A274,$G$6:$G$600))) | I274: =IF($A274="","",IFERROR(INDEX('Cotação de Materiais'!$H$4:$H$200,MATCH($A274,'Cotação de Materiais'!$A$4:$A$200,0)),IFERROR(INDEX('Mão de Obra e Serviços'!$G$4:$G$200,MATCH($A274,'Mão de Obra e Serviços'!$A$4:$A$200,0)),0))) | K274: =IF($A274="","",I274*H274) | M274: =IF($A274="","",IF(B274="CÓDIGO?","CÓDIGO NÃO ACHADO",IF($D274="","FALTA ITEM DO ANEXO",IF($D274="INDIRETO","",IF(COUNTIFS('Anexo III'!$B$8:$B$400,$D274,'Anexo III'!$E$8:$E$400,">0")=0,"ITEM NÃO ACHADO NO ANEXO","")))))
B275: =IF($A275="","",IF(ISNUMBER(MATCH($A275,'Cotação de Materiais'!$A$4:$A$200,0)),"MAT",IF(ISNUMBER(MATCH($A275,'Mão de Obra e Serviços'!$A$4:$A$200,0)),"MO","CÓDIGO?"))) | C275: =IF($A275="","",IFERROR(INDEX('Cotação de Materiais'!$C$4:$C$200,MATCH($A275,'Cotação de Materiais'!$A$4:$A$200,0)),IFERROR(INDEX('Mão de Obra e Serviços'!$B$4:$B$200,MATCH($A275,'Mão de Obra e Serviços'!$A$4:$A$200,0)),""))) | G275: =IF($A275="","",E275*IF(F275="",1,F275)) | H275: =IF($A275="","",IF(SUMIF($A$6:$A$600,$A275,$G$6:$G$600)=0,0,G275/SUMIF($A$6:$A$600,$A275,$G$6:$G$600))) | I275: =IF($A275="","",IFERROR(INDEX('Cotação de Materiais'!$H$4:$H$200,MATCH($A275,'Cotação de Materiais'!$A$4:$A$200,0)),IFERROR(INDEX('Mão de Obra e Serviços'!$G$4:$G$200,MATCH($A275,'Mão de Obra e Serviços'!$A$4:$A$200,0)),0))) | K275: =IF($A275="","",I275*H275) | M275: =IF($A275="","",IF(B275="CÓDIGO?","CÓDIGO NÃO ACHADO",IF($D275="","FALTA ITEM DO ANEXO",IF($D275="INDIRETO","",IF(COUNTIFS('Anexo III'!$B$8:$B$400,$D275,'Anexo III'!$E$8:$E$400,">0")=0,"ITEM NÃO ACHADO NO ANEXO","")))))
B276: =IF($A276="","",IF(ISNUMBER(MATCH($A276,'Cotação de Materiais'!$A$4:$A$200,0)),"MAT",IF(ISNUMBER(MATCH($A276,'Mão de Obra e Serviços'!$A$4:$A$200,0)),"MO","CÓDIGO?"))) | C276: =IF($A276="","",IFERROR(INDEX('Cotação de Materiais'!$C$4:$C$200,MATCH($A276,'Cotação de Materiais'!$A$4:$A$200,0)),IFERROR(INDEX('Mão de Obra e Serviços'!$B$4:$B$200,MATCH($A276,'Mão de Obra e Serviços'!$A$4:$A$200,0)),""))) | G276: =IF($A276="","",E276*IF(F276="",1,F276)) | H276: =IF($A276="","",IF(SUMIF($A$6:$A$600,$A276,$G$6:$G$600)=0,0,G276/SUMIF($A$6:$A$600,$A276,$G$6:$G$600))) | I276: =IF($A276="","",IFERROR(INDEX('Cotação de Materiais'!$H$4:$H$200,MATCH($A276,'Cotação de Materiais'!$A$4:$A$200,0)),IFERROR(INDEX('Mão de Obra e Serviços'!$G$4:$G$200,MATCH($A276,'Mão de Obra e Serviços'!$A$4:$A$200,0)),0))) | K276: =IF($A276="","",I276*H276) | M276: =IF($A276="","",IF(B276="CÓDIGO?","CÓDIGO NÃO ACHADO",IF($D276="","FALTA ITEM DO ANEXO",IF($D276="INDIRETO","",IF(COUNTIFS('Anexo III'!$B$8:$B$400,$D276,'Anexo III'!$E$8:$E$400,">0")=0,"ITEM NÃO ACHADO NO ANEXO","")))))
B277: =IF($A277="","",IF(ISNUMBER(MATCH($A277,'Cotação de Materiais'!$A$4:$A$200,0)),"MAT",IF(ISNUMBER(MATCH($A277,'Mão de Obra e Serviços'!$A$4:$A$200,0)),"MO","CÓDIGO?"))) | C277: =IF($A277="","",IFERROR(INDEX('Cotação de Materiais'!$C$4:$C$200,MATCH($A277,'Cotação de Materiais'!$A$4:$A$200,0)),IFERROR(INDEX('Mão de Obra e Serviços'!$B$4:$B$200,MATCH($A277,'Mão de Obra e Serviços'!$A$4:$A$200,0)),""))) | G277: =IF($A277="","",E277*IF(F277="",1,F277)) | H277: =IF($A277="","",IF(SUMIF($A$6:$A$600,$A277,$G$6:$G$600)=0,0,G277/SUMIF($A$6:$A$600,$A277,$G$6:$G$600))) | I277: =IF($A277="","",IFERROR(INDEX('Cotação de Materiais'!$H$4:$H$200,MATCH($A277,'Cotação de Materiais'!$A$4:$A$200,0)),IFERROR(INDEX('Mão de Obra e Serviços'!$G$4:$G$200,MATCH($A277,'Mão de Obra e Serviços'!$A$4:$A$200,0)),0))) | K277: =IF($A277="","",I277*H277) | M277: =IF($A277="","",IF(B277="CÓDIGO?","CÓDIGO NÃO ACHADO",IF($D277="","FALTA ITEM DO ANEXO",IF($D277="INDIRETO","",IF(COUNTIFS('Anexo III'!$B$8:$B$400,$D277,'Anexo III'!$E$8:$E$400,">0")=0,"ITEM NÃO ACHADO NO ANEXO","")))))
B278: =IF($A278="","",IF(ISNUMBER(MATCH($A278,'Cotação de Materiais'!$A$4:$A$200,0)),"MAT",IF(ISNUMBER(MATCH($A278,'Mão de Obra e Serviços'!$A$4:$A$200,0)),"MO","CÓDIGO?"))) | C278: =IF($A278="","",IFERROR(INDEX('Cotação de Materiais'!$C$4:$C$200,MATCH($A278,'Cotação de Materiais'!$A$4:$A$200,0)),IFERROR(INDEX('Mão de Obra e Serviços'!$B$4:$B$200,MATCH($A278,'Mão de Obra e Serviços'!$A$4:$A$200,0)),""))) | G278: =IF($A278="","",E278*IF(F278="",1,F278)) | H278: =IF($A278="","",IF(SUMIF($A$6:$A$600,$A278,$G$6:$G$600)=0,0,G278/SUMIF($A$6:$A$600,$A278,$G$6:$G$600))) | I278: =IF($A278="","",IFERROR(INDEX('Cotação de Materiais'!$H$4:$H$200,MATCH($A278,'Cotação de Materiais'!$A$4:$A$200,0)),IFERROR(INDEX('Mão de Obra e Serviços'!$G$4:$G$200,MATCH($A278,'Mão de Obra e Serviços'!$A$4:$A$200,0)),0))) | K278: =IF($A278="","",I278*H278) | M278: =IF($A278="","",IF(B278="CÓDIGO?","CÓDIGO NÃO ACHADO",IF($D278="","FALTA ITEM DO ANEXO",IF($D278="INDIRETO","",IF(COUNTIFS('Anexo III'!$B$8:$B$400,$D278,'Anexo III'!$E$8:$E$400,">0")=0,"ITEM NÃO ACHADO NO ANEXO","")))))
B279: =IF($A279="","",IF(ISNUMBER(MATCH($A279,'Cotação de Materiais'!$A$4:$A$200,0)),"MAT",IF(ISNUMBER(MATCH($A279,'Mão de Obra e Serviços'!$A$4:$A$200,0)),"MO","CÓDIGO?"))) | C279: =IF($A279="","",IFERROR(INDEX('Cotação de Materiais'!$C$4:$C$200,MATCH($A279,'Cotação de Materiais'!$A$4:$A$200,0)),IFERROR(INDEX('Mão de Obra e Serviços'!$B$4:$B$200,MATCH($A279,'Mão de Obra e Serviços'!$A$4:$A$200,0)),""))) | G279: =IF($A279="","",E279*IF(F279="",1,F279)) | H279: =IF($A279="","",IF(SUMIF($A$6:$A$600,$A279,$G$6:$G$600)=0,0,G279/SUMIF($A$6:$A$600,$A279,$G$6:$G$600))) | I279: =IF($A279="","",IFERROR(INDEX('Cotação de Materiais'!$H$4:$H$200,MATCH($A279,'Cotação de Materiais'!$A$4:$A$200,0)),IFERROR(INDEX('Mão de Obra e Serviços'!$G$4:$G$200,MATCH($A279,'Mão de Obra e Serviços'!$A$4:$A$200,0)),0))) | K279: =IF($A279="","",I279*H279) | M279: =IF($A279="","",IF(B279="CÓDIGO?","CÓDIGO NÃO ACHADO",IF($D279="","FALTA ITEM DO ANEXO",IF($D279="INDIRETO","",IF(COUNTIFS('Anexo III'!$B$8:$B$400,$D279,'Anexo III'!$E$8:$E$400,">0")=0,"ITEM NÃO ACHADO NO ANEXO","")))))
... B600: =IF($A600="","",IF(ISNUMBER(MATCH($A600,'Cotação de Materiais'!$A$4:$A$200,0)),"MAT",IF(ISNUMBER(MATCH($A600,'Mão de Obra e Serviços'!$A$4:$A$200,0)),"MO","CÓDIGO?"))) | C600: =IF($A600="","",IFERROR(INDEX('Cotação de Materiais'!$C$4:$C$200,MATCH($A600,'Cotação de Materiais'!$A$4:$A$200,0)),IFERROR(INDEX('Mão de Obra e Serviços'!$B$4:$B$200,MATCH($A600,'Mão de Obra e Serviços'!$A$4:$A$200,0)),""))) | G600: =IF($A600="","",E600*IF(F600="",1,F600)) | H600: =IF($A600="","",IF(SUMIF($A$6:$A$600,$A600,$G$6:$G$600)=0,0,G600/SUMIF($A$6:$A$600,$A600,$G$6:$G$600))) | I600: =IF($A600="","",IFERROR(INDEX('Cotação de Materiais'!$H$4:$H$200,MATCH($A600,'Cotação de Materiais'!$A$4:$A$200,0)),IFERROR(INDEX('Mão de Obra e Serviços'!$G$4:$G$200,MATCH($A600,'Mão de Obra e Serviços'!$A$4:$A$200,0)),0))) | K600: =IF($A600="","",I600*H600) | M600: =IF($A600="","",IF(B600="CÓDIGO?","CÓDIGO NÃO ACHADO",IF($D600="","FALTA ITEM DO ANEXO",IF($D600="INDIRETO","",IF(COUNTIFS('Anexo III'!$B$8:$B$400,$D600,'Anexo III'!$E$8:$E$400,">0")=0,"ITEM NÃO ACHADO NO ANEXO","")))))

Sheet Anexo III
A1: ANEXO III — PREÇOS GERADOS PARA A PLANILHA DO SESC
A2: CÓPIA INTERLIGADA DA PLANILHA DO SESC: mesma linha e mesmas colunas F (material) e G (MO) da oficial. Para preencher a oficial: copie o bloco indicado na coluna M e cole na MESMA faixa da oficial com COLAR ESPECIAL > VALORES (Ctrl+Alt+V > Valores). Nunca colar normal: leva fórmula e cria vínculo externo.
C3: TOTAL DO ANEXO → | E3: Centavos: | F3: =ROUND(Precificação!B8-SUMPRODUCT(E8:E400,V8:V400)-SUMPRODUCT(E8:E400,W8:W400),2) -> -0.42 | I3: =SUM(I8:I400) -> 149738.47 | J3: =SUM(J8:J400) -> 189761.53 | K3: =SUM(K8:K400) -> 339500 | L3: =IF(AND(ABS(K3-Precificação!B8)<0.005,Precificação!B30=0),"FECHA NO PREÇO","NÃO FECHA / CONFERIR RATEIO") -> FECHA NO PREÇO | N3: =SUM(N8:N400) -> 78254.481 | O3: =SUM(O8:O400) -> 98194.333 | P3: =SUM(P8:P400) -> 280 | Q3: =SUM(Q8:Q400) -> 20367.667 | R3: =SUM(R8:R400) -> 197096.48 | S3: =SUM(S8:S400) -> 149736.24 | T3: =SUM(T8:T400) -> 189763.76
A4: Nova licitação: cole Item / Item memorial / Descrição / Un / Qtd nas colunas A–E nas MESMAS linhas em que estão na planilha oficial. | P4: Indireto material a ratear: | R4: ='Rateio Anexo'!G3 -> 280 | S4: Indireto MO a ratear: | T4: ='Rateio Anexo'!K3 -> 20367.667
N5: CÁLCULO (não copiar) →
A7: ITEM | B7: ITEM MEMORIAL | C7: DESCRIÇÃO | D7: UN. | E7: QDE. | F7: UNIT. MATERIAL | G7: UNIT. MÃO-DE-OBRA | H7: UNIT. TOTAL | I7: TOTAL MATERIAL | J7: TOTAL MÃO-DE-OBRA | K7: TOTAL | L7: STATUS | M7: COLAR NA OFICIAL (valores) | N7: Custo mat. direto | O7: Custo MO direto | P7: Custo mat. indireto | Q7: Custo MO indireto | R7: Custo total | S7: Venda material | T7: Venda MO | U7: Grade (R$) | V7: Unit. mat. arred. | W7: Unit. MO arred. | X7: fim bloco
B8: A | C8: PROJETO EXPOGRAFICO | F8: =IF($E8="","",V8) | G8: =IF($E8="","",ROUND(W8+IF($B8=Precificação!$B$26,$F$3/$E8,0),2)) | H8: =IF($E8="","",F8+G8) | I8: =IF($E8="","",$E8*F8) | J8: =IF($E8="","",$E8*G8) | K8: =IF($E8="","",I8+J8) | L8: =IF($E8="","",IF(R8=0,"SEM CUSTO — falta linha de custo","OK")) | M8: =IF(AND(ISNUMBER(E8),NOT(ISNUMBER(E7))),"F"&ROW()&":G"&X8,"") | N8: =IF($E8="","",SUMIFS('Rateio Anexo'!$K$6:$K$600,'Rateio Anexo'!$D$6:$D$600,$B8,'Rateio Anexo'!$B$6:$B$600,"MAT")) | O8: =IF($E8="","",SUMIFS('Rateio Anexo'!$K$6:$K$600,'Rateio Anexo'!$D$6:$D$600,$B8,'Rateio Anexo'!$B$6:$B$600,"MO")) | P8: =IF($E8="","",IF($N$3=0,0,N8/$N$3*$R$4)) | Q8: =IF($E8="","",IF($O$3=0,0,O8/$O$3*$T$4)) | R8: =IF($E8="","",N8+O8+P8+Q8) | S8: =IF($E8="","",(N8+P8)*Precificação!$B$19) | T8: =IF($E8="","",(O8+Q8)*Precificação!$B$20) | U8: =IF($E8="","",IF($E8=INT($E8),0.01,IF($E8*2=INT($E8*2),0.02,0.05))) | V8: =IF($E8="","",ROUND(S8/$E8/U8,0)*U8) | W8: =IF($E8="","",ROUND(T8/$E8/U8,0)*U8) | X8: =IF(NOT(ISNUMBER(E8)),"",IF(NOT(ISNUMBER(E9)),ROW(),X9))
A9: 1 | B9: A.1 | C9: Estrutura metálica para reforço da instalação de obra no painel (P05) Detalhes técnicos na prancha 2 do Projeto expografico | F9: =IF($E9="","",V9) | G9: =IF($E9="","",ROUND(W9+IF($B9=Precificação!$B$26,$F$3/$E9,0),2)) | H9: =IF($E9="","",F9+G9) | I9: =IF($E9="","",$E9*F9) | J9: =IF($E9="","",$E9*G9) | K9: =IF($E9="","",I9+J9) | L9: =IF($E9="","",IF(R9=0,"SEM CUSTO — falta linha de custo","OK")) | M9: =IF(AND(ISNUMBER(E9),NOT(ISNUMBER(E8))),"F"&ROW()&":G"&X9,"") | N9: =IF($E9="","",SUMIFS('Rateio Anexo'!$K$6:$K$600,'Rateio Anexo'!$D$6:$D$600,$B9,'Rateio Anexo'!$B$6:$B$600,"MAT")) | O9: =IF($E9="","",SUMIFS('Rateio Anexo'!$K$6:$K$600,'Rateio Anexo'!$D$6:$D$600,$B9,'Rateio Anexo'!$B$6:$B$600,"MO")) | P9: =IF($E9="","",IF($N$3=0,0,N9/$N$3*$R$4)) | Q9: =IF($E9="","",IF($O$3=0,0,O9/$O$3*$T$4)) | R9: =IF($E9="","",N9+O9+P9+Q9) | S9: =IF($E9="","",(N9+P9)*Precificação!$B$19) | T9: =IF($E9="","",(O9+Q9)*Precificação!$B$20) | U9: =IF($E9="","",IF($E9=INT($E9),0.01,IF($E9*2=INT($E9*2),0.02,0.05))) | V9: =IF($E9="","",ROUND(S9/$E9/U9,0)*U9) | W9: =IF($E9="","",ROUND(T9/$E9/U9,0)*U9) | X9: =IF(NOT(ISNUMBER(E9)),"",IF(NOT(ISNUMBER(E10)),ROW(),X10))
A10: 2 | B10: A.1.1 | C10: Molduras metálicas de 37x93cm, feitas com barra de metalon de 50x50mm, formando uma moldura chumbada em uma caixa de marcenaria com estrutura metálica interna, reforços e contrapesos. A peça deve ser feita exatamente na largura do barco, para que ele possa entrar nesse espaço da moldura e ficar fixo apenas pela pressão exercida para travá-lo. Ainda é preciso avaliar se será permitida alguma furação ou ponto de fixação no barco/obra de arte. | D10: unid | E10: 2 | F10: =IF($E10="","",V10) -> 3836.47 | G10: =IF($E10="","",ROUND(W10+IF($B10=Precificação!$B$26,$F$3/$E10,0),2)) -> 1240.75 | H10: =IF($E10="","",F10+G10) -> 5077.22 | I10: =IF($E10="","",$E10*F10) -> 7672.94 | J10: =IF($E10="","",$E10*G10) -> 2481.5 | K10: =IF($E10="","",I10+J10) -> 10154.44 | L10: =IF($E10="","",IF(R10=0,"SEM CUSTO — falta linha de custo","OK")) -> OK | M10: =IF(AND(ISNUMBER(E10),NOT(ISNUMBER(E9))),"F"&ROW()&":G"&X10,"") -> F10:G13 | N10: =IF($E10="","",SUMIFS('Rateio Anexo'!$K$6:$K$600,'Rateio Anexo'!$D$6:$D$600,$B10,'Rateio Anexo'!$B$6:$B$600,"MAT")) -> 4010 | O10: =IF($E10="","",SUMIFS('Rateio Anexo'!$K$6:$K$600,'Rateio Anexo'!$D$6:$D$600,$B10,'Rateio Anexo'!$B$6:$B$600,"MO")) -> 1284.0635 | P10: =IF($E10="","",IF($N$3=0,0,N10/$N$3*$R$4)) -> 14.34806 | Q10: =IF($E10="","",IF($O$3=0,0,O10/$O$3*$T$4)) -> 266.34304 | R10: =IF($E10="","",N10+O10+P10+Q10) -> 5574.7546 | S10: =IF($E10="","",(N10+P10)*Precificação!$B$19) -> 7672.9449 | T10: =IF($E10="","",(O10+Q10)*Precificação!$B$20) -> 2481.4947 | U10: =IF($E10="","",IF($E10=INT($E10),0.01,IF($E10*2=INT($E10*2),0.02,0.05))) -> 0.01 | V10: =IF($E10="","",ROUND(S10/$E10/U10,0)*U10) -> 3836.47 | W10: =IF($E10="","",ROUND(T10/$E10/U10,0)*U10) -> 1240.75 | X10: =IF(NOT(ISNUMBER(E10)),"",IF(NOT(ISNUMBER(E11)),ROW(),X11)) -> 13
A11: 3 | B11: A.1.2 | C11: 4 Barracudas metálicas de 50x50mm com parede de 3mm de espessura com 208cm de comprimento, prensada na laje do espaço e na moldura. Ter uma sapata regulável com chapa metálica na duas pontas da barracuda, seguindo detalhes do projeto de estrutura. | D11: unid | E11: 4 | F11: =IF($E11="","",V11) -> 797.07 | G11: =IF($E11="","",ROUND(W11+IF($B11=Precificação!$B$26,$F$3/$E11,0),2)) -> 627.33 | H11: =IF($E11="","",F11+G11) -> 1424.4 | I11: =IF($E11="","",$E11*F11) -> 3188.28 | J11: =IF($E11="","",$E11*G11) -> 2509.32 | K11: =IF($E11="","",I11+J11) -> 5697.6 | L11: =IF($E11="","",IF(R11=0,"SEM CUSTO — falta linha de custo","OK")) -> OK | M11: =IF(AND(ISNUMBER(E11),NOT(ISNUMBER(E10))),"F"&ROW()&":G"&X11,"") | N11: =IF($E11="","",SUMIFS('Rateio Anexo'!$K$6:$K$600,'Rateio Anexo'!$D$6:$D$600,$B11,'Rateio Anexo'!$B$6:$B$600,"MAT")) -> 1666.25 | O11: =IF($E11="","",SUMIFS('Rateio Anexo'!$K$6:$K$600,'Rateio Anexo'!$D$6:$D$600,$B11,'Rateio Anexo'!$B$6:$B$600,"MO")) -> 1298.4609 | P11: =IF($E11="","",IF($N$3=0,0,N11/$N$3*$R$4)) -> 5.9619589 | Q11: =IF($E11="","",IF($O$3=0,0,O11/$O$3*$T$4)) -> 269.32939 | R11: =IF($E11="","",N11+O11+P11+Q11) -> 3240.0023 | S11: =IF($E11="","",(N11+P11)*Precificação!$B$19) -> 3188.2904 | T11: =IF($E11="","",(O11+Q11)*Precificação!$B$20) -> 2509.3182 | U11: =IF($E11="","",IF($E11=INT($E11),0.01,IF($E11*2=INT($E11*2),0.02,0.05))) -> 0.01 | V11: =IF($E11="","",ROUND(S11/$E11/U11,0)*U11) -> 797.07 | W11: =IF($E11="","",ROUND(T11/$E11/U11,0)*U11) -> 627.33 | X11: =IF(NOT(ISNUMBER(E11)),"",IF(NOT(ISNUMBER(E12)),ROW(),X12)) -> 13
A12: 4 | B12: A.1.3 | C12: Mão-francesa metálica de 40x40cm feita com tubo metálico de 50x50mm instalado embaixo do barco para dar maior sustentação — seguir detalhes indicados no desenho, sendo essa peça composta totalmente de ferro e chapa maciça metálica de 3mm. | D12: unid | E12: 2 | F12: =IF($E12="","",V12) -> 535.77 | G12: =IF($E12="","",ROUND(W12+IF($B12=Precificação!$B$26,$F$3/$E12,0),2)) -> 421.67 | H12: =IF($E12="","",F12+G12) -> 957.44 | I12: =IF($E12="","",$E12*F12) -> 1071.54 | J12: =IF($E12="","",$E12*G12) -> 843.34 | K12: =IF($E12="","",I12+J12) -> 1914.88 | L12: =IF($E12="","",IF(R12=0,"SEM CUSTO — falta linha de custo","OK")) -> OK | M12: =IF(AND(ISNUMBER(E12),NOT(ISNUMBER(E11))),"F"&ROW()&":G"&X12,"") | N12: =IF($E12="","",SUMIFS('Rateio Anexo'!$K$6:$K$600,'Rateio Anexo'!$D$6:$D$600,$B12,'Rateio Anexo'!$B$6:$B$600,"MAT")) -> 560 | O12: =IF($E12="","",SUMIFS('Rateio Anexo'!$K$6:$K$600,'Rateio Anexo'!$D$6:$D$600,$B12,'Rateio Anexo'!$B$6:$B$600,"MO")) -> 436.39197 | P12: =IF($E12="","",IF($N$3=0,0,N12/$N$3*$R$4)) -> 2.0037191 | Q12: =IF($E12="","",IF($O$3=0,0,O12/$O$3*$T$4)) -> 90.517303 | R12: =IF($E12="","",N12+O12+P12+Q12) -> 1088.913 | S12: =IF($E12="","",(N12+P12)*Precificação!$B$19) -> 1071.5335 | T12: =IF($E12="","",(O12+Q12)*Precificação!$B$20) -> 843.34176 | U12: =IF($E12="","",IF($E12=INT($E12),0.01,IF($E12*2=INT($E12*2),0.02,0.05))) -> 0.01 | V12: =IF($E12="","",ROUND(S12/$E12/U12,0)*U12) -> 535.77 | W12: =IF($E12="","",ROUND(T12/$E12/U12,0)*U12) -> 421.67 | X12: =IF(NOT(ISNUMBER(E12)),"",IF(NOT(ISNUMBER(E13)),ROW(),X13)) -> 13
A13: 5 | B13: A.1.4 | C13: Base metálica de 9x450x120cm para distribuição de peso das esculturas da artista Solange Pessoa. Peça com perfil de 50x50mm e 5mm de espessura na parede interna, apoiada diretamente no piso, sobre a qual serão fixadas duas chapas de MDF de 18mm. | D13: unid | E13: 1 | F13: =IF($E13="","",V13) -> 6295.26 | G13: =IF($E13="","",ROUND(W13+IF($B13=Precificação!$B$26,$F$3/$E13,0),2)) -> 4954.63 | H13: =IF($E13="","",F13+G13) -> 11249.89 | I13: =IF($E13="","",$E13*F13) -> 6295.26 | J13: =IF($E13="","",$E13*G13) -> 4954.63 | K13: =IF($E13="","",I13+J13) -> 11249.89 | L13: =IF($E13="","",IF(R13=0,"SEM CUSTO — falta linha de custo","OK")) -> OK | M13: =IF(AND(ISNUMBER(E13),NOT(ISNUMBER(E12))),"F"&ROW()&":G"&X13,"") | N13: =IF($E13="","",SUMIFS('Rateio Anexo'!$K$6:$K$600,'Rateio Anexo'!$D$6:$D$600,$B13,'Rateio Anexo'!$B$6:$B$600,"MAT")) -> 3290 | O13: =IF($E13="","",SUMIFS('Rateio Anexo'!$K$6:$K$600,'Rateio Anexo'!$D$6:$D$600,$B13,'Rateio Anexo'!$B$6:$B$600,"MO")) -> 2563.8028 | P13: =IF($E13="","",IF($N$3=0,0,N13/$N$3*$R$4)) -> 11.77185 | Q13: =IF($E13="","",IF($O$3=0,0,O13/$O$3*$T$4)) -> 531.78916 | R13: =IF($E13="","",N13+O13+P13+Q13) -> 6397.3639 | S13: =IF($E13="","",(N13+P13)*Precificação!$B$19) -> 6295.2591 | T13: =IF($E13="","",(O13+Q13)*Precificação!$B$20) -> 4954.6328 | U13: =IF($E13="","",IF($E13=INT($E13),0.01,IF($E13*2=INT($E13*2),0.02,0.05))) -> 0.01 | V13: =IF($E13="","",ROUND(S13/$E13/U13,0)*U13) -> 6295.26 | W13: =IF($E13="","",ROUND(T13/$E13/U13,0)*U13) -> 4954.63 | X13: =IF(NOT(ISNUMBER(E13)),"",IF(NOT(ISNUMBER(E14)),ROW(),X14)) -> 13
A14: 6 | B14: A.2 | C14: Painéis a serem construidos: construção e pintura de painéis em MDF 18mm, conforme indicações técnicas da folha 01 do projeto expográfico. Metros lineares totais de painéis: 72m. Área total dos painéis: 240m². Prever ignifugação do MDF em todos os painéis. | F14: =IF($E14="","",V14) | G14: =IF($E14="","",ROUND(W14+IF($B14=Precificação!$B$26,$F$3/$E14,0),2)) | H14: =IF($E14="","",F14+G14) | I14: =IF($E14="","",$E14*F14) | J14: =IF($E14="","",$E14*G14) | K14: =IF($E14="","",I14+J14) | L14: =IF($E14="","",IF(R14=0,"SEM CUSTO — falta linha de custo","OK")) | M14: =IF(AND(ISNUMBER(E14),NOT(ISNUMBER(E13))),"F"&ROW()&":G"&X14,"") | N14: =IF($E14="","",SUMIFS('Rateio Anexo'!$K$6:$K$600,'Rateio Anexo'!$D$6:$D$600,$B14,'Rateio Anexo'!$B$6:$B$600,"MAT")) | O14: =IF($E14="","",SUMIFS('Rateio Anexo'!$K$6:$K$600,'Rateio Anexo'!$D$6:$D$600,$B14,'Rateio Anexo'!$B$6:$B$600,"MO")) | P14: =IF($E14="","",IF($N$3=0,0,N14/$N$3*$R$4)) | Q14: =IF($E14="","",IF($O$3=0,0,O14/$O$3*$T$4)) | R14: =IF($E14="","",N14+O14+P14+Q14) | S14: =IF($E14="","",(N14+P14)*Precificação!$B$19) | T14: =IF($E14="","",(O14+Q14)*Precificação!$B$20) | U14: =IF($E14="","",IF($E14=INT($E14),0.01,IF($E14*2=INT($E14*2),0.02,0.05))) | V14: =IF($E14="","",ROUND(S14/$E14/U14,0)*U14) | W14: =IF($E14="","",ROUND(T14/$E14/U14,0)*U14) | X14: =IF(NOT(ISNUMBER(E14)),"",IF(NOT(ISNUMBER(E15)),ROW(),X15))
A15: 7 | B15: A.2.1 | C15: (P01) Painel de MDF de 18mm, com estrutura interna de pontalete 5x5cm e acabamento em pintura acrílica fosca Terra Roxa, da Suvinil. Dimensões gerais: 4,5m lineares, altura do painel de 2,9m, área total de 14m². | D15: m2 | E15: 14 | F15: =IF($E15="","",V15) -> 145.01 | G15: =IF($E15="","",ROUND(W15+IF($B15=Precificação!$B$26,$F$3/$E15,0),2)) -> 228.71 | H15: =IF($E15="","",F15+G15) -> 373.72 | I15: =IF($E15="","",$E15*F15) -> 2030.14 | J15: =IF($E15="","",$E15*G15) -> 3201.94 | K15: =IF($E15="","",I15+J15) -> 5232.08 | L15: =IF($E15="","",IF(R15=0,"SEM CUSTO — falta linha de custo","OK")) -> OK | M15: =IF(AND(ISNUMBER(E15),NOT(ISNUMBER(E14))),"F"&ROW()&":G"&X15,"") -> F15:G23 | N15: =IF($E15="","",SUMIFS('Rateio Anexo'!$K$6:$K$600,'Rateio Anexo'!$D$6:$D$600,$B15,'Rateio Anexo'!$B$6:$B$600,"MAT")) -> 1060.9503 | O15: =IF($E15="","",SUMIFS('Rateio Anexo'!$K$6:$K$600,'Rateio Anexo'!$D$6:$D$600,$B15,'Rateio Anexo'!$B$6:$B$600,"MO")) -> 1656.8406 | P15: =IF($E15="","",IF($N$3=0,0,N15/$N$3*$R$4)) -> 3.7961542 | Q15: =IF($E15="","",IF($O$3=0,0,O15/$O$3*$T$4)) -> 343.66522 | R15: =IF($E15="","",N15+O15+P15+Q15) -> 3065.2522 | S15: =IF($E15="","",(N15+P15)*Precificação!$B$19) -> 2030.0781 | T15: =IF($E15="","",(O15+Q15)*Precificação!$B$20) -> 3201.8986 | U15: =IF($E15="","",IF($E15=INT($E15),0.01,IF($E15*2=INT($E15*2),0.02,0.05))) -> 0.01 | V15: =IF($E15="","",ROUND(S15/$E15/U15,0)*U15) -> 145.01 | W15: =IF($E15="","",ROUND(T15/$E15/U15,0)*U15) -> 228.71 | X15: =IF(NOT(ISNUMBER(E15)),"",IF(NOT(ISNUMBER(E16)),ROW(),X16)) -> 23
A16: 8 | B16: A.2.2 | C16: (P02) Painel de MDF de 18mm, com estrutura interna de pontalete 5x5cm e acabamento em pintura acrílica fosca Terra Roxa, da Suvinil. Dimensões gerais: 4,1m lineares, altura do painel de 2,9m, área total de 11,8m². | D16: m2 | E16: 11.8 | F16: =IF($E16="","",V16) -> 145 | G16: =IF($E16="","",ROUND(W16+IF($B16=Precificação!$B$26,$F$3/$E16,0),2)) -> 228.7 | H16: =IF($E16="","",F16+G16) -> 373.7 | I16: =IF($E16="","",$E16*F16) -> 1711 | J16: =IF($E16="","",$E16*G16) -> 2698.66 | K16: =IF($E16="","",I16+J16) -> 4409.66 | L16: =IF($E16="","",IF(R16=0,"SEM CUSTO — falta linha de custo","OK")) -> OK | M16: =IF(AND(ISNUMBER(E16),NOT(ISNUMBER(E15))),"F"&ROW()&":G"&X16,"") | N16: =IF($E16="","",SUMIFS('Rateio Anexo'!$K$6:$K$600,'Rateio Anexo'!$D$6:$D$600,$B16,'Rateio Anexo'!$B$6:$B$600,"MAT")) -> 894.22952 | O16: =IF($E16="","",SUMIFS('Rateio Anexo'!$K$6:$K$600,'Rateio Anexo'!$D$6:$D$600,$B16,'Rateio Anexo'!$B$6:$B$600,"MO")) -> 1396.4799 | P16: =IF($E16="","",IF($N$3=0,0,N16/$N$3*$R$4)) -> 3.1996157 | Q16: =IF($E16="","",IF($O$3=0,0,O16/$O$3*$T$4)) -> 289.66068 | R16: =IF($E16="","",N16+O16+P16+Q16) -> 2583.5697 | S16: =IF($E16="","",(N16+P16)*Precificação!$B$19) -> 1711.0658 | T16: =IF($E16="","",(O16+Q16)*Precificação!$B$20) -> 2698.7431 | U16: =IF($E16="","",IF($E16=INT($E16),0.01,IF($E16*2=INT($E16*2),0.02,0.05))) -> 0.05 | V16: =IF($E16="","",ROUND(S16/$E16/U16,0)*U16) -> 145 | W16: =IF($E16="","",ROUND(T16/$E16/U16,0)*U16) -> 228.7 | X16: =IF(NOT(ISNUMBER(E16)),"",IF(NOT(ISNUMBER(E17)),ROW(),X17)) -> 23
A17: 9 | B17: A.2.3 | C17: (P03) Painel de MDF de 18mm, com estrutura interna de pontalete 5x5cm e acabamento em pintura acrílica fosca Terra Roxa, da Suvinil. Dimensões gerais: 11m lineares, altura do painel de 2,9m, área total de 32m². | D17: m2 | E17: 32 | F17: =IF($E17="","",V17) -> 145.01 | G17: =IF($E17="","",ROUND(W17+IF($B17=Precificação!$B$26,$F$3/$E17,0),2)) -> 228.71 | H17: =IF($E17="","",F17+G17) -> 373.72 | I17: =IF($E17="","",$E17*F17) -> 4640.32 | J17: =IF($E17="","",$E17*G17) -> 7318.72 | K17: =IF($E17="","",I17+J17) -> 11959.04 | L17: =IF($E17="","",IF(R17=0,"SEM CUSTO — falta linha de custo","OK")) -> OK | M17: =IF(AND(ISNUMBER(E17),NOT(ISNUMBER(E16))),"F"&ROW()&":G"&X17,"") | N17: =IF($E17="","",SUMIFS('Rateio Anexo'!$K$6:$K$600,'Rateio Anexo'!$D$6:$D$600,$B17,'Rateio Anexo'!$B$6:$B$600,"MAT")) -> 2425.0292 | O17: =IF($E17="","",SUMIFS('Rateio Anexo'!$K$6:$K$600,'Rateio Anexo'!$D$6:$D$600,$B17,'Rateio Anexo'!$B$6:$B$600,"MO")) -> 3787.0642 | P17: =IF($E17="","",IF($N$3=0,0,N17/$N$3*$R$4)) -> 8.6769239 | Q17: =IF($E17="","",IF($O$3=0,0,O17/$O$3*$T$4)) -> 785.52049 | R17: =IF($E17="","",N17+O17+P17+Q17) -> 7006.2908 | S17: =IF($E17="","",(N17+P17)*Precificação!$B$19) -> 4640.1785 | T17: =IF($E17="","",(O17+Q17)*Precificação!$B$20) -> 7318.6254 | U17: =IF($E17="","",IF($E17=INT($E17),0.01,IF($E17*2=INT($E17*2),0.02,0.05))) -> 0.01 | V17: =IF($E17="","",ROUND(S17/$E17/U17,0)*U17) -> 145.01 | W17: =IF($E17="","",ROUND(T17/$E17/U17,0)*U17) -> 228.71 | X17: =IF(NOT(ISNUMBER(E17)),"",IF(NOT(ISNUMBER(E18)),ROW(),X18)) -> 23
A18: 10 | B18: A.2.4 | C18: (P04) Painel de MDF de 18mm, com estrutura interna de pontalete 5x5cm e acabamento em pintura acrílica fosca Terra Roxa, da Suvinil. Dimensões gerais: 8,5 m lineares, altura do painel de 2,9m, área total de25m². | D18: m2 | E18: 25 | F18: =IF($E18="","",V18) -> 145.01 | G18: =IF($E18="","",ROUND(W18+IF($B18=Precificação!$B$26,$F$3/$E18,0),2)) -> 228.71 | H18: =IF($E18="","",F18+G18) -> 373.72 | I18: =IF($E18="","",$E18*F18) -> 3625.25 | J18: =IF($E18="","",$E18*G18) -> 5717.75 | K18: =IF($E18="","",I18+J18) -> 9343 | L18: =IF($E18="","",IF(R18=0,"SEM CUSTO — falta linha de custo","OK")) -> OK | M18: =IF(AND(ISNUMBER(E18),NOT(ISNUMBER(E17))),"F"&ROW()&":G"&X18,"") | N18: =IF($E18="","",SUMIFS('Rateio Anexo'!$K$6:$K$600,'Rateio Anexo'!$D$6:$D$600,$B18,'Rateio Anexo'!$B$6:$B$600,"MAT")) -> 1894.5541 | O18: =IF($E18="","",SUMIFS('Rateio Anexo'!$K$6:$K$600,'Rateio Anexo'!$D$6:$D$600,$B18,'Rateio Anexo'!$B$6:$B$600,"MO")) -> 2958.6439 | P18: =IF($E18="","",IF($N$3=0,0,N18/$N$3*$R$4)) -> 6.7788468 | Q18: =IF($E18="","",IF($O$3=0,0,O18/$O$3*$T$4)) -> 613.68789 | R18: =IF($E18="","",N18+O18+P18+Q18) -> 5473.6647 | S18: =IF($E18="","",(N18+P18)*Precificação!$B$19) -> 3625.1394 | T18: =IF($E18="","",(O18+Q18)*Precificação!$B$20) -> 5717.6761 | U18: =IF($E18="","",IF($E18=INT($E18),0.01,IF($E18*2=INT($E18*2),0.02,0.05))) -> 0.01 | V18: =IF($E18="","",ROUND(S18/$E18/U18,0)*U18) -> 145.01 | W18: =IF($E18="","",ROUND(T18/$E18/U18,0)*U18) -> 228.71 | X18: =IF(NOT(ISNUMBER(E18)),"",IF(NOT(ISNUMBER(E19)),ROW(),X19)) -> 23
A19: 11 | B19: A.2.5 | C19: (P05) Painel de MDF de 18mm, com estrutura interna de pontalete 5x5cm e acabamento em pintura acrílica fosca Terra Roxa, da Suvinil. Este painel vai precisar ser recortado para que o barco exposto na exposição adentre 50cm para dentro do painel. Após inserido o barco, um molde na medida do vão e do perfil do barco terá que ser feito para fabricação da peça de fechamento deste furo. Dimensões gerais: 5,67m lineares, altura do painel de 2,9m, área total de 16,5m². | D19: m2 | E19: 16.5 | F19: =IF($E19="","",V19) -> 145 | G19: =IF($E19="","",ROUND(W19+IF($B19=Precificação!$B$26,$F$3/$E19,0),2)) -> 305.32 | H19: =IF($E19="","",F19+G19) -> 450.32 | I19: =IF($E19="","",$E19*F19) -> 2392.5 | J19: =IF($E19="","",$E19*G19) -> 5037.78 | K19: =IF($E19="","",I19+J19) -> 7430.28 | L19: =IF($E19="","",IF(R19=0,"SEM CUSTO — falta linha de custo","OK")) -> OK | M19: =IF(AND(ISNUMBER(E19),NOT(ISNUMBER(E18))),"F"&ROW()&":G"&X19,"") | N19: =IF($E19="","",SUMIFS('Rateio Anexo'!$K$6:$K$600,'Rateio Anexo'!$D$6:$D$600,$B19,'Rateio Anexo'!$B$6:$B$600,"MAT")) -> 1250.4057 | O19: =IF($E19="","",SUMIFS('Rateio Anexo'!$K$6:$K$600,'Rateio Anexo'!$D$6:$D$600,$B19,'Rateio Anexo'!$B$6:$B$600,"MO")) -> 2606.7776 | P19: =IF($E19="","",IF($N$3=0,0,N19/$N$3*$R$4)) -> 4.4740389 | Q19: =IF($E19="","",IF($O$3=0,0,O19/$O$3*$T$4)) -> 540.70307 | R19: =IF($E19="","",N19+O19+P19+Q19) -> 4402.3604 | S19: =IF($E19="","",(N19+P19)*Precificação!$B$19) -> 2392.592 | T19: =IF($E19="","",(O19+Q19)*Precificação!$B$20) -> 5037.683 | U19: =IF($E19="","",IF($E19=INT($E19),0.01,IF($E19*2=INT($E19*2),0.02,0.05))) -> 0.02 | V19: =IF($E19="","",ROUND(S19/$E19/U19,0)*U19) -> 145 | W19: =IF($E19="","",ROUND(T19/$E19/U19,0)*U19) -> 305.32 | X19: =IF(NOT(ISNUMBER(E19)),"",IF(NOT(ISNUMBER(E20)),ROW(),X20)) -> 23
A20: 12 | B20: A.2.6 | C20: (P06) Painel de MDF de 18mm, com estrutura interna de pontalete 5x5cm e acabamento em pintura acrílica fosca Papel de Seda, da Suvinil. Acoplada a este painel, deverá ser contemplada uma base de 50x30cm em MDF de 18mm. Dimensões gerais: 1,2m lineares, altura do painel de 2,9m, área total de 3,8m² | D20: m2 | E20: 3.8 | F20: =IF($E20="","",V20) -> 148.3 | G20: =IF($E20="","",ROUND(W20+IF($B20=Precificação!$B$26,$F$3/$E20,0),2)) -> 228.7 | H20: =IF($E20="","",F20+G20) -> 377 | I20: =IF($E20="","",$E20*F20) -> 563.54 | J20: =IF($E20="","",$E20*G20) -> 869.06 | K20: =IF($E20="","",I20+J20) -> 1432.6 | L20: =IF($E20="","",IF(R20=0,"SEM CUSTO — falta linha de custo","OK")) -> OK | M20: =IF(AND(ISNUMBER(E20),NOT(ISNUMBER(E19))),"F"&ROW()&":G"&X20,"") | N20: =IF($E20="","",SUMIFS('Rateio Anexo'!$K$6:$K$600,'Rateio Anexo'!$D$6:$D$600,$B20,'Rateio Anexo'!$B$6:$B$600,"MAT")) -> 294.49164 | O20: =IF($E20="","",SUMIFS('Rateio Anexo'!$K$6:$K$600,'Rateio Anexo'!$D$6:$D$600,$B20,'Rateio Anexo'!$B$6:$B$600,"MO")) -> 449.71387 | P20: =IF($E20="","",IF($N$3=0,0,N20/$N$3*$R$4)) -> 1.0537116 | Q20: =IF($E20="","",IF($O$3=0,0,O20/$O$3*$T$4)) -> 93.280559 | R20: =IF($E20="","",N20+O20+P20+Q20) -> 838.53978 | S20: =IF($E20="","",(N20+P20)*Precificação!$B$19) -> 563.49579 | T20: =IF($E20="","",(O20+Q20)*Precificação!$B$20) -> 869.08676 | U20: =IF($E20="","",IF($E20=INT($E20),0.01,IF($E20*2=INT($E20*2),0.02,0.05))) -> 0.05 | V20: =IF($E20="","",ROUND(S20/$E20/U20,0)*U20) -> 148.3 | W20: =IF($E20="","",ROUND(T20/$E20/U20,0)*U20) -> 228.7 | X20: =IF(NOT(ISNUMBER(E20)),"",IF(NOT(ISNUMBER(E21)),ROW(),X21)) -> 23
A21: 13 | B21: A.2.7 | C21: (P07) Painel de MDF de 18mm, de 320x160cm parafusado direto no painel existente, acabamento em pintura acrílica acrílica branca. | D21: m2 | E21: 5.2 | F21: =IF($E21="","",V21) -> 139.2 | G21: =IF($E21="","",ROUND(W21+IF($B21=Precificação!$B$26,$F$3/$E21,0),2)) -> 152.1 | H21: =IF($E21="","",F21+G21) -> 291.3 | I21: =IF($E21="","",$E21*F21) -> 723.84 | J21: =IF($E21="","",$E21*G21) -> 790.92 | K21: =IF($E21="","",I21+J21) -> 1514.76 | L21: =IF($E21="","",IF(R21=0,"SEM CUSTO — falta linha de custo","OK")) -> OK | M21: =IF(AND(ISNUMBER(E21),NOT(ISNUMBER(E20))),"F"&ROW()&":G"&X21,"") | N21: =IF($E21="","",SUMIFS('Rateio Anexo'!$K$6:$K$600,'Rateio Anexo'!$D$6:$D$600,$B21,'Rateio Anexo'!$B$6:$B$600,"MAT")) -> 378.25603 | O21: =IF($E21="","",SUMIFS('Rateio Anexo'!$K$6:$K$600,'Rateio Anexo'!$D$6:$D$600,$B21,'Rateio Anexo'!$B$6:$B$600,"MO")) -> 409.26595 | P21: =IF($E21="","",IF($N$3=0,0,N21/$N$3*$R$4)) -> 1.3534265 | Q21: =IF($E21="","",IF($O$3=0,0,O21/$O$3*$T$4)) -> 84.890769 | R21: =IF($E21="","",N21+O21+P21+Q21) -> 873.76618 | S21: =IF($E21="","",(N21+P21)*Precificação!$B$19) -> 723.77498 | T21: =IF($E21="","",(O21+Q21)*Precificação!$B$20) -> 790.91983 | U21: =IF($E21="","",IF($E21=INT($E21),0.01,IF($E21*2=INT($E21*2),0.02,0.05))) -> 0.05 | V21: =IF($E21="","",ROUND(S21/$E21/U21,0)*U21) -> 139.2 | W21: =IF($E21="","",ROUND(T21/$E21/U21,0)*U21) -> 152.1 | X21: =IF(NOT(ISNUMBER(E21)),"",IF(NOT(ISNUMBER(E22)),ROW(),X22)) -> 23
A22: 14 | B22: A.2.8 | C22: (PR01) Painel de MDF de 18mm, com estrutura interna reforçada, treliçada ou em grade, com pontaletes de 5x5cm, e acabamento em pintura acrílica fosca Papel de Seda, da Suvinil. Este painel terá uma abertura em arco na entrada, medindo 150x245cm, e dois recortes laterais — um simulando a geometria de uma lua, e o outro, de uma estrela. | D22: m2 | E22: 35 | F22: =IF($E22="","",V22) -> 148.29 | G22: =IF($E22="","",ROUND(W22+IF($B22=Precificação!$B$26,$F$3/$E22,0),2)) -> 228.71 | H22: =IF($E22="","",F22+G22) -> 377 | I22: =IF($E22="","",$E22*F22) -> 5190.15 | J22: =IF($E22="","",$E22*G22) -> 8004.85 | K22: =IF($E22="","",I22+J22) -> 13195 | L22: =IF($E22="","",IF(R22=0,"SEM CUSTO — falta linha de custo","OK")) -> OK | M22: =IF(AND(ISNUMBER(E22),NOT(ISNUMBER(E21))),"F"&ROW()&":G"&X22,"") | N22: =IF($E22="","",SUMIFS('Rateio Anexo'!$K$6:$K$600,'Rateio Anexo'!$D$6:$D$600,$B22,'Rateio Anexo'!$B$6:$B$600,"MAT")) -> 2712.423 | O22: =IF($E22="","",SUMIFS('Rateio Anexo'!$K$6:$K$600,'Rateio Anexo'!$D$6:$D$600,$B22,'Rateio Anexo'!$B$6:$B$600,"MO")) -> 4142.1015 | P22: =IF($E22="","",IF($N$3=0,0,N22/$N$3*$R$4)) -> 9.7052389 | Q22: =IF($E22="","",IF($O$3=0,0,O22/$O$3*$T$4)) -> 859.16304 | R22: =IF($E22="","",N22+O22+P22+Q22) -> 7723.3927 | S22: =IF($E22="","",(N22+P22)*Precificação!$B$19) -> 5190.0928 | T22: =IF($E22="","",(O22+Q22)*Precificação!$B$20) -> 8004.7465 | U22: =IF($E22="","",IF($E22=INT($E22),0.01,IF($E22*2=INT($E22*2),0.02,0.05))) -> 0.01 | V22: =IF($E22="","",ROUND(S22/$E22/U22,0)*U22) -> 148.29 | W22: =IF($E22="","",ROUND(T22/$E22/U22,0)*U22) -> 228.71 | X22: =IF(NOT(ISNUMBER(E22)),"",IF(NOT(ISNUMBER(E23)),ROW(),X23)) -> 23
A23: 15 | B23: A.2.9 | C23: (PR01 e PR02) Dois painéis de 450x490cm e 30cm de profundidade, com suas 4 faces revestidas com chapa de MDF de 18mm, com estrutura interna reforçada, treliçada ou em grade, com pontaletes de 5x5cm, e acabamento em pintura acrílica fosca Papel de Seda, da Suvinil. Estes dois painéis terão travamento por cabo de aço em 3 pontos cada, conforme indica o projeto de estrutura. Dimensões gerais: 9,6m lineares, altura do painel de 4,9m, área total de 48,5m² 2 unidades | D23: m2 | E23: 97 | F23: =IF($E23="","",V23) -> 175.98 | G23: =IF($E23="","",ROUND(W23+IF($B23=Precificação!$B$26,$F$3/$E23,0),2)) -> 228.71 | H23: =IF($E23="","",F23+G23) -> 404.69 | I23: =IF($E23="","",$E23*F23) -> 17070.06 | J23: =IF($E23="","",$E23*G23) -> 22184.87 | K23: =IF($E23="","",I23+J23) -> 39254.93 | L23: =IF($E23="","",IF(R23=0,"SEM CUSTO — falta linha de custo","OK")) -> OK | M23: =IF(AND(ISNUMBER(E23),NOT(ISNUMBER(E22))),"F"&ROW()&":G"&X23,"") | N23: =IF($E23="","",SUMIFS('Rateio Anexo'!$K$6:$K$600,'Rateio Anexo'!$D$6:$D$600,$B23,'Rateio Anexo'!$B$6:$B$600,"MAT")) -> 8921.2865 | O23: =IF($E23="","",SUMIFS('Rateio Anexo'!$K$6:$K$600,'Rateio Anexo'!$D$6:$D$600,$B23,'Rateio Anexo'!$B$6:$B$600,"MO")) -> 11479.538 | P23: =IF($E23="","",IF($N$3=0,0,N23/$N$3*$R$4)) -> 31.920986 | Q23: =IF($E23="","",IF($O$3=0,0,O23/$O$3*$T$4)) -> 2381.109 | R23: =IF($E23="","",N23+O23+P23+Q23) -> 22813.855 | S23: =IF($E23="","",(N23+P23)*Precificação!$B$19) -> 17070.459 | T23: =IF($E23="","",(O23+Q23)*Precificação!$B$20) -> 22184.583 | U23: =IF($E23="","",IF($E23=INT($E23),0.01,IF($E23*2=INT($E23*2),0.02,0.05))) -> 0.01 | V23: =IF($E23="","",ROUND(S23/$E23/U23,0)*U23) -> 175.98 | W23: =IF($E23="","",ROUND(T23/$E23/U23,0)*U23) -> 228.71 | X23: =IF(NOT(ISNUMBER(E23)),"",IF(NOT(ISNUMBER(E24)),ROW(),X24)) -> 23
A24: 16 | B24: A.3 | C24: Pintura dos painéis | F24: =IF($E24="","",V24) | G24: =IF($E24="","",ROUND(W24+IF($B24=Precificação!$B$26,$F$3/$E24,0),2)) | H24: =IF($E24="","",F24+G24) | I24: =IF($E24="","",$E24*F24) | J24: =IF($E24="","",$E24*G24) | K24: =IF($E24="","",I24+J24) | L24: =IF($E24="","",IF(R24=0,"SEM CUSTO — falta linha de custo","OK")) | M24: =IF(AND(ISNUMBER(E24),NOT(ISNUMBER(E23))),"F"&ROW()&":G"&X24,"") | N24: =IF($E24="","",SUMIFS('Rateio Anexo'!$K$6:$K$600,'Rateio Anexo'!$D$6:$D$600,$B24,'Rateio Anexo'!$B$6:$B$600,"MAT")) | O24: =IF($E24="","",SUMIFS('Rateio Anexo'!$K$6:$K$600,'Rateio Anexo'!$D$6:$D$600,$B24,'Rateio Anexo'!$B$6:$B$600,"MO")) | P24: =IF($E24="","",IF($N$3=0,0,N24/$N$3*$R$4)) | Q24: =IF($E24="","",IF($O$3=0,0,O24/$O$3*$T$4)) | R24: =IF($E24="","",N24+O24+P24+Q24) | S24: =IF($E24="","",(N24+P24)*Precificação!$B$19) | T24: =IF($E24="","",(O24+Q24)*Precificação!$B$20) | U24: =IF($E24="","",IF($E24=INT($E24),0.01,IF($E24*2=INT($E24*2),0.02,0.05))) | V24: =IF($E24="","",ROUND(S24/$E24/U24,0)*U24) | W24: =IF($E24="","",ROUND(T24/$E24/U24,0)*U24) | X24: =IF(NOT(ISNUMBER(E24)),"",IF(NOT(ISNUMBER(E25)),ROW(),X25))
A25: 17 | B25: A.3.1 | C25: Prever a pintura geral, na cor branca, dos painéis que se encontram hoje no espaço expositivo. Esses painéis estão atualmente na cor preta, então é preciso considerar algumas demãos a mais de pintura para que o acabamento fique perfeito. Área total dos painéis: 250m². | D25: m2 | E25: 250 | F25: =IF($E25="","",V25) -> 27.58 | G25: =IF($E25="","",ROUND(W25+IF($B25=Precificação!$B$26,$F$3/$E25,0),2)) -> 75.49 | H25: =IF($E25="","",F25+G25) -> 103.07 | I25: =IF($E25="","",$E25*F25) -> 6895 | J25: =IF($E25="","",$E25*G25) -> 18872.5 | K25: =IF($E25="","",I25+J25) -> 25767.5 | L25: =IF($E25="","",IF(R25=0,"SEM CUSTO — falta linha de custo","OK")) -> OK | M25: =IF(AND(ISNUMBER(E25),NOT(ISNUMBER(E24))),"F"&ROW()&":G"&X25,"") -> F25:G25 | N25: =IF($E25="","",SUMIFS('Rateio Anexo'!$K$6:$K$600,'Rateio Anexo'!$D$6:$D$600,$B25,'Rateio Anexo'!$B$6:$B$600,"MAT")) -> 3602.8546 | O25: =IF($E25="","",SUMIFS('Rateio Anexo'!$K$6:$K$600,'Rateio Anexo'!$D$6:$D$600,$B25,'Rateio Anexo'!$B$6:$B$600,"MO")) -> 9766.0561 | P25: =IF($E25="","",IF($N$3=0,0,N25/$N$3*$R$4)) -> 12.891265 | Q25: =IF($E25="","",IF($O$3=0,0,O25/$O$3*$T$4)) -> 2025.6951 | R25: =IF($E25="","",N25+O25+P25+Q25) -> 15407.497 | S25: =IF($E25="","",(N25+P25)*Precificação!$B$19) -> 6893.8915 | T25: =IF($E25="","",(O25+Q25)*Precificação!$B$20) -> 18873.223 | U25: =IF($E25="","",IF($E25=INT($E25),0.01,IF($E25*2=INT($E25*2),0.02,0.05))) -> 0.01 | V25: =IF($E25="","",ROUND(S25/$E25/U25,0)*U25) -> 27.58 | W25: =IF($E25="","",ROUND(T25/$E25/U25,0)*U25) -> 75.49 | X25: =IF(NOT(ISNUMBER(E25)),"",IF(NOT(ISNUMBER(E26)),ROW(),X26)) -> 25
A26: 18 | B26: A.4 | C26: Construção de mobiliário para espaço expositivo: desenhos localizado na folha 02 do projeto expografico | F26: =IF($E26="","",V26) | G26: =IF($E26="","",ROUND(W26+IF($B26=Precificação!$B$26,$F$3/$E26,0),2)) | H26: =IF($E26="","",F26+G26) | I26: =IF($E26="","",$E26*F26) | J26: =IF($E26="","",$E26*G26) | K26: =IF($E26="","",I26+J26) | L26: =IF($E26="","",IF(R26=0,"SEM CUSTO — falta linha de custo","OK")) | M26: =IF(AND(ISNUMBER(E26),NOT(ISNUMBER(E25))),"F"&ROW()&":G"&X26,"") | N26: =IF($E26="","",SUMIFS('Rateio Anexo'!$K$6:$K$600,'Rateio Anexo'!$D$6:$D$600,$B26,'Rateio Anexo'!$B$6:$B$600,"MAT")) | O26: =IF($E26="","",SUMIFS('Rateio Anexo'!$K$6:$K$600,'Rateio Anexo'!$D$6:$D$600,$B26,'Rateio Anexo'!$B$6:$B$600,"MO")) | P26: =IF($E26="","",IF($N$3=0,0,N26/$N$3*$R$4)) | Q26: =IF($E26="","",IF($O$3=0,0,O26/$O$3*$T$4)) | R26: =IF($E26="","",N26+O26+P26+Q26) | S26: =IF($E26="","",(N26+P26)*Precificação!$B$19) | T26: =IF($E26="","",(O26+Q26)*Precificação!$B$20) | U26: =IF($E26="","",IF($E26=INT($E26),0.01,IF($E26*2=INT($E26*2),0.02,0.05))) | V26: =IF($E26="","",ROUND(S26/$E26/U26,0)*U26) | W26: =IF($E26="","",ROUND(T26/$E26/U26,0)*U26) | X26: =IF(NOT(ISNUMBER(E26)),"",IF(NOT(ISNUMBER(E27)),ROW(),X27))
A27: 19 | B27: A.4.1 | C27: (M01) Mesa construída em MDF de 6, 10 e 18mm, seguindo os detalhes dos desenhos técnicos na prancha 02. Acabamento em pintura acrílica fosca Papel de Seda, da Suvinil. A mesa prevê a instalação de 4 peças de vidro museológico, que devem ser instaladas após a finalização da estrutura da mesa e a realização de molde para que as 4 peças encaixem perfeitamente. O vidro deve seguir o padrão museológico antirreflexo indicado: vidro extra clear laminado temperado 10+10mm (espessura final de 21,52mm), interlayer UV 99%, bordas lapidadas e polidas, junta seca entre peças, em 4 seções. Além destas 4 peças de vidro, há uma peça de acrílico reforçado de 66cm de diâmetro e 18mm de espessura, que servirá de apoio para uma das esculturas. Por dentro dessa peça de acrílico, abaixo dela, serão instaladas luminárias, conforme indicações abaixo: Aplicar fita LED backlight 180°, 12V, 18W/m, 3000K ou 6500K (a confirmar), com dimmer único para todos os trechos, sendo 2 trechos de 30cm, 2 de 50cm e 2 de 60cm, totalizando 220cm de fita. O interior do nicho abaixo do acrílico leitoso deverá ser inteiramente pintado de branco. A alimentação elétrica com cabo PP deve ser feita pelo piso do espaço expositivo, e uma canaleta de piso deve ser instalada para passagem do cabo, nas seguintes especificações: Canaleta de Piso 52x14x2000mm Cinza Enerbras 371/2-ECZ. Dimensões gerais da mesa: 220cm diametro 86cm altura | D27: unid | E27: 1 | F27: =IF($E27="","",V27) -> 5084.89 | G27: =IF($E27="","",ROUND(W27+IF($B27=Precificação!$B$26,$F$3/$E27,0),2)) -> 2433.73 | H27: =IF($E27="","",F27+G27) -> 7518.62 | I27: =IF($E27="","",$E27*F27) -> 5084.89 | J27: =IF($E27="","",$E27*G27) -> 2433.73 | K27: =IF($E27="","",I27+J27) -> 7518.62 | L27: =IF($E27="","",IF(R27=0,"SEM CUSTO — falta linha de custo","OK")) -> OK | M27: =IF(AND(ISNUMBER(E27),NOT(ISNUMBER(E26))),"F"&ROW()&":G"&X27,"") -> F27:G47 | N27: =IF($E27="","",SUMIFS('Rateio Anexo'!$K$6:$K$600,'Rateio Anexo'!$D$6:$D$600,$B27,'Rateio Anexo'!$B$6:$B$600,"MAT")) -> 2657.4409 | O27: =IF($E27="","",SUMIFS('Rateio Anexo'!$K$6:$K$600,'Rateio Anexo'!$D$6:$D$600,$B27,'Rateio Anexo'!$B$6:$B$600,"MO")) -> 1259.3459 | P27: =IF($E27="","",IF($N$3=0,0,N27/$N$3*$R$4)) -> 9.5085092 | Q27: =IF($E27="","",IF($O$3=0,0,O27/$O$3*$T$4)) -> 261.21607 | R27: =IF($E27="","",N27+O27+P27+Q27) -> 4187.5114 | S27: =IF($E27="","",(N27+P27)*Precificação!$B$19) -> 5084.8872 | T27: =IF($E27="","",(O27+Q27)*Precificação!$B$20) -> 2433.7271 | U27: =IF($E27="","",IF($E27=INT($E27),0.01,IF($E27*2=INT($E27*2),0.02,0.05))) -> 0.01 | V27: =IF($E27="","",ROUND(S27/$E27/U27,0)*U27) -> 5084.89 | W27: =IF($E27="","",ROUND(T27/$E27/U27,0)*U27) -> 2433.73 | X27: =IF(NOT(ISNUMBER(E27)),"",IF(NOT(ISNUMBER(E28)),ROW(),X28)) -> 47
A28: 20 | B28: A.4.2 | C28: (M02 e M04) Base para escultura construída em MDF de 6mm e 15mm, com estrutura reforçada com pontalete de 5x5cm e pintura acrílica fosca Papel de Seda, da Suvinil. Dimensões : 75cm diametro e 50cm altura | D28: unid | E28: 2 | F28: =IF($E28="","",V28) -> 200.28 | G28: =IF($E28="","",ROUND(W28+IF($B28=Precificação!$B$26,$F$3/$E28,0),2)) -> 494.61 | H28: =IF($E28="","",F28+G28) -> 694.89 | I28: =IF($E28="","",$E28*F28) -> 400.56 | J28: =IF($E28="","",$E28*G28) -> 989.22 | K28: =IF($E28="","",I28+J28) -> 1389.78 | L28: =IF($E28="","",IF(R28=0,"SEM CUSTO — falta linha de custo","OK")) -> OK | M28: =IF(AND(ISNUMBER(E28),NOT(ISNUMBER(E27))),"F"&ROW()&":G"&X28,"") | N28: =IF($E28="","",SUMIFS('Rateio Anexo'!$K$6:$K$600,'Rateio Anexo'!$D$6:$D$600,$B28,'Rateio Anexo'!$B$6:$B$600,"MAT")) -> 209.34233 | O28: =IF($E28="","",SUMIFS('Rateio Anexo'!$K$6:$K$600,'Rateio Anexo'!$D$6:$D$600,$B28,'Rateio Anexo'!$B$6:$B$600,"MO")) -> 511.87633 | P28: =IF($E28="","",IF($N$3=0,0,N28/$N$3*$R$4)) -> 0.74904149 | Q28: =IF($E28="","",IF($O$3=0,0,O28/$O$3*$T$4)) -> 106.17442 | R28: =IF($E28="","",N28+O28+P28+Q28) -> 828.14213 | S28: =IF($E28="","",(N28+P28)*Precificação!$B$19) -> 400.56663 | T28: =IF($E28="","",(O28+Q28)*Precificação!$B$20) -> 989.21775 | U28: =IF($E28="","",IF($E28=INT($E28),0.01,IF($E28*2=INT($E28*2),0.02,0.05))) -> 0.01 | V28: =IF($E28="","",ROUND(S28/$E28/U28,0)*U28) -> 200.28 | W28: =IF($E28="","",ROUND(T28/$E28/U28,0)*U28) -> 494.61 | X28: =IF(NOT(ISNUMBER(E28)),"",IF(NOT(ISNUMBER(E29)),ROW(),X29)) -> 47
A29: 21 | B29: A.4.3 | C29: (M03 e M05 ) Base para escultura construída em mdf de 6mm e 15mm com dimensões e geometrias variadas, com estrutura de madeira reforçada de pontalete 5x5cm, e acabamento em pintura acrílica fosca Papel de Seda, da Suvinil. Dimensões aproximadas : 75x 200x 225cm | D29: unid | E29: 2 | F29: =IF($E29="","",V29) -> 1901.46 | G29: =IF($E29="","",ROUND(W29+IF($B29=Precificação!$B$26,$F$3/$E29,0),2)) -> 4695.73 | H29: =IF($E29="","",F29+G29) -> 6597.19 | I29: =IF($E29="","",$E29*F29) -> 3802.92 | J29: =IF($E29="","",$E29*G29) -> 9391.46 | K29: =IF($E29="","",I29+J29) -> 13194.38 | L29: =IF($E29="","",IF(R29=0,"SEM CUSTO — falta linha de custo","OK")) -> OK | M29: =IF(AND(ISNUMBER(E29),NOT(ISNUMBER(E28))),"F"&ROW()&":G"&X29,"") | N29: =IF($E29="","",SUMIFS('Rateio Anexo'!$K$6:$K$600,'Rateio Anexo'!$D$6:$D$600,$B29,'Rateio Anexo'!$B$6:$B$600,"MAT")) -> 1987.4599 | O29: =IF($E29="","",SUMIFS('Rateio Anexo'!$K$6:$K$600,'Rateio Anexo'!$D$6:$D$600,$B29,'Rateio Anexo'!$B$6:$B$600,"MO")) -> 4859.6654 | P29: =IF($E29="","",IF($N$3=0,0,N29/$N$3*$R$4)) -> 7.1112704 | Q29: =IF($E29="","",IF($O$3=0,0,O29/$O$3*$T$4)) -> 1008.0016 | R29: =IF($E29="","",N29+O29+P29+Q29) -> 7862.2382 | S29: =IF($E29="","",(N29+P29)*Precificação!$B$19) -> 3802.9104 | T29: =IF($E29="","",(O29+Q29)*Precificação!$B$20) -> 9391.4623 | U29: =IF($E29="","",IF($E29=INT($E29),0.01,IF($E29*2=INT($E29*2),0.02,0.05))) -> 0.01 | V29: =IF($E29="","",ROUND(S29/$E29/U29,0)*U29) -> 1901.46 | W29: =IF($E29="","",ROUND(T29/$E29/U29,0)*U29) -> 4695.73 | X29: =IF(NOT(ISNUMBER(E29)),"",IF(NOT(ISNUMBER(E30)),ROW(),X30)) -> 47
A30: 22 | B30: A.4.4 | C30: (M06,M07,M08 e M09) Base para escultura construída em MDF de18mm, com dimensões e geometria variada e acabamento em pintura acrílica fosca Terra Roxa, da Suvinil. Dimensões aproximadas : 75x220x271cm | D30: unid | E30: 2 | F30: =IF($E30="","",V30) -> 2363.8 | G30: =IF($E30="","",ROUND(W30+IF($B30=Precificação!$B$26,$F$3/$E30,0),2)) -> 5889.51 | H30: =IF($E30="","",F30+G30) -> 8253.31 | I30: =IF($E30="","",$E30*F30) -> 4727.6 | J30: =IF($E30="","",$E30*G30) -> 11779.02 | K30: =IF($E30="","",I30+J30) -> 16506.62 | L30: =IF($E30="","",IF(R30=0,"SEM CUSTO — falta linha de custo","OK")) -> OK | M30: =IF(AND(ISNUMBER(E30),NOT(ISNUMBER(E29))),"F"&ROW()&":G"&X30,"") | N30: =IF($E30="","",SUMIFS('Rateio Anexo'!$K$6:$K$600,'Rateio Anexo'!$D$6:$D$600,$B30,'Rateio Anexo'!$B$6:$B$600,"MAT")) -> 2470.7145 | O30: =IF($E30="","",SUMIFS('Rateio Anexo'!$K$6:$K$600,'Rateio Anexo'!$D$6:$D$600,$B30,'Rateio Anexo'!$B$6:$B$600,"MO")) -> 6095.12 | P30: =IF($E30="","",IF($N$3=0,0,N30/$N$3*$R$4)) -> 8.8403892 | Q30: =IF($E30="","",IF($O$3=0,0,O30/$O$3*$T$4)) -> 1264.2621 | R30: =IF($E30="","",N30+O30+P30+Q30) -> 9838.937 | S30: =IF($E30="","",(N30+P30)*Precificação!$B$19) -> 4727.5952 | T30: =IF($E30="","",(O30+Q30)*Precificação!$B$20) -> 11779.019 | U30: =IF($E30="","",IF($E30=INT($E30),0.01,IF($E30*2=INT($E30*2),0.02,0.05))) -> 0.01 | V30: =IF($E30="","",ROUND(S30/$E30/U30,0)*U30) -> 2363.8 | W30: =IF($E30="","",ROUND(T30/$E30/U30,0)*U30) -> 5889.51 | X30: =IF(NOT(ISNUMBER(E30)),"",IF(NOT(ISNUMBER(E31)),ROW(),X31)) -> 47
A31: 23 | B31: A.4.5 | C31: (M10 ) Base para escultura em MDF de 18mm, com dimensões e geometria variadas, e acabamento em pintura acrílica fosca Terra Roxa, da Suvinil. Dimensões aproximadas : 75x190x182cm | D31: unid | E31: 1 | F31: =IF($E31="","",V31) -> 1531.75 | G31: =IF($E31="","",ROUND(W31+IF($B31=Precificação!$B$26,$F$3/$E31,0),2)) -> 3816.43 | H31: =IF($E31="","",F31+G31) -> 5348.18 | I31: =IF($E31="","",$E31*F31) -> 1531.75 | J31: =IF($E31="","",$E31*G31) -> 3816.43 | K31: =IF($E31="","",I31+J31) -> 5348.18 | L31: =IF($E31="","",IF(R31=0,"SEM CUSTO — falta linha de custo","OK")) -> OK | M31: =IF(AND(ISNUMBER(E31),NOT(ISNUMBER(E30))),"F"&ROW()&":G"&X31,"") | N31: =IF($E31="","",SUMIFS('Rateio Anexo'!$K$6:$K$600,'Rateio Anexo'!$D$6:$D$600,$B31,'Rateio Anexo'!$B$6:$B$600,"MAT")) -> 800.51664 | O31: =IF($E31="","",SUMIFS('Rateio Anexo'!$K$6:$K$600,'Rateio Anexo'!$D$6:$D$600,$B31,'Rateio Anexo'!$B$6:$B$600,"MO")) -> 1974.8315 | P31: =IF($E31="","",IF($N$3=0,0,N31/$N$3*$R$4)) -> 2.8643044 | Q31: =IF($E31="","",IF($O$3=0,0,O31/$O$3*$T$4)) -> 409.62354 | R31: =IF($E31="","",N31+O31+P31+Q31) -> 3187.836 | S31: =IF($E31="","",(N31+P31)*Precificação!$B$19) -> 1531.7506 | T31: =IF($E31="","",(O31+Q31)*Precificação!$B$20) -> 3816.4265 | U31: =IF($E31="","",IF($E31=INT($E31),0.01,IF($E31*2=INT($E31*2),0.02,0.05))) -> 0.01 | V31: =IF($E31="","",ROUND(S31/$E31/U31,0)*U31) -> 1531.75 | W31: =IF($E31="","",ROUND(T31/$E31/U31,0)*U31) -> 3816.43 | X31: =IF(NOT(ISNUMBER(E31)),"",IF(NOT(ISNUMBER(E32)),ROW(),X32)) -> 47
A32: 24 | B32: A.4.6 | C32: (M11) Base para escultura em MDF de 18mm, com bordas chanfradas, e acabamento em pintura acrílica fosca Terra Roxa, da Suvinil Dimensões aproximadas : 8x95x95cm | D32: unid | E32: 1 | F32: =IF($E32="","",V32) -> 258.56 | G32: =IF($E32="","",ROUND(W32+IF($B32=Precificação!$B$26,$F$3/$E32,0),2)) -> 644.21 | H32: =IF($E32="","",F32+G32) -> 902.77 | I32: =IF($E32="","",$E32*F32) -> 258.56 | J32: =IF($E32="","",$E32*G32) -> 644.21 | K32: =IF($E32="","",I32+J32) -> 902.77 | L32: =IF($E32="","",IF(R32=0,"SEM CUSTO — falta linha de custo","OK")) -> OK | M32: =IF(AND(ISNUMBER(E32),NOT(ISNUMBER(E31))),"F"&ROW()&":G"&X32,"") | N32: =IF($E32="","",SUMIFS('Rateio Anexo'!$K$6:$K$600,'Rateio Anexo'!$D$6:$D$600,$B32,'Rateio Anexo'!$B$6:$B$600,"MAT")) -> 135.12721 | O32: =IF($E32="","",SUMIFS('Rateio Anexo'!$K$6:$K$600,'Rateio Anexo'!$D$6:$D$600,$B32,'Rateio Anexo'!$B$6:$B$600,"MO")) -> 333.35156 | P32: =IF($E32="","",IF($N$3=0,0,N32/$N$3*$R$4)) -> 0.48349459 | Q32: =IF($E32="","",IF($O$3=0,0,O32/$O$3*$T$4)) -> 69.144453 | R32: =IF($E32="","",N32+O32+P32+Q32) -> 538.10672 | S32: =IF($E32="","",(N32+P32)*Precificação!$B$19) -> 258.55951 | T32: =IF($E32="","",(O32+Q32)*Precificação!$B$20) -> 644.21279 | U32: =IF($E32="","",IF($E32=INT($E32),0.01,IF($E32*2=INT($E32*2),0.02,0.05))) -> 0.01 | V32: =IF($E32="","",ROUND(S32/$E32/U32,0)*U32) -> 258.56 | W32: =IF($E32="","",ROUND(T32/$E32/U32,0)*U32) -> 644.21 | X32: =IF(NOT(ISNUMBER(E32)),"",IF(NOT(ISNUMBER(E33)),ROW(),X33)) -> 47
A33: 25 | B33: A.4.7 | C33: (M12) Base para escultura em MDF de 18mm, com dimensões e geometria variadas, e acabamento em pintura acrílica fosca Papel de Seda, da Suvinil. Dimensões aproximadas : 110x230x144cm | D33: unid | E33: 1 | F33: =IF($E33="","",V33) -> 1868.47 | G33: =IF($E33="","",ROUND(W33+IF($B33=Precificação!$B$26,$F$3/$E33,0),2)) -> 4533.91 | H33: =IF($E33="","",F33+G33) -> 6402.38 | I33: =IF($E33="","",$E33*F33) -> 1868.47 | J33: =IF($E33="","",$E33*G33) -> 4533.91 | K33: =IF($E33="","",I33+J33) -> 6402.38 | L33: =IF($E33="","",IF(R33=0,"SEM CUSTO — falta linha de custo","OK")) -> OK | M33: =IF(AND(ISNUMBER(E33),NOT(ISNUMBER(E32))),"F"&ROW()&":G"&X33,"") | N33: =IF($E33="","",SUMIFS('Rateio Anexo'!$K$6:$K$600,'Rateio Anexo'!$D$6:$D$600,$B33,'Rateio Anexo'!$B$6:$B$600,"MAT")) -> 976.49096 | O33: =IF($E33="","",SUMIFS('Rateio Anexo'!$K$6:$K$600,'Rateio Anexo'!$D$6:$D$600,$B33,'Rateio Anexo'!$B$6:$B$600,"MO")) -> 2346.0999 | P33: =IF($E33="","",IF($N$3=0,0,N33/$N$3*$R$4)) -> 3.4939529 | Q33: =IF($E33="","",IF($O$3=0,0,O33/$O$3*$T$4)) -> 486.63276 | R33: =IF($E33="","",N33+O33+P33+Q33) -> 3812.7175 | S33: =IF($E33="","",(N33+P33)*Precificação!$B$19) -> 1868.4692 | T33: =IF($E33="","",(O33+Q33)*Precificação!$B$20) -> 4533.9147 | U33: =IF($E33="","",IF($E33=INT($E33),0.01,IF($E33*2=INT($E33*2),0.02,0.05))) -> 0.01 | V33: =IF($E33="","",ROUND(S33/$E33/U33,0)*U33) -> 1868.47 | W33: =IF($E33="","",ROUND(T33/$E33/U33,0)*U33) -> 4533.91 | X33: =IF(NOT(ISNUMBER(E33)),"",IF(NOT(ISNUMBER(E34)),ROW(),X34)) -> 47
A34: 26 | B34: A.4.8 | C34: (M13) Base para escultura em MDF de 18mm, com dimensões e geometria variadas, e acabamento em pintura acrílica fosca Papel de Seda, da Suvinil. Considerar reforço estrutural interno de madeira com pontalete 5x5cm. Dimensões aproximadas : 50x270x65cm | D34: unid | E34: 1 | F34: =IF($E34="","",V34) -> 1017.26 | G34: =IF($E34="","",ROUND(W34+IF($B34=Precificação!$B$26,$F$3/$E34,0),2)) -> 2094.45 | H34: =IF($E34="","",F34+G34) -> 3111.71 | I34: =IF($E34="","",$E34*F34) -> 1017.26 | J34: =IF($E34="","",$E34*G34) -> 2094.45 | K34: =IF($E34="","",I34+J34) -> 3111.71 | L34: =IF($E34="","",IF(R34=0,"SEM CUSTO — falta linha de custo","OK")) -> OK | M34: =IF(AND(ISNUMBER(E34),NOT(ISNUMBER(E33))),"F"&ROW()&":G"&X34,"") | N34: =IF($E34="","",SUMIFS('Rateio Anexo'!$K$6:$K$600,'Rateio Anexo'!$D$6:$D$600,$B34,'Rateio Anexo'!$B$6:$B$600,"MAT")) -> 531.6349 | O34: =IF($E34="","",SUMIFS('Rateio Anexo'!$K$6:$K$600,'Rateio Anexo'!$D$6:$D$600,$B34,'Rateio Anexo'!$B$6:$B$600,"MO")) -> 1083.7875 | P34: =IF($E34="","",IF($N$3=0,0,N34/$N$3*$R$4)) -> 1.9022268 | Q34: =IF($E34="","",IF($O$3=0,0,O34/$O$3*$T$4)) -> 224.8014 | R34: =IF($E34="","",N34+O34+P34+Q34) -> 1842.1261 | S34: =IF($E34="","",(N34+P34)*Precificação!$B$19) -> 1017.2582 | T34: =IF($E34="","",(O34+Q34)*Precificação!$B$20) -> 2094.4549 | U34: =IF($E34="","",IF($E34=INT($E34),0.01,IF($E34*2=INT($E34*2),0.02,0.05))) -> 0.01 | V34: =IF($E34="","",ROUND(S34/$E34/U34,0)*U34) -> 1017.26 | W34: =IF($E34="","",ROUND(T34/$E34/U34,0)*U34) -> 2094.45 | X34: =IF(NOT(ISNUMBER(E34)),"",IF(NOT(ISNUMBER(E35)),ROW(),X35)) -> 47
A35: 27 | B35: A.4.9 | C35: (M14) Base para escultura em MDF de 18mm, com dimensões e geometria variadas, e acabamento em pintura acrílica fosca Papel de Seda, da Suvinil.Dimensões aproximadas : 50x155x95cm | D35: unid | E35: 1 | F35: =IF($E35="","",V35) -> 685.73 | G35: =IF($E35="","",ROUND(W35+IF($B35=Precificação!$B$26,$F$3/$E35,0),2)) -> 1663.96 | H35: =IF($E35="","",F35+G35) -> 2349.69 | I35: =IF($E35="","",$E35*F35) -> 685.73 | J35: =IF($E35="","",$E35*G35) -> 1663.96 | K35: =IF($E35="","",I35+J35) -> 2349.69 | L35: =IF($E35="","",IF(R35=0,"SEM CUSTO — falta linha de custo","OK")) -> OK | M35: =IF(AND(ISNUMBER(E35),NOT(ISNUMBER(E34))),"F"&ROW()&":G"&X35,"") | N35: =IF($E35="","",SUMIFS('Rateio Anexo'!$K$6:$K$600,'Rateio Anexo'!$D$6:$D$600,$B35,'Rateio Anexo'!$B$6:$B$600,"MAT")) -> 358.37547 | O35: =IF($E35="","",SUMIFS('Rateio Anexo'!$K$6:$K$600,'Rateio Anexo'!$D$6:$D$600,$B35,'Rateio Anexo'!$B$6:$B$600,"MO")) -> 861.02655 | P35: =IF($E35="","",IF($N$3=0,0,N35/$N$3*$R$4)) -> 1.2822925 | Q35: =IF($E35="","",IF($O$3=0,0,O35/$O$3*$T$4)) -> 178.59586 | R35: =IF($E35="","",N35+O35+P35+Q35) -> 1399.2802 | S35: =IF($E35="","",(N35+P35)*Precificação!$B$19) -> 685.73448 | T35: =IF($E35="","",(O35+Q35)*Precificação!$B$20) -> 1663.9619 | U35: =IF($E35="","",IF($E35=INT($E35),0.01,IF($E35*2=INT($E35*2),0.02,0.05))) -> 0.01 | V35: =IF($E35="","",ROUND(S35/$E35/U35,0)*U35) -> 685.73 | W35: =IF($E35="","",ROUND(T35/$E35/U35,0)*U35) -> 1663.96 | X35: =IF(NOT(ISNUMBER(E35)),"",IF(NOT(ISNUMBER(E36)),ROW(),X36)) -> 47
A36: 28 | B36: A.4.10 | C36: (M15) Base para escultura em MDF de 18mm, com dimensões e geometria variadas, e acabamento em pintura acrílica fosca Papel de Seda, da Suvinil. Dimensões aproximadas : 30x108x80cm | D36: unid | E36: 1 | F36: =IF($E36="","",V36) -> 359.85 | G36: =IF($E36="","",ROUND(W36+IF($B36=Precificação!$B$26,$F$3/$E36,0),2)) -> 873.2 | H36: =IF($E36="","",F36+G36) -> 1233.05 | I36: =IF($E36="","",$E36*F36) -> 359.85 | J36: =IF($E36="","",$E36*G36) -> 873.2 | K36: =IF($E36="","",I36+J36) -> 1233.05 | L36: =IF($E36="","",IF(R36=0,"SEM CUSTO — falta linha de custo","OK")) -> OK | M36: =IF(AND(ISNUMBER(E36),NOT(ISNUMBER(E35))),"F"&ROW()&":G"&X36,"") | N36: =IF($E36="","",SUMIFS('Rateio Anexo'!$K$6:$K$600,'Rateio Anexo'!$D$6:$D$600,$B36,'Rateio Anexo'!$B$6:$B$600,"MAT")) -> 188.06493 | O36: =IF($E36="","",SUMIFS('Rateio Anexo'!$K$6:$K$600,'Rateio Anexo'!$D$6:$D$600,$B36,'Rateio Anexo'!$B$6:$B$600,"MO")) -> 451.84145 | P36: =IF($E36="","",IF($N$3=0,0,N36/$N$3*$R$4)) -> 0.67290944 | Q36: =IF($E36="","",IF($O$3=0,0,O36/$O$3*$T$4)) -> 93.721866 | R36: =IF($E36="","",N36+O36+P36+Q36) -> 734.30115 | S36: =IF($E36="","",(N36+P36)*Precificação!$B$19) -> 359.85332 | T36: =IF($E36="","",(O36+Q36)*Precificação!$B$20) -> 873.19838 | U36: =IF($E36="","",IF($E36=INT($E36),0.01,IF($E36*2=INT($E36*2),0.02,0.05))) -> 0.01 | V36: =IF($E36="","",ROUND(S36/$E36/U36,0)*U36) -> 359.85 | W36: =IF($E36="","",ROUND(T36/$E36/U36,0)*U36) -> 873.2 | X36: =IF(NOT(ISNUMBER(E36)),"",IF(NOT(ISNUMBER(E37)),ROW(),X37)) -> 47
A37: 29 | B37: A.4.11 | C37: (M16 e M17) Base para escultura em MDF de 18mm, com dimensões e geometria variadas, e acabamento em pintura acrílica fosca Papel de Seda, da Suvinil.Dimensões aproximadas : 70x45x59cm | D37: unid | E37: 2 | F37: =IF($E37="","",V37) -> 250.39 | G37: =IF($E37="","",ROUND(W37+IF($B37=Precificação!$B$26,$F$3/$E37,0),2)) -> 607.58 | H37: =IF($E37="","",F37+G37) -> 857.97 | I37: =IF($E37="","",$E37*F37) -> 500.78 | J37: =IF($E37="","",$E37*G37) -> 1215.16 | K37: =IF($E37="","",I37+J37) -> 1715.94 | L37: =IF($E37="","",IF(R37=0,"SEM CUSTO — falta linha de custo","OK")) -> OK | M37: =IF(AND(ISNUMBER(E37),NOT(ISNUMBER(E36))),"F"&ROW()&":G"&X37,"") | N37: =IF($E37="","",SUMIFS('Rateio Anexo'!$K$6:$K$600,'Rateio Anexo'!$D$6:$D$600,$B37,'Rateio Anexo'!$B$6:$B$600,"MAT")) -> 261.71273 | O37: =IF($E37="","",SUMIFS('Rateio Anexo'!$K$6:$K$600,'Rateio Anexo'!$D$6:$D$600,$B37,'Rateio Anexo'!$B$6:$B$600,"MO")) -> 628.78636 | P37: =IF($E37="","",IF($N$3=0,0,N37/$N$3*$R$4)) -> 0.93642643 | Q37: =IF($E37="","",IF($O$3=0,0,O37/$O$3*$T$4)) -> 130.42413 | R37: =IF($E37="","",N37+O37+P37+Q37) -> 1021.8596 | S37: =IF($E37="","",(N37+P37)*Precificação!$B$19) -> 500.7749 | T37: =IF($E37="","",(O37+Q37)*Precificação!$B$20) -> 1215.1502 | U37: =IF($E37="","",IF($E37=INT($E37),0.01,IF($E37*2=INT($E37*2),0.02,0.05))) -> 0.01 | V37: =IF($E37="","",ROUND(S37/$E37/U37,0)*U37) -> 250.39 | W37: =IF($E37="","",ROUND(T37/$E37/U37,0)*U37) -> 607.58 | X37: =IF(NOT(ISNUMBER(E37)),"",IF(NOT(ISNUMBER(E38)),ROW(),X38)) -> 47
A38: 30 | B38: A.4.12 | C38: (M18) Base para escultura em MDF de 18mm, com dimensões e geometria variadas, e acabamento em pintura acrílica fosca Papel de Seda, da Suvinil. Dimensões aproximadas : 70x40x40cm | D38: unid | E38: 2 | F38: =IF($E38="","",V38) -> 181.18 | G38: =IF($E38="","",ROUND(W38+IF($B38=Precificação!$B$26,$F$3/$E38,0),2)) -> 439.65 | H38: =IF($E38="","",F38+G38) -> 620.83 | I38: =IF($E38="","",$E38*F38) -> 362.36 | J38: =IF($E38="","",$E38*G38) -> 879.3 | K38: =IF($E38="","",I38+J38) -> 1241.66 | L38: =IF($E38="","",IF(R38=0,"SEM CUSTO — falta linha de custo","OK")) -> OK | M38: =IF(AND(ISNUMBER(E38),NOT(ISNUMBER(E37))),"F"&ROW()&":G"&X38,"") | N38: =IF($E38="","",SUMIFS('Rateio Anexo'!$K$6:$K$600,'Rateio Anexo'!$D$6:$D$600,$B38,'Rateio Anexo'!$B$6:$B$600,"MAT")) -> 189.38007 | O38: =IF($E38="","",SUMIFS('Rateio Anexo'!$K$6:$K$600,'Rateio Anexo'!$D$6:$D$600,$B38,'Rateio Anexo'!$B$6:$B$600,"MO")) -> 455.00118 | P38: =IF($E38="","",IF($N$3=0,0,N38/$N$3*$R$4)) -> 0.6776151 | Q38: =IF($E38="","",IF($O$3=0,0,O38/$O$3*$T$4)) -> 94.377263 | R38: =IF($E38="","",N38+O38+P38+Q38) -> 739.43613 | S38: =IF($E38="","",(N38+P38)*Precificação!$B$19) -> 362.36978 | T38: =IF($E38="","",(O38+Q38)*Precificação!$B$20) -> 879.30466 | U38: =IF($E38="","",IF($E38=INT($E38),0.01,IF($E38*2=INT($E38*2),0.02,0.05))) -> 0.01 | V38: =IF($E38="","",ROUND(S38/$E38/U38,0)*U38) -> 181.18 | W38: =IF($E38="","",ROUND(T38/$E38/U38,0)*U38) -> 439.65 | X38: =IF(NOT(ISNUMBER(E38)),"",IF(NOT(ISNUMBER(E39)),ROW(),X39)) -> 47
... A47: 39 | B47: A.4.21 | C47: Caixa para tablet nas medidas 25x35x5cm em MDF 10mm e pintura branca. A posição exata dessa peça será definida pelo projeto gráfico da exposição. | D47: unid | E47: 1 | F47: =IF($E47="","",V47) -> 43.31 | G47: =IF($E47="","",ROUND(W47+IF($B47=Precificação!$B$26,$F$3/$E47,0),2)) -> 105.46 | H47: =IF($E47="","",F47+G47) -> 148.77 | I47: =IF($E47="","",$E47*F47) -> 43.31 | J47: =IF($E47="","",$E47*G47) -> 105.46 | K47: =IF($E47="","",I47+J47) -> 148.77 | L47: =IF($E47="","",IF(R47=0,"SEM CUSTO — falta linha de custo","OK")) -> OK | M47: =IF(AND(ISNUMBER(E47),NOT(ISNUMBER(E46))),"F"&ROW()&":G"&X47,"") | N47: =IF($E47="","",SUMIFS('Rateio Anexo'!$K$6:$K$600,'Rateio Anexo'!$D$6:$D$600,$B47,'Rateio Anexo'!$B$6:$B$600,"MAT")) -> 22.635123 | O47: =IF($E47="","",SUMIFS('Rateio Anexo'!$K$6:$K$600,'Rateio Anexo'!$D$6:$D$600,$B47,'Rateio Anexo'!$B$6:$B$600,"MO")) -> 54.571652 | P47: =IF($E47="","",IF($N$3=0,0,N47/$N$3*$R$4)) -> 0.080990051 | Q47: =IF($E47="","",IF($O$3=0,0,O47/$O$3*$T$4)) -> 11.319362 | R47: =IF($E47="","",N47+O47+P47+Q47) -> 88.607127 | S47: =IF($E47="","",(N47+P47)*Precificação!$B$19) -> 43.311235 | T47: =IF($E47="","",(O47+Q47)*Precificação!$B$20) -> 105.4615 | U47: =IF($E47="","",IF($E47=INT($E47),0.01,IF($E47*2=INT($E47*2),0.02,0.05))) -> 0.01 | V47: =IF($E47="","",ROUND(S47/$E47/U47,0)*U47) -> 43.31 | W47: =IF($E47="","",ROUND(T47/$E47/U47,0)*U47) -> 105.46 | X47: =IF(NOT(ISNUMBER(E47)),"",IF(NOT(ISNUMBER(E48)),ROW(),X48)) -> 47
A48: 40 | B48: A.5 | C48: Pintura e restauro de mobiliário existente do educativo | F48: =IF($E48="","",V48) | G48: =IF($E48="","",ROUND(W48+IF($B48=Precificação!$B$26,$F$3/$E48,0),2)) | H48: =IF($E48="","",F48+G48) | I48: =IF($E48="","",$E48*F48) | J48: =IF($E48="","",$E48*G48) | K48: =IF($E48="","",I48+J48) | L48: =IF($E48="","",IF(R48=0,"SEM CUSTO — falta linha de custo","OK")) | M48: =IF(AND(ISNUMBER(E48),NOT(ISNUMBER(E47))),"F"&ROW()&":G"&X48,"") | N48: =IF($E48="","",SUMIFS('Rateio Anexo'!$K$6:$K$600,'Rateio Anexo'!$D$6:$D$600,$B48,'Rateio Anexo'!$B$6:$B$600,"MAT")) | O48: =IF($E48="","",SUMIFS('Rateio Anexo'!$K$6:$K$600,'Rateio Anexo'!$D$6:$D$600,$B48,'Rateio Anexo'!$B$6:$B$600,"MO")) | P48: =IF($E48="","",IF($N$3=0,0,N48/$N$3*$R$4)) | Q48: =IF($E48="","",IF($O$3=0,0,O48/$O$3*$T$4)) | R48: =IF($E48="","",N48+O48+P48+Q48) | S48: =IF($E48="","",(N48+P48)*Precificação!$B$19) | T48: =IF($E48="","",(O48+Q48)*Precificação!$B$20) | U48: =IF($E48="","",IF($E48=INT($E48),0.01,IF($E48*2=INT($E48*2),0.02,0.05))) | V48: =IF($E48="","",ROUND(S48/$E48/U48,0)*U48) | W48: =IF($E48="","",ROUND(T48/$E48/U48,0)*U48) | X48: =IF(NOT(ISNUMBER(E48)),"",IF(NOT(ISNUMBER(E49)),ROW(),X49))
A49: 41 | B49: A.5.1 | C49: Pintura de banquinhos existentes com tinta acrílica fosca Terra Roxa, da Suvinil. Dimensões aproximadas : 50x45x45cm | D49: unid | E49: 15 | F49: =IF($E49="","",V49) -> 109.88 | G49: =IF($E49="","",ROUND(W49+IF($B49=Precificação!$B$26,$F$3/$E49,0),2)) -> 98.14 | H49: =IF($E49="","",F49+G49) -> 208.02 | I49: =IF($E49="","",$E49*F49) -> 1648.2 | J49: =IF($E49="","",$E49*G49) -> 1472.1 | K49: =IF($E49="","",I49+J49) -> 3120.3 | L49: =IF($E49="","",IF(R49=0,"SEM CUSTO — falta linha de custo","OK")) -> OK | M49: =IF(AND(ISNUMBER(E49),NOT(ISNUMBER(E48))),"F"&ROW()&":G"&X49,"") -> F49:G53 | N49: =IF($E49="","",SUMIFS('Rateio Anexo'!$K$6:$K$600,'Rateio Anexo'!$D$6:$D$600,$B49,'Rateio Anexo'!$B$6:$B$600,"MAT")) -> 861.3685 | O49: =IF($E49="","",SUMIFS('Rateio Anexo'!$K$6:$K$600,'Rateio Anexo'!$D$6:$D$600,$B49,'Rateio Anexo'!$B$6:$B$600,"MO")) -> 761.75238 | P49: =IF($E49="","",IF($N$3=0,0,N49/$N$3*$R$4)) -> 3.0820366 | Q49: =IF($E49="","",IF($O$3=0,0,O49/$O$3*$T$4)) -> 158.00421 | R49: =IF($E49="","",N49+O49+P49+Q49) -> 1784.2071 | S49: =IF($E49="","",(N49+P49)*Precificação!$B$19) -> 1648.1878 | T49: =IF($E49="","",(O49+Q49)*Precificação!$B$20) -> 1472.1114 | U49: =IF($E49="","",IF($E49=INT($E49),0.01,IF($E49*2=INT($E49*2),0.02,0.05))) -> 0.01 | V49: =IF($E49="","",ROUND(S49/$E49/U49,0)*U49) -> 109.88 | W49: =IF($E49="","",ROUND(T49/$E49/U49,0)*U49) -> 98.14 | X49: =IF(NOT(ISNUMBER(E49)),"",IF(NOT(ISNUMBER(E50)),ROW(),X50)) -> 53
A50: 42 | B50: A.5.2 | C50: Pintura eletroestática de estrutura de mesas com tinta acrílica fosca Terra Roxa, da Suvinil. Dimensões aproximadas: 180x70cm | D50: unid | E50: 2 | F50: =IF($E50="","",V50) -> 669.71 | G50: =IF($E50="","",ROUND(W50+IF($B50=Precificação!$B$26,$F$3/$E50,0),2)) -> 0 | H50: =IF($E50="","",F50+G50) -> 669.71 | I50: =IF($E50="","",$E50*F50) -> 1339.42 | J50: =IF($E50="","",$E50*G50) -> 0 | K50: =IF($E50="","",I50+J50) -> 1339.42 | L50: =IF($E50="","",IF(R50=0,"SEM CUSTO — falta linha de custo","OK")) -> OK | M50: =IF(AND(ISNUMBER(E50),NOT(ISNUMBER(E49))),"F"&ROW()&":G"&X50,"") | N50: =IF($E50="","",SUMIFS('Rateio Anexo'!$K$6:$K$600,'Rateio Anexo'!$D$6:$D$600,$B50,'Rateio Anexo'!$B$6:$B$600,"MAT")) -> 700 | O50: =IF($E50="","",SUMIFS('Rateio Anexo'!$K$6:$K$600,'Rateio Anexo'!$D$6:$D$600,$B50,'Rateio Anexo'!$B$6:$B$600,"MO")) -> 0 | P50: =IF($E50="","",IF($N$3=0,0,N50/$N$3*$R$4)) -> 2.5046489 | Q50: =IF($E50="","",IF($O$3=0,0,O50/$O$3*$T$4)) -> 0 | R50: =IF($E50="","",N50+O50+P50+Q50) -> 702.50465 | S50: =IF($E50="","",(N50+P50)*Precificação!$B$19) -> 1339.4168 | T50: =IF($E50="","",(O50+Q50)*Precificação!$B$20) -> 0 | U50: =IF($E50="","",IF($E50=INT($E50),0.01,IF($E50*2=INT($E50*2),0.02,0.05))) -> 0.01 | V50: =IF($E50="","",ROUND(S50/$E50/U50,0)*U50) -> 669.71 | W50: =IF($E50="","",ROUND(T50/$E50/U50,0)*U50) -> 0 | X50: =IF(NOT(ISNUMBER(E50)),"",IF(NOT(ISNUMBER(E51)),ROW(),X51)) -> 53
A51: 43 | B51: A.5.3 | C51: Pintura de porta folders existentes com tinta acrílica fosca Terra Roxa, da Suvinil, com medida aprox.75x25x50cm | D51: unid | E51: 2 | F51: =IF($E51="","",V51) -> 110.75 | G51: =IF($E51="","",ROUND(W51+IF($B51=Precificação!$B$26,$F$3/$E51,0),2)) -> 104.18 | H51: =IF($E51="","",F51+G51) -> 214.93 | I51: =IF($E51="","",$E51*F51) -> 221.5 | J51: =IF($E51="","",$E51*G51) -> 208.36 | K51: =IF($E51="","",I51+J51) -> 429.86 | L51: =IF($E51="","",IF(R51=0,"SEM CUSTO — falta linha de custo","OK")) -> OK | M51: =IF(AND(ISNUMBER(E51),NOT(ISNUMBER(E50))),"F"&ROW()&":G"&X51,"") | N51: =IF($E51="","",SUMIFS('Rateio Anexo'!$K$6:$K$600,'Rateio Anexo'!$D$6:$D$600,$B51,'Rateio Anexo'!$B$6:$B$600,"MAT")) -> 115.76293 | O51: =IF($E51="","",SUMIFS('Rateio Anexo'!$K$6:$K$600,'Rateio Anexo'!$D$6:$D$600,$B51,'Rateio Anexo'!$B$6:$B$600,"MO")) -> 107.81726 | P51: =IF($E51="","",IF($N$3=0,0,N51/$N$3*$R$4)) -> 0.41420783 | Q51: =IF($E51="","",IF($O$3=0,0,O51/$O$3*$T$4)) -> 22.363673 | R51: =IF($E51="","",N51+O51+P51+Q51) -> 246.35807 | S51: =IF($E51="","",(N51+P51)*Precificação!$B$19) -> 221.50687 | T51: =IF($E51="","",(O51+Q51)*Precificação!$B$20) -> 208.36038 | U51: =IF($E51="","",IF($E51=INT($E51),0.01,IF($E51*2=INT($E51*2),0.02,0.05))) -> 0.01 | V51: =IF($E51="","",ROUND(S51/$E51/U51,0)*U51) -> 110.75 | W51: =IF($E51="","",ROUND(T51/$E51/U51,0)*U51) -> 104.18 | X51: =IF(NOT(ISNUMBER(E51)),"",IF(NOT(ISNUMBER(E52)),ROW(),X52)) -> 53
A52: 44 | B52: A.5.4 | C52: Pintura de mesa tátil com tinta acrílica fosca Terra Roxa, da Suvinil e aplicação de vinil de recorte na mesa. Dimensões aproximadas: 100x85x120cm | D52: unid | E52: 1 | F52: =IF($E52="","",V52) -> 411.52 | G52: =IF($E52="","",ROUND(W52+IF($B52=Precificação!$B$26,$F$3/$E52,0),2)) -> 705.09 | H52: =IF($E52="","",F52+G52) -> 1116.61 | I52: =IF($E52="","",$E52*F52) -> 411.52 | J52: =IF($E52="","",$E52*G52) -> 705.09 | K52: =IF($E52="","",I52+J52) -> 1116.61 | L52: =IF($E52="","",IF(R52=0,"SEM CUSTO — falta linha de custo","OK")) -> OK | M52: =IF(AND(ISNUMBER(E52),NOT(ISNUMBER(E51))),"F"&ROW()&":G"&X52,"") | N52: =IF($E52="","",SUMIFS('Rateio Anexo'!$K$6:$K$600,'Rateio Anexo'!$D$6:$D$600,$B52,'Rateio Anexo'!$B$6:$B$600,"MAT")) -> 215.0668 | O52: =IF($E52="","",SUMIFS('Rateio Anexo'!$K$6:$K$600,'Rateio Anexo'!$D$6:$D$600,$B52,'Rateio Anexo'!$B$6:$B$600,"MO")) -> 364.85434 | P52: =IF($E52="","",IF($N$3=0,0,N52/$N$3*$R$4)) -> 0.76952403 | Q52: =IF($E52="","",IF($O$3=0,0,O52/$O$3*$T$4)) -> 75.678823 | R52: =IF($E52="","",N52+O52+P52+Q52) -> 656.36948 | S52: =IF($E52="","",(N52+P52)*Precificação!$B$19) -> 411.52012 | T52: =IF($E52="","",(O52+Q52)*Precificação!$B$20) -> 705.09294 | U52: =IF($E52="","",IF($E52=INT($E52),0.01,IF($E52*2=INT($E52*2),0.02,0.05))) -> 0.01 | V52: =IF($E52="","",ROUND(S52/$E52/U52,0)*U52) -> 411.52 | W52: =IF($E52="","",ROUND(T52/$E52/U52,0)*U52) -> 705.09 | X52: =IF(NOT(ISNUMBER(E52)),"",IF(NOT(ISNUMBER(E53)),ROW(),X53)) -> 53
A53: 45 | B53: A.5.5 | C53: Pintura electroestática de suporte metálico com tinta acrílica fosca Terra Roxa, da Suvinil Dimensões aproximadas: 100x85x50cm. | D53: unid | E53: 1 | F53: =IF($E53="","",V53) -> 478.36 | G53: =IF($E53="","",ROUND(W53+IF($B53=Precificação!$B$26,$F$3/$E53,0),2)) -> 0 | H53: =IF($E53="","",F53+G53) -> 478.36 | I53: =IF($E53="","",$E53*F53) -> 478.36 | J53: =IF($E53="","",$E53*G53) -> 0 | K53: =IF($E53="","",I53+J53) -> 478.36 | L53: =IF($E53="","",IF(R53=0,"SEM CUSTO — falta linha de custo","OK")) -> OK | M53: =IF(AND(ISNUMBER(E53),NOT(ISNUMBER(E52))),"F"&ROW()&":G"&X53,"") | N53: =IF($E53="","",SUMIFS('Rateio Anexo'!$K$6:$K$600,'Rateio Anexo'!$D$6:$D$600,$B53,'Rateio Anexo'!$B$6:$B$600,"MAT")) -> 250 | O53: =IF($E53="","",SUMIFS('Rateio Anexo'!$K$6:$K$600,'Rateio Anexo'!$D$6:$D$600,$B53,'Rateio Anexo'!$B$6:$B$600,"MO")) -> 0 | P53: =IF($E53="","",IF($N$3=0,0,N53/$N$3*$R$4)) -> 0.89451746 | Q53: =IF($E53="","",IF($O$3=0,0,O53/$O$3*$T$4)) -> 0 | R53: =IF($E53="","",N53+O53+P53+Q53) -> 250.89452 | S53: =IF($E53="","",(N53+P53)*Precificação!$B$19) -> 478.36315 | T53: =IF($E53="","",(O53+Q53)*Precificação!$B$20) -> 0 | U53: =IF($E53="","",IF($E53=INT($E53),0.01,IF($E53*2=INT($E53*2),0.02,0.05))) -> 0.01 | V53: =IF($E53="","",ROUND(S53/$E53/U53,0)*U53) -> 478.36 | W53: =IF($E53="","",ROUND(T53/$E53/U53,0)*U53) -> 0 | X53: =IF(NOT(ISNUMBER(E53)),"",IF(NOT(ISNUMBER(E54)),ROW(),X54)) -> 53
A54: 46 | B54: A.6 | C54: Comunicação Visual | F54: =IF($E54="","",V54) | G54: =IF($E54="","",ROUND(W54+IF($B54=Precificação!$B$26,$F$3/$E54,0),2)) | H54: =IF($E54="","",F54+G54) | I54: =IF($E54="","",$E54*F54) | J54: =IF($E54="","",$E54*G54) | K54: =IF($E54="","",I54+J54) | L54: =IF($E54="","",IF(R54=0,"SEM CUSTO — falta linha de custo","OK")) | M54: =IF(AND(ISNUMBER(E54),NOT(ISNUMBER(E53))),"F"&ROW()&":G"&X54,"") | N54: =IF($E54="","",SUMIFS('Rateio Anexo'!$K$6:$K$600,'Rateio Anexo'!$D$6:$D$600,$B54,'Rateio Anexo'!$B$6:$B$600,"MAT")) | O54: =IF($E54="","",SUMIFS('Rateio Anexo'!$K$6:$K$600,'Rateio Anexo'!$D$6:$D$600,$B54,'Rateio Anexo'!$B$6:$B$600,"MO")) | P54: =IF($E54="","",IF($N$3=0,0,N54/$N$3*$R$4)) | Q54: =IF($E54="","",IF($O$3=0,0,O54/$O$3*$T$4)) | R54: =IF($E54="","",N54+O54+P54+Q54) | S54: =IF($E54="","",(N54+P54)*Precificação!$B$19) | T54: =IF($E54="","",(O54+Q54)*Precificação!$B$20) | U54: =IF($E54="","",IF($E54=INT($E54),0.01,IF($E54*2=INT($E54*2),0.02,0.05))) | V54: =IF($E54="","",ROUND(S54/$E54/U54,0)*U54) | W54: =IF($E54="","",ROUND(T54/$E54/U54,0)*U54) | X54: =IF(NOT(ISNUMBER(E54)),"",IF(NOT(ISNUMBER(E55)),ROW(),X55))
A55: 47 | B55: A.6.1 | C55: Substituição do insulfilme dos 12 painéis de vidro do 6º andar Medida aproximada de cada painel de vidro: 320x190cm. Essas medidas precisam ser conferidas in loco, pois, por conta da altura, não foi possível a checagem precisa da medida por parte da equipe de arquitetura. Considerar a remoção da película atual e aplicação de novo filme na tonalidade chocolate ou âmbar, a serem definidos e testados in loco. Incluir no serviço a remoção destes ao final da exposição. | D55: unid | E55: 12 | F55: =IF($E55="","",V55) -> 2181.57 | G55: =IF($E55="","",ROUND(W55+IF($B55=Precificação!$B$26,$F$3/$E55,0),2)) -> 201.31 | H55: =IF($E55="","",F55+G55) -> 2382.88 | I55: =IF($E55="","",$E55*F55) -> 26178.84 | J55: =IF($E55="","",$E55*G55) -> 2415.72 | K55: =IF($E55="","",I55+J55) -> 28594.56 | L55: =IF($E55="","",IF(R55=0,"SEM CUSTO — falta linha de custo","OK")) -> OK | M55: =IF(AND(ISNUMBER(E55),NOT(ISNUMBER(E54))),"F"&ROW()&":G"&X55,"") -> F55:G55 | N55: =IF($E55="","",SUMIFS('Rateio Anexo'!$K$6:$K$600,'Rateio Anexo'!$D$6:$D$600,$B55,'Rateio Anexo'!$B$6:$B$600,"MAT")) -> 13681.459 | O55: =IF($E55="","",SUMIFS('Rateio Anexo'!$K$6:$K$600,'Rateio Anexo'!$D$6:$D$600,$B55,'Rateio Anexo'!$B$6:$B$600,"MO")) -> 1250 | P55: =IF($E55="","",IF($N$3=0,0,N55/$N$3*$R$4)) -> 48.953217 | Q55: =IF($E55="","",IF($O$3=0,0,O55/$O$3*$T$4)) -> 259.27752 | R55: =IF($E55="","",N55+O55+P55+Q55) -> 15239.69 | S55: =IF($E55="","",(N55+P55)*Precificação!$B$19) -> 26178.824 | T55: =IF($E55="","",(O55+Q55)*Precificação!$B$20) -> 2415.6659 | U55: =IF($E55="","",IF($E55=INT($E55),0.01,IF($E55*2=INT($E55*2),0.02,0.05))) -> 0.01 | V55: =IF($E55="","",ROUND(S55/$E55/U55,0)*U55) -> 2181.57 | W55: =IF($E55="","",ROUND(T55/$E55/U55,0)*U55) -> 201.31 | X55: =IF(NOT(ISNUMBER(E55)),"",IF(NOT(ISNUMBER(E56)),ROW(),X56)) -> 55
A56: 48 | B56: A.7 | C56: Manutenção e serviços gerais | F56: =IF($E56="","",V56) | G56: =IF($E56="","",ROUND(W56+IF($B56=Precificação!$B$26,$F$3/$E56,0),2)) | H56: =IF($E56="","",F56+G56) | I56: =IF($E56="","",$E56*F56) | J56: =IF($E56="","",$E56*G56) | K56: =IF($E56="","",I56+J56) | L56: =IF($E56="","",IF(R56=0,"SEM CUSTO — falta linha de custo","OK")) | M56: =IF(AND(ISNUMBER(E56),NOT(ISNUMBER(E55))),"F"&ROW()&":G"&X56,"") | N56: =IF($E56="","",SUMIFS('Rateio Anexo'!$K$6:$K$600,'Rateio Anexo'!$D$6:$D$600,$B56,'Rateio Anexo'!$B$6:$B$600,"MAT")) | O56: =IF($E56="","",SUMIFS('Rateio Anexo'!$K$6:$K$600,'Rateio Anexo'!$D$6:$D$600,$B56,'Rateio Anexo'!$B$6:$B$600,"MO")) | P56: =IF($E56="","",IF($N$3=0,0,N56/$N$3*$R$4)) | Q56: =IF($E56="","",IF($O$3=0,0,O56/$O$3*$T$4)) | R56: =IF($E56="","",N56+O56+P56+Q56) | S56: =IF($E56="","",(N56+P56)*Precificação!$B$19) | T56: =IF($E56="","",(O56+Q56)*Precificação!$B$20) | U56: =IF($E56="","",IF($E56=INT($E56),0.01,IF($E56*2=INT($E56*2),0.02,0.05))) | V56: =IF($E56="","",ROUND(S56/$E56/U56,0)*U56) | W56: =IF($E56="","",ROUND(T56/$E56/U56,0)*U56) | X56: =IF(NOT(ISNUMBER(E56)),"",IF(NOT(ISNUMBER(E57)),ROW(),X57))
A57: 49 | B57: A.7.1 | C57: Considerar no escopo de montagem ao menos um cenotécnico e um pintor disponível até a abertura da exposição, para realização de retoques e ajustes gerais. | D57: unid | E57: 2 | F57: =IF($E57="","",V57) -> 0 | G57: =IF($E57="","",ROUND(W57+IF($B57=Precificação!$B$26,$F$3/$E57,0),2)) -> 0 | H57: =IF($E57="","",F57+G57) -> 0 | I57: =IF($E57="","",$E57*F57) -> 0 | J57: =IF($E57="","",$E57*G57) -> 0 | K57: =IF($E57="","",I57+J57) -> 0 | L57: =IF($E57="","",IF(R57=0,"SEM CUSTO — falta linha de custo","OK")) -> SEM CUSTO — falta linha de custo | M57: =IF(AND(ISNUMBER(E57),NOT(ISNUMBER(E56))),"F"&ROW()&":G"&X57,"") -> F57:G61 | N57: =IF($E57="","",SUMIFS('Rateio Anexo'!$K$6:$K$600,'Rateio Anexo'!$D$6:$D$600,$B57,'Rateio Anexo'!$B$6:$B$600,"MAT")) -> 0 | O57: =IF($E57="","",SUMIFS('Rateio Anexo'!$K$6:$K$600,'Rateio Anexo'!$D$6:$D$600,$B57,'Rateio Anexo'!$B$6:$B$600,"MO")) -> 0 | P57: =IF($E57="","",IF($N$3=0,0,N57/$N$3*$R$4)) -> 0 | Q57: =IF($E57="","",IF($O$3=0,0,O57/$O$3*$T$4)) -> 0 | R57: =IF($E57="","",N57+O57+P57+Q57) -> 0 | S57: =IF($E57="","",(N57+P57)*Precificação!$B$19) -> 0 | T57: =IF($E57="","",(O57+Q57)*Precificação!$B$20) -> 0 | U57: =IF($E57="","",IF($E57=INT($E57),0.01,IF($E57*2=INT($E57*2),0.02,0.05))) -> 0.01 | V57: =IF($E57="","",ROUND(S57/$E57/U57,0)*U57) -> 0 | W57: =IF($E57="","",ROUND(T57/$E57/U57,0)*U57) -> 0 | X57: =IF(NOT(ISNUMBER(E57)),"",IF(NOT(ISNUMBER(E58)),ROW(),X58)) -> 61
A58: 50 | B58: A.7.2 | C58: MANUTENÇÃO. Fornecimento de material e mão de obra para realização de serviços de manutenção preventiva e corretiva para os 8 meses de duração da exposição. Deverá considerar no mínimo 1 (uma) visita quinzenal, às segundas-feiras. O atendimento aos chamados do Sesc deverá ser realizado por equipe técnica habilitada, contemplando no mínimo 2 (dois) profissionais tecnicamente capacitados de acordo com a natureza do reparo a ser executado. A manutenção da exposição deverá ser realizada de maneira periódica, mantendo as características do projeto do início até o fim. A manutenção consiste em: repintura das áreas com desgaste, revisão e troca de lâmpadas, revisão e manutenção semanal das estruturas, substituição de pisos e revestimentos quando danificados e manutenção de material gráfico quando necessária. Os materiais empregados e a mão-de-obra são de responsabilidade da CONTRATADA. No caso de eventuais ocorrências, a CONTRATADA receberá um chamado da equipe do Sesc e deverá recorrer à imediata limpeza e/ou conserto. A CONTRATADA deverá atender aos chamados do Sesc em até 24 horas (corridas) para serviços de manutenção corretiva durante todo o período da exposição. | D58: visita | E58: 18 | F58: =IF($E58="","",V58) -> 0 | G58: =IF($E58="","",ROUND(W58+IF($B58=Precificação!$B$26,$F$3/$E58,0),2)) -> 773.01 | H58: =IF($E58="","",F58+G58) -> 773.01 | I58: =IF($E58="","",$E58*F58) -> 0 | J58: =IF($E58="","",$E58*G58) -> 13914.18 | K58: =IF($E58="","",I58+J58) -> 13914.18 | L58: =IF($E58="","",IF(R58=0,"SEM CUSTO — falta linha de custo","OK")) -> OK | M58: =IF(AND(ISNUMBER(E58),NOT(ISNUMBER(E57))),"F"&ROW()&":G"&X58,"") | N58: =IF($E58="","",SUMIFS('Rateio Anexo'!$K$6:$K$600,'Rateio Anexo'!$D$6:$D$600,$B58,'Rateio Anexo'!$B$6:$B$600,"MAT")) -> 0 | O58: =IF($E58="","",SUMIFS('Rateio Anexo'!$K$6:$K$600,'Rateio Anexo'!$D$6:$D$600,$B58,'Rateio Anexo'!$B$6:$B$600,"MO")) -> 7200 | P58: =IF($E58="","",IF($N$3=0,0,N58/$N$3*$R$4)) -> 0 | Q58: =IF($E58="","",IF($O$3=0,0,O58/$O$3*$T$4)) -> 1493.4385 | R58: =IF($E58="","",N58+O58+P58+Q58) -> 8693.4385 | S58: =IF($E58="","",(N58+P58)*Precificação!$B$19) -> 0 | T58: =IF($E58="","",(O58+Q58)*Precificação!$B$20) -> 13914.235 | U58: =IF($E58="","",IF($E58=INT($E58),0.01,IF($E58*2=INT($E58*2),0.02,0.05))) -> 0.01 | V58: =IF($E58="","",ROUND(S58/$E58/U58,0)*U58) -> 0 | W58: =IF($E58="","",ROUND(T58/$E58/U58,0)*U58) -> 773.01 | X58: =IF(NOT(ISNUMBER(E58)),"",IF(NOT(ISNUMBER(E59)),ROW(),X59)) -> 61
A59: 51 | B59: A.7.3 | C59: MONTAGEM NOTURNA. A contratada deve prever diárias de equipe para montagem noturna, a depender do cronograma de montagem que será confirmado com equipe do Sesc e Produção. | D59: diária | E59: 4 | F59: =IF($E59="","",V59) -> 0 | G59: =IF($E59="","",ROUND(W59+IF($B59=Precificação!$B$26,$F$3/$E59,0),2)) -> 0 | H59: =IF($E59="","",F59+G59) -> 0 | I59: =IF($E59="","",$E59*F59) -> 0 | J59: =IF($E59="","",$E59*G59) -> 0 | K59: =IF($E59="","",I59+J59) -> 0 | L59: =IF($E59="","",IF(R59=0,"SEM CUSTO — falta linha de custo","OK")) -> SEM CUSTO — falta linha de custo | M59: =IF(AND(ISNUMBER(E59),NOT(ISNUMBER(E58))),"F"&ROW()&":G"&X59,"") | N59: =IF($E59="","",SUMIFS('Rateio Anexo'!$K$6:$K$600,'Rateio Anexo'!$D$6:$D$600,$B59,'Rateio Anexo'!$B$6:$B$600,"MAT")) -> 0 | O59: =IF($E59="","",SUMIFS('Rateio Anexo'!$K$6:$K$600,'Rateio Anexo'!$D$6:$D$600,$B59,'Rateio Anexo'!$B$6:$B$600,"MO")) -> 0 | P59: =IF($E59="","",IF($N$3=0,0,N59/$N$3*$R$4)) -> 0 | Q59: =IF($E59="","",IF($O$3=0,0,O59/$O$3*$T$4)) -> 0 | R59: =IF($E59="","",N59+O59+P59+Q59) -> 0 | S59: =IF($E59="","",(N59+P59)*Precificação!$B$19) -> 0 | T59: =IF($E59="","",(O59+Q59)*Precificação!$B$20) -> 0 | U59: =IF($E59="","",IF($E59=INT($E59),0.01,IF($E59*2=INT($E59*2),0.02,0.05))) -> 0.01 | V59: =IF($E59="","",ROUND(S59/$E59/U59,0)*U59) -> 0 | W59: =IF($E59="","",ROUND(T59/$E59/U59,0)*U59) -> 0 | X59: =IF(NOT(ISNUMBER(E59)),"",IF(NOT(ISNUMBER(E60)),ROW(),X60)) -> 61
A60: 52 | B60: A.7.4 | C60: LIMPEZA DO ESPAÇO EXPOSITIVO. Fornecimento de material e mão de obra para serviço de limpeza do espaço. Esta equipe deverá acompanhar a montagem cenotécnica a fim de manter o espaço expositivo limpo durante a montagem. TOTAL de diárias : 4 | D60: verba | E60: 1 | F60: =IF($E60="","",V60) -> 0 | G60: =IF($E60="","",ROUND(W60+IF($B60=Precificação!$B$26,$F$3/$E60,0),2)) -> 1739.28 | H60: =IF($E60="","",F60+G60) -> 1739.28 | I60: =IF($E60="","",$E60*F60) -> 0 | J60: =IF($E60="","",$E60*G60) -> 1739.28 | K60: =IF($E60="","",I60+J60) -> 1739.28 | L60: =IF($E60="","",IF(R60=0,"SEM CUSTO — falta linha de custo","OK")) -> OK | M60: =IF(AND(ISNUMBER(E60),NOT(ISNUMBER(E59))),"F"&ROW()&":G"&X60,"") | N60: =IF($E60="","",SUMIFS('Rateio Anexo'!$K$6:$K$600,'Rateio Anexo'!$D$6:$D$600,$B60,'Rateio Anexo'!$B$6:$B$600,"MAT")) -> 0 | O60: =IF($E60="","",SUMIFS('Rateio Anexo'!$K$6:$K$600,'Rateio Anexo'!$D$6:$D$600,$B60,'Rateio Anexo'!$B$6:$B$600,"MO")) -> 900 | P60: =IF($E60="","",IF($N$3=0,0,N60/$N$3*$R$4)) -> 0 | Q60: =IF($E60="","",IF($O$3=0,0,O60/$O$3*$T$4)) -> 186.67982 | R60: =IF($E60="","",N60+O60+P60+Q60) -> 1086.6798 | S60: =IF($E60="","",(N60+P60)*Precificação!$B$19) -> 0 | T60: =IF($E60="","",(O60+Q60)*Precificação!$B$20) -> 1739.2794 | U60: =IF($E60="","",IF($E60=INT($E60),0.01,IF($E60*2=INT($E60*2),0.02,0.05))) -> 0.01 | V60: =IF($E60="","",ROUND(S60/$E60/U60,0)*U60) -> 0 | W60: =IF($E60="","",ROUND(T60/$E60/U60,0)*U60) -> 1739.28 | X60: =IF(NOT(ISNUMBER(E60)),"",IF(NOT(ISNUMBER(E61)),ROW(),X61)) -> 61
A61: 53 | B61: A.7.5 | C61: DESMONTAGEM FINAL. Fornecimento de material e mão de obra para serviços de desmontagem, transporte e descarte dos materiais instalados (conforme determinação do Sesc). Incluso neste item o transporte e descarte em local adequado, conforme legislação vigente e limpeza final do ambiente. A desmontagem das instalações cenográficas e provisórias deve seguir os mesmos cuidados da montagem. Recomenda-se realizar uma reunião técnica envolvendo as equipes que executaram o projeto de maneira a sincronizar as atividades de desmobilização. As atividades de desmontagem devem ainda atender a todas as recomendações de segurança para a execução dos serviços e restrições de horários e de interferências à estrutura e programação da Unidade. A limpeza abrange todos os tipos de pisos, divisórias, paredes, carpetes, forros, tetos, estruturas metálicas aparentes ou sobre o forro, lajes de cobertura, calhas, esquadrias metálicas, esquadrias de madeiras, vidros, cobertura, tubulações aparentes, mobiliários, equipamentos diversos, louças, metais, e outros que possam ser afetados pela construção cenográfica. | D61: verba | E61: 1 | F61: =IF($E61="","",V61) -> 0 | G61: =IF($E61="","",ROUND(W61+IF($B61=Precificação!$B$26,$F$3/$E61,0),2)) -> 837.01 | H61: =IF($E61="","",F61+G61) -> 837.01 | I61: =IF($E61="","",$E61*F61) -> 0 | J61: =IF($E61="","",$E61*G61) -> 837.01 | K61: =IF($E61="","",I61+J61) -> 837.01 | L61: =IF($E61="","",IF(R61=0,"SEM CUSTO — falta linha de custo","OK")) -> OK | M61: =IF(AND(ISNUMBER(E61),NOT(ISNUMBER(E60))),"F"&ROW()&":G"&X61,"") | N61: =IF($E61="","",SUMIFS('Rateio Anexo'!$K$6:$K$600,'Rateio Anexo'!$D$6:$D$600,$B61,'Rateio Anexo'!$B$6:$B$600,"MAT")) -> 0 | O61: =IF($E61="","",SUMIFS('Rateio Anexo'!$K$6:$K$600,'Rateio Anexo'!$D$6:$D$600,$B61,'Rateio Anexo'!$B$6:$B$600,"MO")) -> 433.33333 | P61: =IF($E61="","",IF($N$3=0,0,N61/$N$3*$R$4)) -> 0 | Q61: =IF($E61="","",IF($O$3=0,0,O61/$O$3*$T$4)) -> 89.882874 | R61: =IF($E61="","",N61+O61+P61+Q61) -> 523.21621 | S61: =IF($E61="","",(N61+P61)*Precificação!$B$19) -> 0 | T61: =IF($E61="","",(O61+Q61)*Precificação!$B$20) -> 837.43083 | U61: =IF($E61="","",IF($E61=INT($E61),0.01,IF($E61*2=INT($E61*2),0.02,0.05))) -> 0.01 | V61: =IF($E61="","",ROUND(S61/$E61/U61,0)*U61) -> 0 | W61: =IF($E61="","",ROUND(T61/$E61/U61,0)*U61) -> 837.43 | X61: =IF(NOT(ISNUMBER(E61)),"",IF(NOT(ISNUMBER(E62)),ROW(),X62)) -> 61
B62: B | C62: PROJETO DE ELÉTRICA (conforme projeto e memoriais), incluindo todos os materiais, equipamentos, instrumentos e mão-de-obra, detalhados ou não nos projetos, memoriais e neste planilha, mas necessários à perfeita execução, funcionamento e operação do sistema, dentro das Normas Técnicas vigentes e da segurança, que deverão ter seus custos incluídos nos itens apontados nesta planilha) | F62: =IF($E62="","",V62) | G62: =IF($E62="","",ROUND(W62+IF($B62=Precificação!$B$26,$F$3/$E62,0),2)) | H62: =IF($E62="","",F62+G62) | I62: =IF($E62="","",$E62*F62) | J62: =IF($E62="","",$E62*G62) | K62: =IF($E62="","",I62+J62) | L62: =IF($E62="","",IF(R62=0,"SEM CUSTO — falta linha de custo","OK")) | M62: =IF(AND(ISNUMBER(E62),NOT(ISNUMBER(E61))),"F"&ROW()&":G"&X62,"") | N62: =IF($E62="","",SUMIFS('Rateio Anexo'!$K$6:$K$600,'Rateio Anexo'!$D$6:$D$600,$B62,'Rateio Anexo'!$B$6:$B$600,"MAT")) | O62: =IF($E62="","",SUMIFS('Rateio Anexo'!$K$6:$K$600,'Rateio Anexo'!$D$6:$D$600,$B62,'Rateio Anexo'!$B$6:$B$600,"MO")) | P62: =IF($E62="","",IF($N$3=0,0,N62/$N$3*$R$4)) | Q62: =IF($E62="","",IF($O$3=0,0,O62/$O$3*$T$4)) | R62: =IF($E62="","",N62+O62+P62+Q62) | S62: =IF($E62="","",(N62+P62)*Precificação!$B$19) | T62: =IF($E62="","",(O62+Q62)*Precificação!$B$20) | U62: =IF($E62="","",IF($E62=INT($E62),0.01,IF($E62*2=INT($E62*2),0.02,0.05))) | V62: =IF($E62="","",ROUND(S62/$E62/U62,0)*U62) | W62: =IF($E62="","",ROUND(T62/$E62/U62,0)*U62) | X62: =IF(NOT(ISNUMBER(E62)),"",IF(NOT(ISNUMBER(E63)),ROW(),X63))
A63: 54 | B63: B.1 | C63: Cabo PP Afumex 3x2,5mm - Cabo Afumex 0,6/1kV, CONDUTOR Metal: fios de cobre nu, têmpera mole. Encordoamento: extraflexível (classe 5). ISOLAÇÃO Composto termofixo em dupla camada de borracha HEPR (EPR/B - Alto módulo). instalado, de acordo com a NBR 5410/2004 e NBR 13570/1996 | D63: m | E63: 260 | F63: =IF($E63="","",V63) -> 29.35 | G63: =IF($E63="","",ROUND(W63+IF($B63=Precificação!$B$26,$F$3/$E63,0),2)) -> 21.08 | H63: =IF($E63="","",F63+G63) -> 50.43 | I63: =IF($E63="","",$E63*F63) -> 7631 | J63: =IF($E63="","",$E63*G63) -> 5480.8 | K63: =IF($E63="","",I63+J63) -> 13111.8 | L63: =IF($E63="","",IF(R63=0,"SEM CUSTO — falta linha de custo","OK")) -> OK | M63: =IF(AND(ISNUMBER(E63),NOT(ISNUMBER(E62))),"F"&ROW()&":G"&X63,"") -> F63:G70 | N63: =IF($E63="","",SUMIFS('Rateio Anexo'!$K$6:$K$600,'Rateio Anexo'!$D$6:$D$600,$B63,'Rateio Anexo'!$B$6:$B$600,"MAT")) -> 3987.5 | O63: =IF($E63="","",SUMIFS('Rateio Anexo'!$K$6:$K$600,'Rateio Anexo'!$D$6:$D$600,$B63,'Rateio Anexo'!$B$6:$B$600,"MO")) -> 2836.5439 | P63: =IF($E63="","",IF($N$3=0,0,N63/$N$3*$R$4)) -> 14.267554 | Q63: =IF($E63="","",IF($O$3=0,0,O63/$O$3*$T$4)) -> 588.36166 | R63: =IF($E63="","",N63+O63+P63+Q63) -> 7426.6732 | S63: =IF($E63="","",(N63+P63)*Precificação!$B$19) -> 7629.8922 | T63: =IF($E63="","",(O63+Q63)*Precificação!$B$20) -> 5481.7139 | U63: =IF($E63="","",IF($E63=INT($E63),0.01,IF($E63*2=INT($E63*2),0.02,0.05))) -> 0.01 | V63: =IF($E63="","",ROUND(S63/$E63/U63,0)*U63) -> 29.35 | W63: =IF($E63="","",ROUND(T63/$E63/U63,0)*U63) -> 21.08 | X63: =IF(NOT(ISNUMBER(E63)),"",IF(NOT(ISNUMBER(E64)),ROW(),X64)) -> 70
A64: 55 | B64: B.2 | C64: Cabos flexíveis afumex unipolares tipo HEPR 90°C - 0,6/1KV #1x16mm, cor PRETO | D64: m | E64: 93 | F64: =IF($E64="","",V64) -> 8.15 | G64: =IF($E64="","",ROUND(W64+IF($B64=Precificação!$B$26,$F$3/$E64,0),2)) -> 5.85 | H64: =IF($E64="","",F64+G64) -> 14 | I64: =IF($E64="","",$E64*F64) -> 757.95 | J64: =IF($E64="","",$E64*G64) -> 544.05 | K64: =IF($E64="","",I64+J64) -> 1302 | L64: =IF($E64="","",IF(R64=0,"SEM CUSTO — falta linha de custo","OK")) -> OK | M64: =IF(AND(ISNUMBER(E64),NOT(ISNUMBER(E63))),"F"&ROW()&":G"&X64,"") | N64: =IF($E64="","",SUMIFS('Rateio Anexo'!$K$6:$K$600,'Rateio Anexo'!$D$6:$D$600,$B64,'Rateio Anexo'!$B$6:$B$600,"MAT")) -> 396.09 | O64: =IF($E64="","",SUMIFS('Rateio Anexo'!$K$6:$K$600,'Rateio Anexo'!$D$6:$D$600,$B64,'Rateio Anexo'!$B$6:$B$600,"MO")) -> 281.76218 | P64: =IF($E64="","",IF($N$3=0,0,N64/$N$3*$R$4)) -> 1.4172377 | Q64: =IF($E64="","",IF($O$3=0,0,O64/$O$3*$T$4)) -> 58.443679 | R64: =IF($E64="","",N64+O64+P64+Q64) -> 737.7131 | S64: =IF($E64="","",(N64+P64)*Precificação!$B$19) -> 757.89944 | T64: =IF($E64="","",(O64+Q64)*Precificação!$B$20) -> 544.51462 | U64: =IF($E64="","",IF($E64=INT($E64),0.01,IF($E64*2=INT($E64*2),0.02,0.05))) -> 0.01 | V64: =IF($E64="","",ROUND(S64/$E64/U64,0)*U64) -> 8.15 | W64: =IF($E64="","",ROUND(T64/$E64/U64,0)*U64) -> 5.85 | X64: =IF(NOT(ISNUMBER(E64)),"",IF(NOT(ISNUMBER(E65)),ROW(),X65)) -> 70
A65: 56 | B65: B.3 | C65: Cabos flexíveis afumex unipolares tipo HEPR 90°C - 0,6/1KV #1x16,0mm, cor AZUL | D65: m | E65: 31 | F65: =IF($E65="","",V65) -> 8.15 | G65: =IF($E65="","",ROUND(W65+IF($B65=Precificação!$B$26,$F$3/$E65,0),2)) -> 5.85 | H65: =IF($E65="","",F65+G65) -> 14 | I65: =IF($E65="","",$E65*F65) -> 252.65 | J65: =IF($E65="","",$E65*G65) -> 181.35 | K65: =IF($E65="","",I65+J65) -> 434 | L65: =IF($E65="","",IF(R65=0,"SEM CUSTO — falta linha de custo","OK")) -> OK | M65: =IF(AND(ISNUMBER(E65),NOT(ISNUMBER(E64))),"F"&ROW()&":G"&X65,"") | N65: =IF($E65="","",SUMIFS('Rateio Anexo'!$K$6:$K$600,'Rateio Anexo'!$D$6:$D$600,$B65,'Rateio Anexo'!$B$6:$B$600,"MAT")) -> 132.03 | O65: =IF($E65="","",SUMIFS('Rateio Anexo'!$K$6:$K$600,'Rateio Anexo'!$D$6:$D$600,$B65,'Rateio Anexo'!$B$6:$B$600,"MO")) -> 93.920726 | P65: =IF($E65="","",IF($N$3=0,0,N65/$N$3*$R$4)) -> 0.47241256 | Q65: =IF($E65="","",IF($O$3=0,0,O65/$O$3*$T$4)) -> 19.481226 | R65: =IF($E65="","",N65+O65+P65+Q65) -> 245.90437 | S65: =IF($E65="","",(N65+P65)*Precificação!$B$19) -> 252.63315 | T65: =IF($E65="","",(O65+Q65)*Precificação!$B$20) -> 181.50487 | U65: =IF($E65="","",IF($E65=INT($E65),0.01,IF($E65*2=INT($E65*2),0.02,0.05))) -> 0.01 | V65: =IF($E65="","",ROUND(S65/$E65/U65,0)*U65) -> 8.15 | W65: =IF($E65="","",ROUND(T65/$E65/U65,0)*U65) -> 5.85 | X65: =IF(NOT(ISNUMBER(E65)),"",IF(NOT(ISNUMBER(E66)),ROW(),X66)) -> 70
A66: 57 | B66: B.4 | C66: Cabos flexíveis afumex unipolares tipo HEPR 90°C - 0,6/1KV #1x16,0mm, cor VERDE | D66: m | E66: 31 | F66: =IF($E66="","",V66) -> 8.15 | G66: =IF($E66="","",ROUND(W66+IF($B66=Precificação!$B$26,$F$3/$E66,0),2)) -> 5.85 | H66: =IF($E66="","",F66+G66) -> 14 | I66: =IF($E66="","",$E66*F66) -> 252.65 | J66: =IF($E66="","",$E66*G66) -> 181.35 | K66: =IF($E66="","",I66+J66) -> 434 | L66: =IF($E66="","",IF(R66=0,"SEM CUSTO — falta linha de custo","OK")) -> OK | M66: =IF(AND(ISNUMBER(E66),NOT(ISNUMBER(E65))),"F"&ROW()&":G"&X66,"") | N66: =IF($E66="","",SUMIFS('Rateio Anexo'!$K$6:$K$600,'Rateio Anexo'!$D$6:$D$600,$B66,'Rateio Anexo'!$B$6:$B$600,"MAT")) -> 132.03 | O66: =IF($E66="","",SUMIFS('Rateio Anexo'!$K$6:$K$600,'Rateio Anexo'!$D$6:$D$600,$B66,'Rateio Anexo'!$B$6:$B$600,"MO")) -> 93.920726 | P66: =IF($E66="","",IF($N$3=0,0,N66/$N$3*$R$4)) -> 0.47241256 | Q66: =IF($E66="","",IF($O$3=0,0,O66/$O$3*$T$4)) -> 19.481226 | R66: =IF($E66="","",N66+O66+P66+Q66) -> 245.90437 | S66: =IF($E66="","",(N66+P66)*Precificação!$B$19) -> 252.63315 | T66: =IF($E66="","",(O66+Q66)*Precificação!$B$20) -> 181.50487 | U66: =IF($E66="","",IF($E66=INT($E66),0.01,IF($E66*2=INT($E66*2),0.02,0.05))) -> 0.01 | V66: =IF($E66="","",ROUND(S66/$E66/U66,0)*U66) -> 8.15 | W66: =IF($E66="","",ROUND(T66/$E66/U66,0)*U66) -> 5.85 | X66: =IF(NOT(ISNUMBER(E66)),"",IF(NOT(ISNUMBER(E67)),ROW(),X67)) -> 70
A67: 58 | B67: B.5 | C67: Prolongador saída axial, 2P+T, com prensa cabos, para cabos até 8mm de diâmetro externo, em termoplástico preto, 20A - 250V (plug femea)(REF. PIAL LEGRAND) | D67: pç | E67: 18 | F67: =IF($E67="","",V67) -> 0 | G67: =IF($E67="","",ROUND(W67+IF($B67=Precificação!$B$26,$F$3/$E67,0),2)) -> 40.79 | H67: =IF($E67="","",F67+G67) -> 40.79 | I67: =IF($E67="","",$E67*F67) -> 0 | J67: =IF($E67="","",$E67*G67) -> 734.22 | K67: =IF($E67="","",I67+J67) -> 734.22 | L67: =IF($E67="","",IF(R67=0,"SEM CUSTO — falta linha de custo","OK")) -> OK | M67: =IF(AND(ISNUMBER(E67),NOT(ISNUMBER(E66))),"F"&ROW()&":G"&X67,"") | N67: =IF($E67="","",SUMIFS('Rateio Anexo'!$K$6:$K$600,'Rateio Anexo'!$D$6:$D$600,$B67,'Rateio Anexo'!$B$6:$B$600,"MAT")) -> 0 | O67: =IF($E67="","",SUMIFS('Rateio Anexo'!$K$6:$K$600,'Rateio Anexo'!$D$6:$D$600,$B67,'Rateio Anexo'!$B$6:$B$600,"MO")) -> 379.90838 | P67: =IF($E67="","",IF($N$3=0,0,N67/$N$3*$R$4)) -> 0 | Q67: =IF($E67="","",IF($O$3=0,0,O67/$O$3*$T$4)) -> 78.801362 | R67: =IF($E67="","",N67+O67+P67+Q67) -> 458.70974 | S67: =IF($E67="","",(N67+P67)*Precificação!$B$19) -> 0 | T67: =IF($E67="","",(O67+Q67)*Precificação!$B$20) -> 734.18536 | U67: =IF($E67="","",IF($E67=INT($E67),0.01,IF($E67*2=INT($E67*2),0.02,0.05))) -> 0.01 | V67: =IF($E67="","",ROUND(S67/$E67/U67,0)*U67) -> 0 | W67: =IF($E67="","",ROUND(T67/$E67/U67,0)*U67) -> 40.79 | X67: =IF(NOT(ISNUMBER(E67)),"",IF(NOT(ISNUMBER(E68)),ROW(),X68)) -> 70
A68: 59 | B68: B.6 | C68: Fornecimento e instalação de painel elétrico metalico de sobrepor, composto por: 01 minidisjuntor tripolar 50A, 01 IDR-dispositivo diferencial residual - tetrapolar de 63A - 30ma, 13 disjuntores 250V - 20A BIPOLAR, 4 disjuntores 250V - 25A UNIPOLAR,01 disjuntor 250V - 50A TRIPOLAR, 01 dispositivo de proteção contra surtos 175V, 20kA, barramentos de neutro e terra 16 FUROS, barramento tipo pente trifasico 80A-40 posições, caixa metálica 600x600x200mm em chapa com tratamento de Fosfato de Zinco e pintura a pó, placa de montagem pintado na cor laranja RAL 2008, porta e corpo pintado na cor bege RAL 7032, Fecho Lingueta Yale Regulável Com Uma Chave Tasco, pino metálico nas dobradiças, porta com borracha de vedação. Com todos acessorios para montagem(canaletas, cabos, barramentos para fase, neutro e terra, trilho din) do quadro conforme projeto de elétrica e memorial descritivo.Verificar projeto eletrico. Item será usado pelo setor de Infraestrutura após o término da exposição. | D68: pç | E68: 1 | F68: =IF($E68="","",V68) -> 5376.8 | G68: =IF($E68="","",ROUND(W68+IF($B68=Precificação!$B$26,$F$3/$E68,0),2)) -> 3862.98 | H68: =IF($E68="","",F68+G68) -> 9239.78 | I68: =IF($E68="","",$E68*F68) -> 5376.8 | J68: =IF($E68="","",$E68*G68) -> 3862.98 | K68: =IF($E68="","",I68+J68) -> 9239.78 | L68: =IF($E68="","",IF(R68=0,"SEM CUSTO — falta linha de custo","OK")) -> OK | M68: =IF(AND(ISNUMBER(E68),NOT(ISNUMBER(E67))),"F"&ROW()&":G"&X68,"") | N68: =IF($E68="","",SUMIFS('Rateio Anexo'!$K$6:$K$600,'Rateio Anexo'!$D$6:$D$600,$B68,'Rateio Anexo'!$B$6:$B$600,"MAT")) -> 2810 | O68: =IF($E68="","",SUMIFS('Rateio Anexo'!$K$6:$K$600,'Rateio Anexo'!$D$6:$D$600,$B68,'Rateio Anexo'!$B$6:$B$600,"MO")) -> 1998.9187 | P68: =IF($E68="","",IF($N$3=0,0,N68/$N$3*$R$4)) -> 10.054376 | Q68: =IF($E68="","",IF($O$3=0,0,O68/$O$3*$T$4)) -> 414.61976 | R68: =IF($E68="","",N68+O68+P68+Q68) -> 5233.5929 | S68: =IF($E68="","",(N68+P68)*Precificação!$B$19) -> 5376.8018 | T68: =IF($E68="","",(O68+Q68)*Precificação!$B$20) -> 3862.9758 | U68: =IF($E68="","",IF($E68=INT($E68),0.01,IF($E68*2=INT($E68*2),0.02,0.05))) -> 0.01 | V68: =IF($E68="","",ROUND(S68/$E68/U68,0)*U68) -> 5376.8 | W68: =IF($E68="","",ROUND(T68/$E68/U68,0)*U68) -> 3862.98 | X68: =IF(NOT(ISNUMBER(E68)),"",IF(NOT(ISNUMBER(E69)),ROW(),X69)) -> 70
A69: 60 | B69: B.7 | C69: Protetor Passa Cabos Fios De Piso 1 VIA | D69: m | E69: 6 | F69: =IF($E69="","",V69) -> 334.85 | G69: =IF($E69="","",ROUND(W69+IF($B69=Precificação!$B$26,$F$3/$E69,0),2)) -> 240.58 | H69: =IF($E69="","",F69+G69) -> 575.43 | I69: =IF($E69="","",$E69*F69) -> 2009.1 | J69: =IF($E69="","",$E69*G69) -> 1443.48 | K69: =IF($E69="","",I69+J69) -> 3452.58 | L69: =IF($E69="","",IF(R69=0,"SEM CUSTO — falta linha de custo","OK")) -> OK | M69: =IF(AND(ISNUMBER(E69),NOT(ISNUMBER(E68))),"F"&ROW()&":G"&X69,"") | N69: =IF($E69="","",SUMIFS('Rateio Anexo'!$K$6:$K$600,'Rateio Anexo'!$D$6:$D$600,$B69,'Rateio Anexo'!$B$6:$B$600,"MAT")) -> 1050 | O69: =IF($E69="","",SUMIFS('Rateio Anexo'!$K$6:$K$600,'Rateio Anexo'!$D$6:$D$600,$B69,'Rateio Anexo'!$B$6:$B$600,"MO")) -> 746.92693 | P69: =IF($E69="","",IF($N$3=0,0,N69/$N$3*$R$4)) -> 3.7569733 | Q69: =IF($E69="","",IF($O$3=0,0,O69/$O$3*$T$4)) -> 154.92909 | R69: =IF($E69="","",N69+O69+P69+Q69) -> 1955.613 | S69: =IF($E69="","",(N69+P69)*Precificação!$B$19) -> 2009.1252 | T69: =IF($E69="","",(O69+Q69)*Precificação!$B$20) -> 1443.4607 | U69: =IF($E69="","",IF($E69=INT($E69),0.01,IF($E69*2=INT($E69*2),0.02,0.05))) -> 0.01 | V69: =IF($E69="","",ROUND(S69/$E69/U69,0)*U69) -> 334.85 | W69: =IF($E69="","",ROUND(T69/$E69/U69,0)*U69) -> 240.58 | X69: =IF(NOT(ISNUMBER(E69)),"",IF(NOT(ISNUMBER(E70)),ROW(),X70)) -> 70
A70: 61 | B70: B.8 | C70: Eletroduto galvanizado a fogo bitola de 3/4" | D70: m | E70: 9 | F70: =IF($E70="","",V70) -> 94.21 | G70: =IF($E70="","",ROUND(W70+IF($B70=Precificação!$B$26,$F$3/$E70,0),2)) -> 67.68 | H70: =IF($E70="","",F70+G70) -> 161.89 | I70: =IF($E70="","",$E70*F70) -> 847.89 | J70: =IF($E70="","",$E70*G70) -> 609.12 | K70: =IF($E70="","",I70+J70) -> 1457.01 | L70: =IF($E70="","",IF(R70=0,"SEM CUSTO — falta linha de custo","OK")) -> OK | M70: =IF(AND(ISNUMBER(E70),NOT(ISNUMBER(E69))),"F"&ROW()&":G"&X70,"") | N70: =IF($E70="","",SUMIFS('Rateio Anexo'!$K$6:$K$600,'Rateio Anexo'!$D$6:$D$600,$B70,'Rateio Anexo'!$B$6:$B$600,"MAT")) -> 443.1 | O70: =IF($E70="","",SUMIFS('Rateio Anexo'!$K$6:$K$600,'Rateio Anexo'!$D$6:$D$600,$B70,'Rateio Anexo'!$B$6:$B$600,"MO")) -> 315.20316 | P70: =IF($E70="","",IF($N$3=0,0,N70/$N$3*$R$4)) -> 1.5854428 | Q70: =IF($E70="","",IF($O$3=0,0,O70/$O$3*$T$4)) -> 65.380076 | R70: =IF($E70="","",N70+O70+P70+Q70) -> 825.26868 | S70: =IF($E70="","",(N70+P70)*Precificação!$B$19) -> 847.85085 | T70: =IF($E70="","",(O70+Q70)*Precificação!$B$20) -> 609.14042 | U70: =IF($E70="","",IF($E70=INT($E70),0.01,IF($E70*2=INT($E70*2),0.02,0.05))) -> 0.01 | V70: =IF($E70="","",ROUND(S70/$E70/U70,0)*U70) -> 94.21 | W70: =IF($E70="","",ROUND(T70/$E70/U70,0)*U70) -> 67.68 | X70: =IF(NOT(ISNUMBER(E70)),"",IF(NOT(ISNUMBER(E71)),ROW(),X71)) -> 70
B71: C | C71: PROJETO DE SEGURANÇA.(conforme projeto e memoriais), incluindo fornecimento, instalação, mão-de-obra de todos os materiais, equipamentos, instrumentos, preparo da superfice onde será instalados os equipamentos, detalhados ou não nos projetos, memoriais e nesta planilha, mas necessários à perfeita execução, funcionamento e operação do sistema, dentro das Normas Técnicas vigentes e da segurança, que deverão ter seus custos incluídos nos itens apontados nesta planilha) - Placas retangulares fotoluminescentes sinalização de emergência saidas. Todas as placas de sinalização deverão ser do fabricante TOTAL LUX (MODELO PADRÃO SESC) Todos os equipamentos deverão ser fornecidos e instalados. | F71: =IF($E71="","",V71) | G71: =IF($E71="","",ROUND(W71+IF($B71=Precificação!$B$26,$F$3/$E71,0),2)) | H71: =IF($E71="","",F71+G71) | I71: =IF($E71="","",$E71*F71) | J71: =IF($E71="","",$E71*G71) | K71: =IF($E71="","",I71+J71) | L71: =IF($E71="","",IF(R71=0,"SEM CUSTO — falta linha de custo","OK")) | M71: =IF(AND(ISNUMBER(E71),NOT(ISNUMBER(E70))),"F"&ROW()&":G"&X71,"") | N71: =IF($E71="","",SUMIFS('Rateio Anexo'!$K$6:$K$600,'Rateio Anexo'!$D$6:$D$600,$B71,'Rateio Anexo'!$B$6:$B$600,"MAT")) | O71: =IF($E71="","",SUMIFS('Rateio Anexo'!$K$6:$K$600,'Rateio Anexo'!$D$6:$D$600,$B71,'Rateio Anexo'!$B$6:$B$600,"MO")) | P71: =IF($E71="","",IF($N$3=0,0,N71/$N$3*$R$4)) | Q71: =IF($E71="","",IF($O$3=0,0,O71/$O$3*$T$4)) | R71: =IF($E71="","",N71+O71+P71+Q71) | S71: =IF($E71="","",(N71+P71)*Precificação!$B$19) | T71: =IF($E71="","",(O71+Q71)*Precificação!$B$20) | U71: =IF($E71="","",IF($E71=INT($E71),0.01,IF($E71*2=INT($E71*2),0.02,0.05))) | V71: =IF($E71="","",ROUND(S71/$E71/U71,0)*U71) | W71: =IF($E71="","",ROUND(T71/$E71/U71,0)*U71) | X71: =IF(NOT(ISNUMBER(E71)),"",IF(NOT(ISNUMBER(E72)),ROW(),X72))
A72: 62 | B72: C.1 | C72: Sinalização de emergência | F72: =IF($E72="","",V72) | G72: =IF($E72="","",ROUND(W72+IF($B72=Precificação!$B$26,$F$3/$E72,0),2)) | H72: =IF($E72="","",F72+G72) | I72: =IF($E72="","",$E72*F72) | J72: =IF($E72="","",$E72*G72) | K72: =IF($E72="","",I72+J72) | L72: =IF($E72="","",IF(R72=0,"SEM CUSTO — falta linha de custo","OK")) | M72: =IF(AND(ISNUMBER(E72),NOT(ISNUMBER(E71))),"F"&ROW()&":G"&X72,"") | N72: =IF($E72="","",SUMIFS('Rateio Anexo'!$K$6:$K$600,'Rateio Anexo'!$D$6:$D$600,$B72,'Rateio Anexo'!$B$6:$B$600,"MAT")) | O72: =IF($E72="","",SUMIFS('Rateio Anexo'!$K$6:$K$600,'Rateio Anexo'!$D$6:$D$600,$B72,'Rateio Anexo'!$B$6:$B$600,"MO")) | P72: =IF($E72="","",IF($N$3=0,0,N72/$N$3*$R$4)) | Q72: =IF($E72="","",IF($O$3=0,0,O72/$O$3*$T$4)) | R72: =IF($E72="","",N72+O72+P72+Q72) | S72: =IF($E72="","",(N72+P72)*Precificação!$B$19) | T72: =IF($E72="","",(O72+Q72)*Precificação!$B$20) | U72: =IF($E72="","",IF($E72=INT($E72),0.01,IF($E72*2=INT($E72*2),0.02,0.05))) | V72: =IF($E72="","",ROUND(S72/$E72/U72,0)*U72) | W72: =IF($E72="","",ROUND(T72/$E72/U72,0)*U72) | X72: =IF(NOT(ISNUMBER(E72)),"",IF(NOT(ISNUMBER(E73)),ROW(),X73))
A73: 63 | B73: C.1.1 | C73: Placa retangular fotoluminescente rota saida a direita 15x30cm - cod. S1 | D73: pç | E73: 3 | F73: =IF($E73="","",V73) -> 43.05 | G73: =IF($E73="","",ROUND(W73+IF($B73=Precificação!$B$26,$F$3/$E73,0),2)) -> 0 | H73: =IF($E73="","",F73+G73) -> 43.05 | I73: =IF($E73="","",$E73*F73) -> 129.15 | J73: =IF($E73="","",$E73*G73) -> 0 | K73: =IF($E73="","",I73+J73) -> 129.15 | L73: =IF($E73="","",IF(R73=0,"SEM CUSTO — falta linha de custo","OK")) -> OK | M73: =IF(AND(ISNUMBER(E73),NOT(ISNUMBER(E72))),"F"&ROW()&":G"&X73,"") -> F73:G76 | N73: =IF($E73="","",SUMIFS('Rateio Anexo'!$K$6:$K$600,'Rateio Anexo'!$D$6:$D$600,$B73,'Rateio Anexo'!$B$6:$B$600,"MAT")) -> 67.5 | O73: =IF($E73="","",SUMIFS('Rateio Anexo'!$K$6:$K$600,'Rateio Anexo'!$D$6:$D$600,$B73,'Rateio Anexo'!$B$6:$B$600,"MO")) -> 0 | P73: =IF($E73="","",IF($N$3=0,0,N73/$N$3*$R$4)) -> 0.24151972 | Q73: =IF($E73="","",IF($O$3=0,0,O73/$O$3*$T$4)) -> 0 | R73: =IF($E73="","",N73+O73+P73+Q73) -> 67.74152 | S73: =IF($E73="","",(N73+P73)*Precificação!$B$19) -> 129.15805 | T73: =IF($E73="","",(O73+Q73)*Precificação!$B$20) -> 0 | U73: =IF($E73="","",IF($E73=INT($E73),0.01,IF($E73*2=INT($E73*2),0.02,0.05))) -> 0.01 | V73: =IF($E73="","",ROUND(S73/$E73/U73,0)*U73) -> 43.05 | W73: =IF($E73="","",ROUND(T73/$E73/U73,0)*U73) -> 0 | X73: =IF(NOT(ISNUMBER(E73)),"",IF(NOT(ISNUMBER(E74)),ROW(),X74)) -> 76
A74: 64 | B74: C.1.2 | C74: Placa retangular fotoluminescente rota saida a direita 15x30cm - cod. S2 | D74: pç | E74: 4 | F74: =IF($E74="","",V74) -> 43.05 | G74: =IF($E74="","",ROUND(W74+IF($B74=Precificação!$B$26,$F$3/$E74,0),2)) -> 0 | H74: =IF($E74="","",F74+G74) -> 43.05 | I74: =IF($E74="","",$E74*F74) -> 172.2 | J74: =IF($E74="","",$E74*G74) -> 0 | K74: =IF($E74="","",I74+J74) -> 172.2 | L74: =IF($E74="","",IF(R74=0,"SEM CUSTO — falta linha de custo","OK")) -> OK | M74: =IF(AND(ISNUMBER(E74),NOT(ISNUMBER(E73))),"F"&ROW()&":G"&X74,"") | N74: =IF($E74="","",SUMIFS('Rateio Anexo'!$K$6:$K$600,'Rateio Anexo'!$D$6:$D$600,$B74,'Rateio Anexo'!$B$6:$B$600,"MAT")) -> 90 | O74: =IF($E74="","",SUMIFS('Rateio Anexo'!$K$6:$K$600,'Rateio Anexo'!$D$6:$D$600,$B74,'Rateio Anexo'!$B$6:$B$600,"MO")) -> 0 | P74: =IF($E74="","",IF($N$3=0,0,N74/$N$3*$R$4)) -> 0.32202629 | Q74: =IF($E74="","",IF($O$3=0,0,O74/$O$3*$T$4)) -> 0 | R74: =IF($E74="","",N74+O74+P74+Q74) -> 90.322026 | S74: =IF($E74="","",(N74+P74)*Precificação!$B$19) -> 172.21073 | T74: =IF($E74="","",(O74+Q74)*Precificação!$B$20) -> 0 | U74: =IF($E74="","",IF($E74=INT($E74),0.01,IF($E74*2=INT($E74*2),0.02,0.05))) -> 0.01 | V74: =IF($E74="","",ROUND(S74/$E74/U74,0)*U74) -> 43.05 | W74: =IF($E74="","",ROUND(T74/$E74/U74,0)*U74) -> 0 | X74: =IF(NOT(ISNUMBER(E74)),"",IF(NOT(ISNUMBER(E75)),ROW(),X75)) -> 76
A75: 65 | B75: C.1.3 | C75: Placa retangular fotoluminescente rota saida a direita 15x30cm - cod. S3 | D75: pç | E75: 6 | F75: =IF($E75="","",V75) -> 43.05 | G75: =IF($E75="","",ROUND(W75+IF($B75=Precificação!$B$26,$F$3/$E75,0),2)) -> 0 | H75: =IF($E75="","",F75+G75) -> 43.05 | I75: =IF($E75="","",$E75*F75) -> 258.3 | J75: =IF($E75="","",$E75*G75) -> 0 | K75: =IF($E75="","",I75+J75) -> 258.3 | L75: =IF($E75="","",IF(R75=0,"SEM CUSTO — falta linha de custo","OK")) -> OK | M75: =IF(AND(ISNUMBER(E75),NOT(ISNUMBER(E74))),"F"&ROW()&":G"&X75,"") | N75: =IF($E75="","",SUMIFS('Rateio Anexo'!$K$6:$K$600,'Rateio Anexo'!$D$6:$D$600,$B75,'Rateio Anexo'!$B$6:$B$600,"MAT")) -> 135 | O75: =IF($E75="","",SUMIFS('Rateio Anexo'!$K$6:$K$600,'Rateio Anexo'!$D$6:$D$600,$B75,'Rateio Anexo'!$B$6:$B$600,"MO")) -> 0 | P75: =IF($E75="","",IF($N$3=0,0,N75/$N$3*$R$4)) -> 0.48303943 | Q75: =IF($E75="","",IF($O$3=0,0,O75/$O$3*$T$4)) -> 0 | R75: =IF($E75="","",N75+O75+P75+Q75) -> 135.48304 | S75: =IF($E75="","",(N75+P75)*Precificação!$B$19) -> 258.3161 | T75: =IF($E75="","",(O75+Q75)*Precificação!$B$20) -> 0 | U75: =IF($E75="","",IF($E75=INT($E75),0.01,IF($E75*2=INT($E75*2),0.02,0.05))) -> 0.01 | V75: =IF($E75="","",ROUND(S75/$E75/U75,0)*U75) -> 43.05 | W75: =IF($E75="","",ROUND(T75/$E75/U75,0)*U75) -> 0 | X75: =IF(NOT(ISNUMBER(E75)),"",IF(NOT(ISNUMBER(E76)),ROW(),X76)) -> 76
A76: 66 | B76: C.1.4 | C76: Placa de indicação de equipamentos - Indicação de localização de extintor de incêndio - cod. E5 | D76: pç | E76: 7 | F76: =IF($E76="","",V76) -> 43.05 | G76: =IF($E76="","",ROUND(W76+IF($B76=Precificação!$B$26,$F$3/$E76,0),2)) -> 0 | H76: =IF($E76="","",F76+G76) -> 43.05 | I76: =IF($E76="","",$E76*F76) -> 301.35 | J76: =IF($E76="","",$E76*G76) -> 0 | K76: =IF($E76="","",I76+J76) -> 301.35 | L76: =IF($E76="","",IF(R76=0,"SEM CUSTO — falta linha de custo","OK")) -> OK | M76: =IF(AND(ISNUMBER(E76),NOT(ISNUMBER(E75))),"F"&ROW()&":G"&X76,"") | N76: =IF($E76="","",SUMIFS('Rateio Anexo'!$K$6:$K$600,'Rateio Anexo'!$D$6:$D$600,$B76,'Rateio Anexo'!$B$6:$B$600,"MAT")) -> 157.5 | O76: =IF($E76="","",SUMIFS('Rateio Anexo'!$K$6:$K$600,'Rateio Anexo'!$D$6:$D$600,$B76,'Rateio Anexo'!$B$6:$B$600,"MO")) -> 0 | P76: =IF($E76="","",IF($N$3=0,0,N76/$N$3*$R$4)) -> 0.563546 | Q76: =IF($E76="","",IF($O$3=0,0,O76/$O$3*$T$4)) -> 0 | R76: =IF($E76="","",N76+O76+P76+Q76) -> 158.06355 | S76: =IF($E76="","",(N76+P76)*Precificação!$B$19) -> 301.36878 | T76: =IF($E76="","",(O76+Q76)*Precificação!$B$20) -> 0 | U76: =IF($E76="","",IF($E76=INT($E76),0.01,IF($E76*2=INT($E76*2),0.02,0.05))) -> 0.01 | V76: =IF($E76="","",ROUND(S76/$E76/U76,0)*U76) -> 43.05 | W76: =IF($E76="","",ROUND(T76/$E76/U76,0)*U76) -> 0 | X76: =IF(NOT(ISNUMBER(E76)),"",IF(NOT(ISNUMBER(E77)),ROW(),X77)) -> 76
A77: 67 | B77: C.2 | C77: Extintores de Incêndio fabricado em aço carbono, com pintura vermelha aplicada, interna e externamente, por processo eletrostático e rotulação por processo de serigrafia obedescendo as normas do Inmetro. | F77: =IF($E77="","",V77) | G77: =IF($E77="","",ROUND(W77+IF($B77=Precificação!$B$26,$F$3/$E77,0),2)) | H77: =IF($E77="","",F77+G77) | I77: =IF($E77="","",$E77*F77) | J77: =IF($E77="","",$E77*G77) | K77: =IF($E77="","",I77+J77) | L77: =IF($E77="","",IF(R77=0,"SEM CUSTO — falta linha de custo","OK")) | M77: =IF(AND(ISNUMBER(E77),NOT(ISNUMBER(E76))),"F"&ROW()&":G"&X77,"") | N77: =IF($E77="","",SUMIFS('Rateio Anexo'!$K$6:$K$600,'Rateio Anexo'!$D$6:$D$600,$B77,'Rateio Anexo'!$B$6:$B$600,"MAT")) | O77: =IF($E77="","",SUMIFS('Rateio Anexo'!$K$6:$K$600,'Rateio Anexo'!$D$6:$D$600,$B77,'Rateio Anexo'!$B$6:$B$600,"MO")) | P77: =IF($E77="","",IF($N$3=0,0,N77/$N$3*$R$4)) | Q77: =IF($E77="","",IF($O$3=0,0,O77/$O$3*$T$4)) | R77: =IF($E77="","",N77+O77+P77+Q77) | S77: =IF($E77="","",(N77+P77)*Precificação!$B$19) | T77: =IF($E77="","",(O77+Q77)*Precificação!$B$20) | U77: =IF($E77="","",IF($E77=INT($E77),0.01,IF($E77*2=INT($E77*2),0.02,0.05))) | V77: =IF($E77="","",ROUND(S77/$E77/U77,0)*U77) | W77: =IF($E77="","",ROUND(T77/$E77/U77,0)*U77) | X77: =IF(NOT(ISNUMBER(E77)),"",IF(NOT(ISNUMBER(E78)),ROW(),X78))
A78: 68 | B78: C.2.1 | C78: Extintor de pó ABC 4kg - Capacidade Extintora 2-A : 20-B : C | D78: pç | E78: 7 | F78: =IF($E78="","",V78) -> 139.82 | G78: =IF($E78="","",ROUND(W78+IF($B78=Precificação!$B$26,$F$3/$E78,0),2)) -> 0 | H78: =IF($E78="","",F78+G78) -> 139.82 | I78: =IF($E78="","",$E78*F78) -> 978.74 | J78: =IF($E78="","",$E78*G78) -> 0 | K78: =IF($E78="","",I78+J78) -> 978.74 | L78: =IF($E78="","",IF(R78=0,"SEM CUSTO — falta linha de custo","OK")) -> OK | M78: =IF(AND(ISNUMBER(E78),NOT(ISNUMBER(E77))),"F"&ROW()&":G"&X78,"") -> F78:G79 | N78: =IF($E78="","",SUMIFS('Rateio Anexo'!$K$6:$K$600,'Rateio Anexo'!$D$6:$D$600,$B78,'Rateio Anexo'!$B$6:$B$600,"MAT")) -> 511.498 | O78: =IF($E78="","",SUMIFS('Rateio Anexo'!$K$6:$K$600,'Rateio Anexo'!$D$6:$D$600,$B78,'Rateio Anexo'!$B$6:$B$600,"MO")) -> 0 | P78: =IF($E78="","",IF($N$3=0,0,N78/$N$3*$R$4)) -> 1.8301756 | Q78: =IF($E78="","",IF($O$3=0,0,O78/$O$3*$T$4)) -> 0 | R78: =IF($E78="","",N78+O78+P78+Q78) -> 513.32818 | S78: =IF($E78="","",(N78+P78)*Precificação!$B$19) -> 978.72718 | T78: =IF($E78="","",(O78+Q78)*Precificação!$B$20) -> 0 | U78: =IF($E78="","",IF($E78=INT($E78),0.01,IF($E78*2=INT($E78*2),0.02,0.05))) -> 0.01 | V78: =IF($E78="","",ROUND(S78/$E78/U78,0)*U78) -> 139.82 | W78: =IF($E78="","",ROUND(T78/$E78/U78,0)*U78) -> 0 | X78: =IF(NOT(ISNUMBER(E78)),"",IF(NOT(ISNUMBER(E79)),ROW(),X79)) -> 79
A79: 69 | B79: C.2.2 | C79: Suporte de Extintor Tripé Bicromatizado Com Haste de Sinalização - 4 a 6 Kg PQS - CS185 | D79: pç | E79: 7 | F79: =IF($E79="","",V79) -> 75.29 | G79: =IF($E79="","",ROUND(W79+IF($B79=Precificação!$B$26,$F$3/$E79,0),2)) -> 0 | H79: =IF($E79="","",F79+G79) -> 75.29 | I79: =IF($E79="","",$E79*F79) -> 527.03 | J79: =IF($E79="","",$E79*G79) -> 0 | K79: =IF($E79="","",I79+J79) -> 527.03 | L79: =IF($E79="","",IF(R79=0,"SEM CUSTO — falta linha de custo","OK")) -> OK | M79: =IF(AND(ISNUMBER(E79),NOT(ISNUMBER(E78))),"F"&ROW()&":G"&X79,"") | N79: =IF($E79="","",SUMIFS('Rateio Anexo'!$K$6:$K$600,'Rateio Anexo'!$D$6:$D$600,$B79,'Rateio Anexo'!$B$6:$B$600,"MAT")) -> 275.422 | O79: =IF($E79="","",SUMIFS('Rateio Anexo'!$K$6:$K$600,'Rateio Anexo'!$D$6:$D$600,$B79,'Rateio Anexo'!$B$6:$B$600,"MO")) -> 0 | P79: =IF($E79="","",IF($N$3=0,0,N79/$N$3*$R$4)) -> 0.98547915 | Q79: =IF($E79="","",IF($O$3=0,0,O79/$O$3*$T$4)) -> 0 | R79: =IF($E79="","",N79+O79+P79+Q79) -> 276.40748 | S79: =IF($E79="","",(N79+P79)*Precificação!$B$19) -> 527.00694 | T79: =IF($E79="","",(O79+Q79)*Precificação!$B$20) -> 0 | U79: =IF($E79="","",IF($E79=INT($E79),0.01,IF($E79*2=INT($E79*2),0.02,0.05))) -> 0.01 | V79: =IF($E79="","",ROUND(S79/$E79/U79,0)*U79) -> 75.29 | W79: =IF($E79="","",ROUND(T79/$E79/U79,0)*U79) -> 0 | X79: =IF(NOT(ISNUMBER(E79)),"",IF(NOT(ISNUMBER(E80)),ROW(),X80)) -> 79
A80: 70 | B80: C.3 | C80: Bloco autonomo de sobrepor para aclaramento e balizamento, com lâmpada fluorescente compacta, comutação automática, bateria selada e todos acessórios necessários para instalação. | F80: =IF($E80="","",V80) | G80: =IF($E80="","",ROUND(W80+IF($B80=Precificação!$B$26,$F$3/$E80,0),2)) | H80: =IF($E80="","",F80+G80) | I80: =IF($E80="","",$E80*F80) | J80: =IF($E80="","",$E80*G80) | K80: =IF($E80="","",I80+J80) | L80: =IF($E80="","",IF(R80=0,"SEM CUSTO — falta linha de custo","OK")) | M80: =IF(AND(ISNUMBER(E80),NOT(ISNUMBER(E79))),"F"&ROW()&":G"&X80,"") | N80: =IF($E80="","",SUMIFS('Rateio Anexo'!$K$6:$K$600,'Rateio Anexo'!$D$6:$D$600,$B80,'Rateio Anexo'!$B$6:$B$600,"MAT")) | O80: =IF($E80="","",SUMIFS('Rateio Anexo'!$K$6:$K$600,'Rateio Anexo'!$D$6:$D$600,$B80,'Rateio Anexo'!$B$6:$B$600,"MO")) | P80: =IF($E80="","",IF($N$3=0,0,N80/$N$3*$R$4)) | Q80: =IF($E80="","",IF($O$3=0,0,O80/$O$3*$T$4)) | R80: =IF($E80="","",N80+O80+P80+Q80) | S80: =IF($E80="","",(N80+P80)*Precificação!$B$19) | T80: =IF($E80="","",(O80+Q80)*Precificação!$B$20) | U80: =IF($E80="","",IF($E80=INT($E80),0.01,IF($E80*2=INT($E80*2),0.02,0.05))) | V80: =IF($E80="","",ROUND(S80/$E80/U80,0)*U80) | W80: =IF($E80="","",ROUND(T80/$E80/U80,0)*U80) | X80: =IF(NOT(ISNUMBER(E80)),"",IF(NOT(ISNUMBER(E81)),ROW(),X81))
A81: 71 | B81: C.3.1 | C81: Bloco autônomo aclaramento - LUMINÁRIA DE EMERGÊNCIA Led 60L LED 3W 127V/220V BRANCA | D81: pç | E81: 4 | F81: =IF($E81="","",V81) -> 172.21 | G81: =IF($E81="","",ROUND(W81+IF($B81=Precificação!$B$26,$F$3/$E81,0),2)) -> 0 | H81: =IF($E81="","",F81+G81) -> 172.21 | I81: =IF($E81="","",$E81*F81) -> 688.84 | J81: =IF($E81="","",$E81*G81) -> 0 | K81: =IF($E81="","",I81+J81) -> 688.84 | L81: =IF($E81="","",IF(R81=0,"SEM CUSTO — falta linha de custo","OK")) -> OK | M81: =IF(AND(ISNUMBER(E81),NOT(ISNUMBER(E80))),"F"&ROW()&":G"&X81,"") -> F81:G81 | N81: =IF($E81="","",SUMIFS('Rateio Anexo'!$K$6:$K$600,'Rateio Anexo'!$D$6:$D$600,$B81,'Rateio Anexo'!$B$6:$B$600,"MAT")) -> 360 | O81: =IF($E81="","",SUMIFS('Rateio Anexo'!$K$6:$K$600,'Rateio Anexo'!$D$6:$D$600,$B81,'Rateio Anexo'!$B$6:$B$600,"MO")) -> 0 | P81: =IF($E81="","",IF($N$3=0,0,N81/$N$3*$R$4)) -> 1.2881051 | Q81: =IF($E81="","",IF($O$3=0,0,O81/$O$3*$T$4)) -> 0 | R81: =IF($E81="","",N81+O81+P81+Q81) -> 361.28811 | S81: =IF($E81="","",(N81+P81)*Precificação!$B$19) -> 688.84294 | T81: =IF($E81="","",(O81+Q81)*Precificação!$B$20) -> 0 | U81: =IF($E81="","",IF($E81=INT($E81),0.01,IF($E81*2=INT($E81*2),0.02,0.05))) -> 0.01 | V81: =IF($E81="","",ROUND(S81/$E81/U81,0)*U81) -> 172.21 | W81: =IF($E81="","",ROUND(T81/$E81/U81,0)*U81) -> 0 | X81: =IF(NOT(ISNUMBER(E81)),"",IF(NOT(ISNUMBER(E82)),ROW(),X82)) -> 81
F82: =IF($E82="","",V82) | G82: =IF($E82="","",ROUND(W82+IF($B82=Precificação!$B$26,$F$3/$E82,0),2)) | H82: =IF($E82="","",F82+G82) | I82: =IF($E82="","",$E82*F82) | J82: =IF($E82="","",$E82*G82) | K82: =IF($E82="","",I82+J82) | L82: =IF($E82="","",IF(R82=0,"SEM CUSTO — falta linha de custo","OK")) | M82: =IF(AND(ISNUMBER(E82),NOT(ISNUMBER(E81))),"F"&ROW()&":G"&X82,"") | N82: =IF($E82="","",SUMIFS('Rateio Anexo'!$K$6:$K$600,'Rateio Anexo'!$D$6:$D$600,$B82,'Rateio Anexo'!$B$6:$B$600,"MAT")) | O82: =IF($E82="","",SUMIFS('Rateio Anexo'!$K$6:$K$600,'Rateio Anexo'!$D$6:$D$600,$B82,'Rateio Anexo'!$B$6:$B$600,"MO")) | P82: =IF($E82="","",IF($N$3=0,0,N82/$N$3*$R$4)) | Q82: =IF($E82="","",IF($O$3=0,0,O82/$O$3*$T$4)) | R82: =IF($E82="","",N82+O82+P82+Q82) | S82: =IF($E82="","",(N82+P82)*Precificação!$B$19) | T82: =IF($E82="","",(O82+Q82)*Precificação!$B$20) | U82: =IF($E82="","",IF($E82=INT($E82),0.01,IF($E82*2=INT($E82*2),0.02,0.05))) | V82: =IF($E82="","",ROUND(S82/$E82/U82,0)*U82) | W82: =IF($E82="","",ROUND(T82/$E82/U82,0)*U82) | X82: =IF(NOT(ISNUMBER(E82)),"",IF(NOT(ISNUMBER(E83)),ROW(),X83))
F83: =IF($E83="","",V83) | G83: =IF($E83="","",ROUND(W83+IF($B83=Precificação!$B$26,$F$3/$E83,0),2)) | H83: =IF($E83="","",F83+G83) | I83: =IF($E83="","",$E83*F83) | J83: =IF($E83="","",$E83*G83) | K83: =IF($E83="","",I83+J83) | L83: =IF($E83="","",IF(R83=0,"SEM CUSTO — falta linha de custo","OK")) | M83: =IF(AND(ISNUMBER(E83),NOT(ISNUMBER(E82))),"F"&ROW()&":G"&X83,"") | N83: =IF($E83="","",SUMIFS('Rateio Anexo'!$K$6:$K$600,'Rateio Anexo'!$D$6:$D$600,$B83,'Rateio Anexo'!$B$6:$B$600,"MAT")) | O83: =IF($E83="","",SUMIFS('Rateio Anexo'!$K$6:$K$600,'Rateio Anexo'!$D$6:$D$600,$B83,'Rateio Anexo'!$B$6:$B$600,"MO")) | P83: =IF($E83="","",IF($N$3=0,0,N83/$N$3*$R$4)) | Q83: =IF($E83="","",IF($O$3=0,0,O83/$O$3*$T$4)) | R83: =IF($E83="","",N83+O83+P83+Q83) | S83: =IF($E83="","",(N83+P83)*Precificação!$B$19) | T83: =IF($E83="","",(O83+Q83)*Precificação!$B$20) | U83: =IF($E83="","",IF($E83=INT($E83),0.01,IF($E83*2=INT($E83*2),0.02,0.05))) | V83: =IF($E83="","",ROUND(S83/$E83/U83,0)*U83) | W83: =IF($E83="","",ROUND(T83/$E83/U83,0)*U83) | X83: =IF(NOT(ISNUMBER(E83)),"",IF(NOT(ISNUMBER(E84)),ROW(),X84))
F84: =IF($E84="","",V84) | G84: =IF($E84="","",ROUND(W84+IF($B84=Precificação!$B$26,$F$3/$E84,0),2)) | H84: =IF($E84="","",F84+G84) | I84: =IF($E84="","",$E84*F84) | J84: =IF($E84="","",$E84*G84) | K84: =IF($E84="","",I84+J84) | L84: =IF($E84="","",IF(R84=0,"SEM CUSTO — falta linha de custo","OK")) | M84: =IF(AND(ISNUMBER(E84),NOT(ISNUMBER(E83))),"F"&ROW()&":G"&X84,"") | N84: =IF($E84="","",SUMIFS('Rateio Anexo'!$K$6:$K$600,'Rateio Anexo'!$D$6:$D$600,$B84,'Rateio Anexo'!$B$6:$B$600,"MAT")) | O84: =IF($E84="","",SUMIFS('Rateio Anexo'!$K$6:$K$600,'Rateio Anexo'!$D$6:$D$600,$B84,'Rateio Anexo'!$B$6:$B$600,"MO")) | P84: =IF($E84="","",IF($N$3=0,0,N84/$N$3*$R$4)) | Q84: =IF($E84="","",IF($O$3=0,0,O84/$O$3*$T$4)) | R84: =IF($E84="","",N84+O84+P84+Q84) | S84: =IF($E84="","",(N84+P84)*Precificação!$B$19) | T84: =IF($E84="","",(O84+Q84)*Precificação!$B$20) | U84: =IF($E84="","",IF($E84=INT($E84),0.01,IF($E84*2=INT($E84*2),0.02,0.05))) | V84: =IF($E84="","",ROUND(S84/$E84/U84,0)*U84) | W84: =IF($E84="","",ROUND(T84/$E84/U84,0)*U84) | X84: =IF(NOT(ISNUMBER(E84)),"",IF(NOT(ISNUMBER(E85)),ROW(),X85))
F85: =IF($E85="","",V85) | G85: =IF($E85="","",ROUND(W85+IF($B85=Precificação!$B$26,$F$3/$E85,0),2)) | H85: =IF($E85="","",F85+G85) | I85: =IF($E85="","",$E85*F85) | J85: =IF($E85="","",$E85*G85) | K85: =IF($E85="","",I85+J85) | L85: =IF($E85="","",IF(R85=0,"SEM CUSTO — falta linha de custo","OK")) | M85: =IF(AND(ISNUMBER(E85),NOT(ISNUMBER(E84))),"F"&ROW()&":G"&X85,"") | N85: =IF($E85="","",SUMIFS('Rateio Anexo'!$K$6:$K$600,'Rateio Anexo'!$D$6:$D$600,$B85,'Rateio Anexo'!$B$6:$B$600,"MAT")) | O85: =IF($E85="","",SUMIFS('Rateio Anexo'!$K$6:$K$600,'Rateio Anexo'!$D$6:$D$600,$B85,'Rateio Anexo'!$B$6:$B$600,"MO")) | P85: =IF($E85="","",IF($N$3=0,0,N85/$N$3*$R$4)) | Q85: =IF($E85="","",IF($O$3=0,0,O85/$O$3*$T$4)) | R85: =IF($E85="","",N85+O85+P85+Q85) | S85: =IF($E85="","",(N85+P85)*Precificação!$B$19) | T85: =IF($E85="","",(O85+Q85)*Precificação!$B$20) | U85: =IF($E85="","",IF($E85=INT($E85),0.01,IF($E85*2=INT($E85*2),0.02,0.05))) | V85: =IF($E85="","",ROUND(S85/$E85/U85,0)*U85) | W85: =IF($E85="","",ROUND(T85/$E85/U85,0)*U85) | X85: =IF(NOT(ISNUMBER(E85)),"",IF(NOT(ISNUMBER(E86)),ROW(),X86))
F86: =IF($E86="","",V86) | G86: =IF($E86="","",ROUND(W86+IF($B86=Precificação!$B$26,$F$3/$E86,0),2)) | H86: =IF($E86="","",F86+G86) | I86: =IF($E86="","",$E86*F86) | J86: =IF($E86="","",$E86*G86) | K86: =IF($E86="","",I86+J86) | L86: =IF($E86="","",IF(R86=0,"SEM CUSTO — falta linha de custo","OK")) | M86: =IF(AND(ISNUMBER(E86),NOT(ISNUMBER(E85))),"F"&ROW()&":G"&X86,"") | N86: =IF($E86="","",SUMIFS('Rateio Anexo'!$K$6:$K$600,'Rateio Anexo'!$D$6:$D$600,$B86,'Rateio Anexo'!$B$6:$B$600,"MAT")) | O86: =IF($E86="","",SUMIFS('Rateio Anexo'!$K$6:$K$600,'Rateio Anexo'!$D$6:$D$600,$B86,'Rateio Anexo'!$B$6:$B$600,"MO")) | P86: =IF($E86="","",IF($N$3=0,0,N86/$N$3*$R$4)) | Q86: =IF($E86="","",IF($O$3=0,0,O86/$O$3*$T$4)) | R86: =IF($E86="","",N86+O86+P86+Q86) | S86: =IF($E86="","",(N86+P86)*Precificação!$B$19) | T86: =IF($E86="","",(O86+Q86)*Precificação!$B$20) | U86: =IF($E86="","",IF($E86=INT($E86),0.01,IF($E86*2=INT($E86*2),0.02,0.05))) | V86: =IF($E86="","",ROUND(S86/$E86/U86,0)*U86) | W86: =IF($E86="","",ROUND(T86/$E86/U86,0)*U86) | X86: =IF(NOT(ISNUMBER(E86)),"",IF(NOT(ISNUMBER(E87)),ROW(),X87))
F87: =IF($E87="","",V87) | G87: =IF($E87="","",ROUND(W87+IF($B87=Precificação!$B$26,$F$3/$E87,0),2)) | H87: =IF($E87="","",F87+G87) | I87: =IF($E87="","",$E87*F87) | J87: =IF($E87="","",$E87*G87) | K87: =IF($E87="","",I87+J87) | L87: =IF($E87="","",IF(R87=0,"SEM CUSTO — falta linha de custo","OK")) | M87: =IF(AND(ISNUMBER(E87),NOT(ISNUMBER(E86))),"F"&ROW()&":G"&X87,"") | N87: =IF($E87="","",SUMIFS('Rateio Anexo'!$K$6:$K$600,'Rateio Anexo'!$D$6:$D$600,$B87,'Rateio Anexo'!$B$6:$B$600,"MAT")) | O87: =IF($E87="","",SUMIFS('Rateio Anexo'!$K$6:$K$600,'Rateio Anexo'!$D$6:$D$600,$B87,'Rateio Anexo'!$B$6:$B$600,"MO")) | P87: =IF($E87="","",IF($N$3=0,0,N87/$N$3*$R$4)) | Q87: =IF($E87="","",IF($O$3=0,0,O87/$O$3*$T$4)) | R87: =IF($E87="","",N87+O87+P87+Q87) | S87: =IF($E87="","",(N87+P87)*Precificação!$B$19) | T87: =IF($E87="","",(O87+Q87)*Precificação!$B$20) | U87: =IF($E87="","",IF($E87=INT($E87),0.01,IF($E87*2=INT($E87*2),0.02,0.05))) | V87: =IF($E87="","",ROUND(S87/$E87/U87,0)*U87) | W87: =IF($E87="","",ROUND(T87/$E87/U87,0)*U87) | X87: =IF(NOT(ISNUMBER(E87)),"",IF(NOT(ISNUMBER(E88)),ROW(),X88))
F88: =IF($E88="","",V88) | G88: =IF($E88="","",ROUND(W88+IF($B88=Precificação!$B$26,$F$3/$E88,0),2)) | H88: =IF($E88="","",F88+G88) | I88: =IF($E88="","",$E88*F88) | J88: =IF($E88="","",$E88*G88) | K88: =IF($E88="","",I88+J88) | L88: =IF($E88="","",IF(R88=0,"SEM CUSTO — falta linha de custo","OK")) | M88: =IF(AND(ISNUMBER(E88),NOT(ISNUMBER(E87))),"F"&ROW()&":G"&X88,"") | N88: =IF($E88="","",SUMIFS('Rateio Anexo'!$K$6:$K$600,'Rateio Anexo'!$D$6:$D$600,$B88,'Rateio Anexo'!$B$6:$B$600,"MAT")) | O88: =IF($E88="","",SUMIFS('Rateio Anexo'!$K$6:$K$600,'Rateio Anexo'!$D$6:$D$600,$B88,'Rateio Anexo'!$B$6:$B$600,"MO")) | P88: =IF($E88="","",IF($N$3=0,0,N88/$N$3*$R$4)) | Q88: =IF($E88="","",IF($O$3=0,0,O88/$O$3*$T$4)) | R88: =IF($E88="","",N88+O88+P88+Q88) | S88: =IF($E88="","",(N88+P88)*Precificação!$B$19) | T88: =IF($E88="","",(O88+Q88)*Precificação!$B$20) | U88: =IF($E88="","",IF($E88=INT($E88),0.01,IF($E88*2=INT($E88*2),0.02,0.05))) | V88: =IF($E88="","",ROUND(S88/$E88/U88,0)*U88) | W88: =IF($E88="","",ROUND(T88/$E88/U88,0)*U88) | X88: =IF(NOT(ISNUMBER(E88)),"",IF(NOT(ISNUMBER(E89)),ROW(),X89))
F89: =IF($E89="","",V89) | G89: =IF($E89="","",ROUND(W89+IF($B89=Precificação!$B$26,$F$3/$E89,0),2)) | H89: =IF($E89="","",F89+G89) | I89: =IF($E89="","",$E89*F89) | J89: =IF($E89="","",$E89*G89) | K89: =IF($E89="","",I89+J89) | L89: =IF($E89="","",IF(R89=0,"SEM CUSTO — falta linha de custo","OK")) | M89: =IF(AND(ISNUMBER(E89),NOT(ISNUMBER(E88))),"F"&ROW()&":G"&X89,"") | N89: =IF($E89="","",SUMIFS('Rateio Anexo'!$K$6:$K$600,'Rateio Anexo'!$D$6:$D$600,$B89,'Rateio Anexo'!$B$6:$B$600,"MAT")) | O89: =IF($E89="","",SUMIFS('Rateio Anexo'!$K$6:$K$600,'Rateio Anexo'!$D$6:$D$600,$B89,'Rateio Anexo'!$B$6:$B$600,"MO")) | P89: =IF($E89="","",IF($N$3=0,0,N89/$N$3*$R$4)) | Q89: =IF($E89="","",IF($O$3=0,0,O89/$O$3*$T$4)) | R89: =IF($E89="","",N89+O89+P89+Q89) | S89: =IF($E89="","",(N89+P89)*Precificação!$B$19) | T89: =IF($E89="","",(O89+Q89)*Precificação!$B$20) | U89: =IF($E89="","",IF($E89=INT($E89),0.01,IF($E89*2=INT($E89*2),0.02,0.05))) | V89: =IF($E89="","",ROUND(S89/$E89/U89,0)*U89) | W89: =IF($E89="","",ROUND(T89/$E89/U89,0)*U89) | X89: =IF(NOT(ISNUMBER(E89)),"",IF(NOT(ISNUMBER(E90)),ROW(),X90))
F90: =IF($E90="","",V90) | G90: =IF($E90="","",ROUND(W90+IF($B90=Precificação!$B$26,$F$3/$E90,0),2)) | H90: =IF($E90="","",F90+G90) | I90: =IF($E90="","",$E90*F90) | J90: =IF($E90="","",$E90*G90) | K90: =IF($E90="","",I90+J90) | L90: =IF($E90="","",IF(R90=0,"SEM CUSTO — falta linha de custo","OK")) | M90: =IF(AND(ISNUMBER(E90),NOT(ISNUMBER(E89))),"F"&ROW()&":G"&X90,"") | N90: =IF($E90="","",SUMIFS('Rateio Anexo'!$K$6:$K$600,'Rateio Anexo'!$D$6:$D$600,$B90,'Rateio Anexo'!$B$6:$B$600,"MAT")) | O90: =IF($E90="","",SUMIFS('Rateio Anexo'!$K$6:$K$600,'Rateio Anexo'!$D$6:$D$600,$B90,'Rateio Anexo'!$B$6:$B$600,"MO")) | P90: =IF($E90="","",IF($N$3=0,0,N90/$N$3*$R$4)) | Q90: =IF($E90="","",IF($O$3=0,0,O90/$O$3*$T$4)) | R90: =IF($E90="","",N90+O90+P90+Q90) | S90: =IF($E90="","",(N90+P90)*Precificação!$B$19) | T90: =IF($E90="","",(O90+Q90)*Precificação!$B$20) | U90: =IF($E90="","",IF($E90=INT($E90),0.01,IF($E90*2=INT($E90*2),0.02,0.05))) | V90: =IF($E90="","",ROUND(S90/$E90/U90,0)*U90) | W90: =IF($E90="","",ROUND(T90/$E90/U90,0)*U90) | X90: =IF(NOT(ISNUMBER(E90)),"",IF(NOT(ISNUMBER(E91)),ROW(),X91))
F91: =IF($E91="","",V91) | G91: =IF($E91="","",ROUND(W91+IF($B91=Precificação!$B$26,$F$3/$E91,0),2)) | H91: =IF($E91="","",F91+G91) | I91: =IF($E91="","",$E91*F91) | J91: =IF($E91="","",$E91*G91) | K91: =IF($E91="","",I91+J91) | L91: =IF($E91="","",IF(R91=0,"SEM CUSTO — falta linha de custo","OK")) | M91: =IF(AND(ISNUMBER(E91),NOT(ISNUMBER(E90))),"F"&ROW()&":G"&X91,"") | N91: =IF($E91="","",SUMIFS('Rateio Anexo'!$K$6:$K$600,'Rateio Anexo'!$D$6:$D$600,$B91,'Rateio Anexo'!$B$6:$B$600,"MAT")) | O91: =IF($E91="","",SUMIFS('Rateio Anexo'!$K$6:$K$600,'Rateio Anexo'!$D$6:$D$600,$B91,'Rateio Anexo'!$B$6:$B$600,"MO")) | P91: =IF($E91="","",IF($N$3=0,0,N91/$N$3*$R$4)) | Q91: =IF($E91="","",IF($O$3=0,0,O91/$O$3*$T$4)) | R91: =IF($E91="","",N91+O91+P91+Q91) | S91: =IF($E91="","",(N91+P91)*Precificação!$B$19) | T91: =IF($E91="","",(O91+Q91)*Precificação!$B$20) | U91: =IF($E91="","",IF($E91=INT($E91),0.01,IF($E91*2=INT($E91*2),0.02,0.05))) | V91: =IF($E91="","",ROUND(S91/$E91/U91,0)*U91) | W91: =IF($E91="","",ROUND(T91/$E91/U91,0)*U91) | X91: =IF(NOT(ISNUMBER(E91)),"",IF(NOT(ISNUMBER(E92)),ROW(),X92))
F92: =IF($E92="","",V92) | G92: =IF($E92="","",ROUND(W92+IF($B92=Precificação!$B$26,$F$3/$E92,0),2)) | H92: =IF($E92="","",F92+G92) | I92: =IF($E92="","",$E92*F92) | J92: =IF($E92="","",$E92*G92) | K92: =IF($E92="","",I92+J92) | L92: =IF($E92="","",IF(R92=0,"SEM CUSTO — falta linha de custo","OK")) | M92: =IF(AND(ISNUMBER(E92),NOT(ISNUMBER(E91))),"F"&ROW()&":G"&X92,"") | N92: =IF($E92="","",SUMIFS('Rateio Anexo'!$K$6:$K$600,'Rateio Anexo'!$D$6:$D$600,$B92,'Rateio Anexo'!$B$6:$B$600,"MAT")) | O92: =IF($E92="","",SUMIFS('Rateio Anexo'!$K$6:$K$600,'Rateio Anexo'!$D$6:$D$600,$B92,'Rateio Anexo'!$B$6:$B$600,"MO")) | P92: =IF($E92="","",IF($N$3=0,0,N92/$N$3*$R$4)) | Q92: =IF($E92="","",IF($O$3=0,0,O92/$O$3*$T$4)) | R92: =IF($E92="","",N92+O92+P92+Q92) | S92: =IF($E92="","",(N92+P92)*Precificação!$B$19) | T92: =IF($E92="","",(O92+Q92)*Precificação!$B$20) | U92: =IF($E92="","",IF($E92=INT($E92),0.01,IF($E92*2=INT($E92*2),0.02,0.05))) | V92: =IF($E92="","",ROUND(S92/$E92/U92,0)*U92) | W92: =IF($E92="","",ROUND(T92/$E92/U92,0)*U92) | X92: =IF(NOT(ISNUMBER(E92)),"",IF(NOT(ISNUMBER(E93)),ROW(),X93))
F93: =IF($E93="","",V93) | G93: =IF($E93="","",ROUND(W93+IF($B93=Precificação!$B$26,$F$3/$E93,0),2)) | H93: =IF($E93="","",F93+G93) | I93: =IF($E93="","",$E93*F93) | J93: =IF($E93="","",$E93*G93) | K93: =IF($E93="","",I93+J93) | L93: =IF($E93="","",IF(R93=0,"SEM CUSTO — falta linha de custo","OK")) | M93: =IF(AND(ISNUMBER(E93),NOT(ISNUMBER(E92))),"F"&ROW()&":G"&X93,"") | N93: =IF($E93="","",SUMIFS('Rateio Anexo'!$K$6:$K$600,'Rateio Anexo'!$D$6:$D$600,$B93,'Rateio Anexo'!$B$6:$B$600,"MAT")) | O93: =IF($E93="","",SUMIFS('Rateio Anexo'!$K$6:$K$600,'Rateio Anexo'!$D$6:$D$600,$B93,'Rateio Anexo'!$B$6:$B$600,"MO")) | P93: =IF($E93="","",IF($N$3=0,0,N93/$N$3*$R$4)) | Q93: =IF($E93="","",IF($O$3=0,0,O93/$O$3*$T$4)) | R93: =IF($E93="","",N93+O93+P93+Q93) | S93: =IF($E93="","",(N93+P93)*Precificação!$B$19) | T93: =IF($E93="","",(O93+Q93)*Precificação!$B$20) | U93: =IF($E93="","",IF($E93=INT($E93),0.01,IF($E93*2=INT($E93*2),0.02,0.05))) | V93: =IF($E93="","",ROUND(S93/$E93/U93,0)*U93) | W93: =IF($E93="","",ROUND(T93/$E93/U93,0)*U93) | X93: =IF(NOT(ISNUMBER(E93)),"",IF(NOT(ISNUMBER(E94)),ROW(),X94))
... F400: =IF($E400="","",V400) | G400: =IF($E400="","",ROUND(W400+IF($B400=Precificação!$B$26,$F$3/$E400,0),2)) | H400: =IF($E400="","",F400+G400) | I400: =IF($E400="","",$E400*F400) | J400: =IF($E400="","",$E400*G400) | K400: =IF($E400="","",I400+J400) | L400: =IF($E400="","",IF(R400=0,"SEM CUSTO — falta linha de custo","OK")) | M400: =IF(AND(ISNUMBER(E400),NOT(ISNUMBER(E399))),"F"&ROW()&":G"&X400,"") | N400: =IF($E400="","",SUMIFS('Rateio Anexo'!$K$6:$K$600,'Rateio Anexo'!$D$6:$D$600,$B400,'Rateio Anexo'!$B$6:$B$600,"MAT")) | O400: =IF($E400="","",SUMIFS('Rateio Anexo'!$K$6:$K$600,'Rateio Anexo'!$D$6:$D$600,$B400,'Rateio Anexo'!$B$6:$B$600,"MO")) | P400: =IF($E400="","",IF($N$3=0,0,N400/$N$3*$R$4)) | Q400: =IF($E400="","",IF($O$3=0,0,O400/$O$3*$T$4)) | R400: =IF($E400="","",N400+O400+P400+Q400) | S400: =IF($E400="","",(N400+P400)*Precificação!$B$19) | T400: =IF($E400="","",(O400+Q400)*Precificação!$B$20) | U400: =IF($E400="","",IF($E400=INT($E400),0.01,IF($E400*2=INT($E400*2),0.02,0.05))) | V400: =IF($E400="","",ROUND(S400/$E400/U400,0)*U400) | W400: =IF($E400="","",ROUND(T400/$E400/U400,0)*U400) | X400: =IF(NOT(ISNUMBER(E400)),"",IF(NOT(ISNUMBER(E401)),ROW(),X401))

Sheet Resumo por Disciplina
A1: RESUMO DE CUSTOS POR DISCIPLINA — SESC PAULISTA (v12.0)
A3: Item | B3: Disciplina | C3: Qtd. Itens Mapeados | D3: Valor Total Cotado (R$) | E3: % do Total Geral
A4: 01 | B4: Marcenaria e Cenotecnia | C4: =COUNTIF('Cotação de Materiais'!B4:B44, B4) -> 4 | D4: =SUMIF('Cotação de Materiais'!B4:B44, B4, 'Cotação de Materiais'!H4:H44) -> 21347.26 | E4: =D4/$D$13 -> 0.27182022
A5: 02 | B5: Serralheria e Estruturas Metálicas | C5: =COUNTIF('Cotação de Materiais'!B4:B44, B5) -> 6 | D5: =SUMIF('Cotação de Materiais'!B4:B44, B5, 'Cotação de Materiais'!H4:H44) -> 6546.25 | E5: =D5/$D$13 -> 0.083355106
A6: 03 | B6: Elétrica e Iluminação | C6: =COUNTIF('Cotação de Materiais'!B4:B44, B6) -> 8 | D6: =SUMIF('Cotação de Materiais'!B4:B44, B6, 'Cotação de Materiais'!H4:H44) -> 9176.262 | E6: =D6/$D$13 -> 0.11684373
A7: 04 | B7: Pintura e Acabamentos | C7: =COUNTIF('Cotação de Materiais'!B4:B44, B7) -> 3 | D7: =SUMIF('Cotação de Materiais'!B4:B44, B7, 'Cotação de Materiais'!H4:H44) -> 6741.02 | E7: =D7/$D$13 -> 0.085835163
A8: 05 | B8: Vidros e Acrílicos | C8: =COUNTIF('Cotação de Materiais'!B4:B44, B8) -> 1 | D8: =SUMIF('Cotação de Materiais'!B4:B44, B8, 'Cotação de Materiais'!H4:H44) -> 1376.71 | E8: =D8/$D$13 -> 0.017530007
A9: 06 | B9: Comunicação Visual | C9: =COUNTIF('Cotação de Materiais'!B4:B44, B9) -> 3 | D9: =SUMIF('Cotação de Materiais'!B4:B44, B9, 'Cotação de Materiais'!H4:H44) -> 13681.459 | E9: =D9/$D$13 -> 0.17420958
A10: 07 | B10: Segurança Contra Incêndio | C10: =COUNTIF('Cotação de Materiais'!B4:B44, B10) -> 5 | D10: =SUMIF('Cotação de Materiais'!B4:B44, B10, 'Cotação de Materiais'!H4:H44) -> 10636.92 | E10: =D10/$D$13 -> 0.13544267
A11: 08 | B11: Ferragens e Ancoragens | C11: =COUNTIF('Cotação de Materiais'!B4:B44, B11) -> 4 | D11: =SUMIF('Cotação de Materiais'!B4:B44, B11, 'Cotação de Materiais'!H4:H44) -> 7048.6 | E11: =D11/$D$13 -> 0.089751659
A12: 09 | B12: Elementos Reformados | C12: =COUNTIF('Cotação de Materiais'!B4:B44, B12) -> 5 | D12: =SUMIF('Cotação de Materiais'!B4:B44, B12, 'Cotação de Materiais'!H4:H44) -> 1980 | E12: =D12/$D$13 -> 0.025211856
A13: TOTAL | B13: TODAS AS DISCIPLINAS | C13: =SUM(C4:C12) -> 39 | D13: =SUM(D4:D12) -> 78534.481 | E13: =SUM(E4:E12) -> 1

Sheet Dashboard Executivo
A1: PAINEL EXECUTIVO — SESC PAULISTA | COSMOCHÃO
R2: Disciplina | S2: Valor | U2: Componente | V2: Valor
A3: Base v12.0 | Fabricação em galpão: 5 dias úteis | Montagem SESC: 28/10 a 16/11 | Reserva técnica: 17/11 | Abertura: 18/11/2026 | R3: Marcenaria e Cenotecnia | S3: ='Resumo por Disciplina'!D4 -> 21347.26 | U3: Materiais e Insumos | V3: ='Cotação de Materiais'!H45 -> 78534.481
R4: Serralheria e Estruturas Metálicas | S4: ='Resumo por Disciplina'!D5 -> 6546.25 | U4: M.O. + Serviços + Logística | V4: ='Mão de Obra e Serviços'!G21 -> 118562
A5: CUSTO TOTAL GERAL | F5: MATERIAIS E INSUMOS | J5: M.O. + SERVIÇOS + LOGÍSTICA | N5: ITENS PENDENTES DE DEFINIÇÃO | R5: Elétrica e Iluminação | S5: ='Resumo por Disciplina'!D6 -> 9176.262
R6: Pintura e Acabamentos | S6: ='Resumo por Disciplina'!D7 -> 6741.02
A7: ="R$ "&TEXT('Instruções e Resumo'!B16,"#,##0.00") -> R$ 197,096.48 | F7: ="R$ "&TEXT('Cotação de Materiais'!H45,"#,##0.00") -> R$ 78,534.48 | J7: ="R$ "&TEXT('Mão de Obra e Serviços'!G21,"#,##0.00") -> R$ 118,562.00 | N7: =COUNTIF('Cotação de Materiais'!I4:I44,"PENDENTE")+COUNTIF('Mão de Obra e Serviços'!H4:H20,"PENDENTE") -> 6 | R7: Vidros e Acrílicos | S7: ='Resumo por Disciplina'!D8 -> 1376.71
R8: Comunicação Visual | S8: ='Resumo por Disciplina'!D9 -> 13681.459
R9: Segurança Contra Incêndio | S9: ='Resumo por Disciplina'!D10 -> 10636.92
A10: GALPÃO — EQUIPE | F10: GALPÃO — DURAÇÃO | J10: SESC — EQUIPE PRINCIPAL | N10: MARGEM DE SEGURANÇA | R10: Ferragens e Ancoragens | S10: ='Resumo por Disciplina'!D11 -> 7048.6
R11: Elementos Reformados | S11: ='Resumo por Disciplina'!D12 -> 1980
A12: =4 -> 4 | F12: =5 -> 5 | J12: =8 -> 8 | N12: =1 -> 1
A15: CUSTOS POR DISCIPLINA | J15: COMPOSIÇÃO DO CUSTO
A34: CRONOGRAMA EXECUTIVO — VISÃO GERAL
A35: Fase | D35: Período | F35: Equipe | I35: Objetivo
A36: Pré-fabricação no galpão | D36: 21–27/10 | F36: 4 marceneiros | I36: 5 dias úteis de fabricação; preparação e ignifugação antes da entrada no SESC.
A37: Entrada + implantação pesada | D37: 28–30/10 | F37: 8 marc. + 4 ajud. (28–29) | I37: Descarga, distribuição, locação e início das estruturas/painéis.
A38: Montagem pesada | D38: 31/10–05/11 | F38: 8 marc. + serralheria | I38: Painéis, estruturas principais, P05, PR01/PR02 e fechamentos.
A39: Montagem técnica / especiais | D39: 06–10/11 | F39: 8 marc. + elétrica/serralheria | I39: M22, M27, bases especiais, ancoragens e fechamentos técnicos.
A40: Mobiliário + elétrica + CV | D40: 11–13/11 | F40: 8 marc. + eletricista + 2 adesiv. | I40: Mobiliário, acessibilidade, LED, eletrofita, insulfilm e vinil.
A41: Acabamentos e correções | D41: 14–16/11 | F41: 8 marc. + pintura + limpeza | I41: Retoques, testes, alinhamentos e limpeza progressiva.
A42: Reserva / entrega técnica | D42: 17/11 | F42: Equipe mínima + limpeza | I42: Punch list, correções finais e liberação.
A43: Abertura da exposição | D43: 18/11 | F43: — | I43: Abertura ao público.
A45: MATERIAIS DE MAIOR IMPACTO — BASE ATUAL | J45: STATUS DA COTAÇÃO / PENDÊNCIAS
A46: Item | B46: Material | E46: Disciplina | G46: Custo Total | J46: Status | M46: Quantidade
A47: ='Cotação de Materiais'!A31 -> SEG-01 | B47: ='Cotação de Materiais'!C31 -> Retardante de Chamas CKC-2020 | E47: ='Cotação de Materiais'!B31 -> Segurança Contra Incêndio | G47: ="R$ "&TEXT('Cotação de Materiais'!H31,"#,##0.00") -> R$ 8,760.00 | J47: PENDENTE | M47: =COUNTIF('Cotação de Materiais'!I4:I44,"PENDENTE")+COUNTIF('Mão de Obra e Serviços'!H4:H20,"PENDENTE") -> 6
A48: ='Cotação de Materiais'!A4 -> MAT-01 | B48: ='Cotação de Materiais'!C4 -> Chapas de MDF Comum 18mm | E48: ='Cotação de Materiais'!B4 -> Marcenaria e Cenotecnia | G48: ="R$ "&TEXT('Cotação de Materiais'!H4,"#,##0.00") -> R$ 15,607.36 | J48: FECHADO | M48: =COUNTIF('Cotação de Materiais'!I4:I44,"FECHADO")+COUNTIF('Mão de Obra e Serviços'!H4:H20,"FECHADO") -> 6
A49: ='Cotação de Materiais'!A25 -> VID-01 | B49: ='Cotação de Materiais'!C25 -> Vidro Laminado M01 | E49: ='Cotação de Materiais'!B25 -> Vidros e Acrílicos | G49: ="R$ "&TEXT('Cotação de Materiais'!H25,"#,##0.00") -> R$ 1,376.71 | J49: EXPLÍCITO | M49: =COUNTIF('Cotação de Materiais'!I4:I44,"EXPLÍCITO")+COUNTIF('Mão de Obra e Serviços'!H4:H20,"EXPLÍCITO") -> 28
A50: ='Cotação de Materiais'!A28 -> CV-01 | B50: ='Cotação de Materiais'!C28 -> Aplicação de Película Refl. Prata-Bronze 05 | E50: ='Cotação de Materiais'!B28 -> Comunicação Visual | G50: ="R$ "&TEXT('Cotação de Materiais'!H28,"#,##0.00") -> R$ 8,209.46 | J50: DERIVADO | M50: =COUNTIF('Cotação de Materiais'!I4:I44,"DERIVADO")+COUNTIF('Mão de Obra e Serviços'!H4:H20,"DERIVADO") -> 11
A51: ='Cotação de Materiais'!A39 -> FER-04 | B51: ='Cotação de Materiais'!C39 -> Lastros de Estabilização | E51: ='Cotação de Materiais'!B39 -> Ferragens e Ancoragens | G51: ="R$ "&TEXT('Cotação de Materiais'!H39,"#,##0.00") -> R$ 4,800.00 | J51: REFORMADO | M51: =COUNTIF('Cotação de Materiais'!I4:I44,"REFORMADO")+COUNTIF('Mão de Obra e Serviços'!H4:H20,"REFORMADO") -> 5
A52: ='Cotação de Materiais'!A17 -> ELE-04 | B52: ='Cotação de Materiais'!C17 -> Cabos PP Antichama | E52: ='Cotação de Materiais'!B17 -> Elétrica e Iluminação | G52: ="R$ "&TEXT('Cotação de Materiais'!H17,"#,##0.00") -> R$ 3,987.50
A53: ='Cotação de Materiais'!A24 -> TIN-03 | B53: ='Cotação de Materiais'!C24 -> Tinta Acrílica Branca | E53: ='Cotação de Materiais'!B24 -> Pintura e Acabamentos | G53: ="R$ "&TEXT('Cotação de Materiais'!H24,"#,##0.00") -> R$ 3,695.52 | J53: Itens pendentes atuais: MDF 10mm, MDF 6/15mm, tubo S03, perfil LED, QDLF temporário e tapeceiro. Revisar antes do fechamento final.
A54: ='Cotação de Materiais'!A29 -> CV-02 | B54: ='Cotação de Materiais'!C29 -> Remoção de Película Anterior | E54: ='Cotação de Materiais'!B29 -> Comunicação Visual | G54: ="R$ "&TEXT('Cotação de Materiais'!H29,"#,##0.00") -> R$ 3,429.12
A56: Detalhamento: custos item a item na aba “Cotação de Materiais”; mão de obra, serviços e logística na aba “Mão de Obra e Serviços”; cronograma diário na aba “Cronograma Operacional”.

Sheet Cronograma Operacional
A1: CRONOGRAMA OPERACIONAL — COSMOCHÃO | FABRICAÇÃO + MONTAGEM SESC
A3: Planejamento-base: 4 marceneiros no galpão por 5 dias úteis; 8 marceneiros na montagem principal do SESC; 17/11 reservado para entrega técnica.
A5: Código | B5: Fase | C5: Início | D5: Fim | E5: Duração | F5: Equipe principal | G5: Objetivo / observação | H5: 46316 | I5: 46317 | J5: 46318 | K5: 46319 | L5: 46320 | M5: 46321 | N5: 46322 | O5: 46323 | P5: 46324 | Q5: 46325 | R5: 46326 | S5: 46327 | T5: 46328 | U5: 46329 | V5: 46330 | W5: 46331 | X5: 46332 | Y5: 46333 | Z5: 46334 | AA5: 46335 | AB5: 46336 | AC5: 46337 | AD5: 46338 | AE5: 46339 | AF5: 46340 | AG5: 46341 | AH5: 46342 | AI5: 46343 | AJ5: 46344
H6: QUA | I6: QUI | J6: SEX | K6: SÁB | L6: DOM | M6: SEG | N6: TER | O6: QUA | P6: QUI | Q6: SEX | R6: SÁB | S6: DOM | T6: SEG | U6: TER | V6: QUA | W6: QUI | X6: SEX | Y6: SÁB | Z6: DOM | AA6: SEG | AB6: TER | AC6: QUA | AD6: QUI | AE6: SEX | AF6: SÁB | AG6: DOM | AH6: SEG | AI6: TER | AJ6: QUA
A7: GAL-01 | B7: Pré-fabricação em Galpão | C7: 46316 | D7: 46322 | E7: 5 dias úteis | F7: 4 marceneiros | G7: Pré-fabricação, preparação dos módulos e ignifugação antes da entrada no SESC. | H7: ■ | I7: ■ | J7: ■ | M7: ■ | N7: ■
A8: SESC-01 | B8: Entrada + Implantação Pesada | C8: 46323 | D8: 46325 | E8: 3 dias | F8: 8 marc. + 4 ajud. (28–29) + supervisor | G8: Descarga, distribuição, locação e início das estruturas/painéis. | O8: ■ | P8: ■ | Q8: ■
A9: SESC-02 | B9: Montagem Pesada | C9: 46326 | D9: 46331 | E9: 6 dias | F9: 8 marc. + serralheria + supervisor | G9: Painéis, estruturas principais, P05, PR01/PR02 e fechamentos. | R9: ■ | S9: ■ | T9: ■ | U9: ■ | V9: ■ | W9: ■
A10: SESC-03 | B10: Montagem Técnica / Especiais | C10: 46332 | D10: 46336 | E10: 5 dias | F10: 8 marc. + elétrica/serralheria + supervisor | G10: M22, M27, bases especiais, ancoragens e fechamentos técnicos. | X10: ■ | Y10: ■ | Z10: ■ | AA10: ■ | AB10: ■
A11: SESC-04 | B11: Mobiliário + Elétrica + Comunicação | C11: 46337 | D11: 46339 | E11: 3 dias | F11: 8 marc. + eletricista + 2 adesivadores + supervisor | G11: Mobiliário, acessibilidade, LED, eletrofita, insulfilm e vinil. | AC11: ■ | AD11: ■ | AE11: ■
A12: SESC-05 | B12: Acabamentos + Correções | C12: 46340 | D12: 46342 | E12: 3 dias | F12: 8 marc. + pintura + limpeza + supervisor | G12: Retoques, alinhamentos, testes e limpeza progressiva. | AF12: ■ | AG12: ■ | AH12: ■
A13: SESC-06 | B13: Reserva / Entrega Técnica | C13: 46343 | D13: 46343 | E13: 1 dia | F13: Equipe mínima + 3 limpeza | G13: Punch list, correções finais, limpeza fina e liberação. | AI13: ■
A14: MARCO | B14: Abertura ao Público | C14: 46344 | D14: 46344 | E14: Marco | F14: — | G14: Abertura oficial da exposição. | AJ14: ■
A17: MAPA DE EQUIPES E CUSTOS DIRETAMENTE RELACIONADOS À MONTAGEM
A18: Item | B18: Equipe / Função | C18: Quantidade | D18: Unidade | E18: Valor Unitário | F18: Custo Total | G18: Observação
A19: MO-02A | B19: Marceneiros — Galpão | C19: ='Mão de Obra e Serviços'!D5 -> 20 | D19: ='Mão de Obra e Serviços'!E5 -> pessoa-dia | E19: ="R$ "&TEXT('Mão de Obra e Serviços'!F5,"#,##0.00") -> R$ 250.00 | F19: ="R$ "&TEXT('Mão de Obra e Serviços'!G5,"#,##0.00") -> R$ 5,000.00 | G19: 5 dias × 4 pessoas
A20: MO-02B | B20: Marceneiros — SESC | C20: ='Mão de Obra e Serviços'!D6 -> 160 | D20: ='Mão de Obra e Serviços'!E6 -> pessoa-dia | E20: ="R$ "&TEXT('Mão de Obra e Serviços'!F6,"#,##0.00") -> R$ 270.00 | F20: ="R$ "&TEXT('Mão de Obra e Serviços'!G6,"#,##0.00") -> R$ 43,200.00 | G20: 20 dias × 8 pessoas
A21: MO-03 | B21: Ajudantes / carga e descarga | C21: ='Mão de Obra e Serviços'!D7 -> 10 | D21: ='Mão de Obra e Serviços'!E7 -> pessoa-dia | E21: ="R$ "&TEXT('Mão de Obra e Serviços'!F7,"#,##0.00") -> R$ 130.00 | F21: ="R$ "&TEXT('Mão de Obra e Serviços'!G7,"#,##0.00") -> R$ 1,300.00 | G21: 8 p-d na montagem + 4 p-d na desmontagem
A22: MO-04 | B22: Limpeza fina | C22: ='Mão de Obra e Serviços'!D8 -> 9 | D22: ='Mão de Obra e Serviços'!E8 -> pessoa-dia | E22: ="R$ "&TEXT('Mão de Obra e Serviços'!F8,"#,##0.00") -> R$ 100.00 | F22: ="R$ "&TEXT('Mão de Obra e Serviços'!G8,"#,##0.00") -> R$ 900.00 | G22: 3 pessoas × 3 dias
A23: MO-05 | B23: Serralheria — empreita | C23: ='Mão de Obra e Serviços'!D9 -> 1 | D23: ='Mão de Obra e Serviços'!E9 -> cj | E23: ="R$ "&TEXT('Mão de Obra e Serviços'!F9,"#,##0.00") -> R$ 5,000.00 | F23: ="R$ "&TEXT('Mão de Obra e Serviços'!G9,"#,##0.00") -> R$ 5,000.00 | G23: Preço fechado
A24: MO-06 | B24: Supervisor de montagem | C24: ='Mão de Obra e Serviços'!D10 -> 20 | D24: ='Mão de Obra e Serviços'!E10 -> dia | E24: ="R$ "&TEXT('Mão de Obra e Serviços'!F10,"#,##0.00") -> R$ 300.00 | F24: ="R$ "&TEXT('Mão de Obra e Serviços'!G10,"#,##0.00") -> R$ 6,000.00 | G24: 20 dias
A25: MO-07 | B25: Tapeceiro | C25: ='Mão de Obra e Serviços'!D11 -> 5 | D25: ='Mão de Obra e Serviços'!E11 -> pessoa-dia | E25: ="R$ "&TEXT('Mão de Obra e Serviços'!F11,"#,##0.00") -> R$ 1.00 | F25: ="R$ "&TEXT('Mão de Obra e Serviços'!G11,"#,##0.00") -> R$ 5.00 | G25: Quantidade ainda pendente
A26: MO-08 | B26: Adesivadores | C26: ='Mão de Obra e Serviços'!D12 -> 6 | D26: ='Mão de Obra e Serviços'!E12 -> pessoa-dia | E26: ="R$ "&TEXT('Mão de Obra e Serviços'!F12,"#,##0.00") -> R$ 250.00 | F26: ="R$ "&TEXT('Mão de Obra e Serviços'!G12,"#,##0.00") -> R$ 1,500.00 | G26: 2 pessoas × 3 dias
A27: MO-09 | B27: Eletricista — empreita | C27: ='Mão de Obra e Serviços'!D13 -> 1 | D27: ='Mão de Obra e Serviços'!E13 -> cj | E27: ="R$ "&TEXT('Mão de Obra e Serviços'!F13,"#,##0.00") -> R$ 7,000.00 | F27: ="R$ "&TEXT('Mão de Obra e Serviços'!G13,"#,##0.00") -> R$ 7,000.00 | G27: Preço fechado
A29: Premissas do planejamento: o período de 28/10 a 16/11 utiliza os 20 dias corridos previstos para a equipe principal de 8 marceneiros. O dia 17/11 fica preservado como contingência/entrega técnica. A pré-fabricação de 21 a 27/10 considera 5 dias úteis (21, 22, 23, 26 e 27/10). Horários noturnos/restrições operacionais continuam sujeitos ao alinhamento com o SESC.
A33: Fonte operacional: cronograma do projeto + parâmetros de equipe da planilha v12.0. Custos permanecem vinculados às abas-base para atualização automática.
